Workbook

Sheet CIF
C3: Origin Warehouse | N3: Inland Logistics | S3: Consolidation | X3: Outbound Logistics | AB3: Documentation | AH3: CIF | AN3: Cert Costs | AQ3: Terms Total
B4: Region | C4: Terms | D4: Receiving | E4: Load Out | F4: Compression | G4: Class | H4: Marking | I4: Storage | J4: Interest | K4: Origin Commission | L4: Total Equity | M4: Total Origin | N4: Flatbed | O4: Late Fee | P4: Transit Truck | R4: Total Inland | S4: Block Handling | T4: Storage | U4: Interest | W4: Total Consol | X4: Dray | Y4: Ocean | AA4: Total Out | AB4: Sight LC | AC4: Forwarding | AD4: Controlling | AE4: Insurance | AG4: Total Doc | AH4: Destination Comission | AI4: Cost of Funds | AJ4: Qclaim | AM4: Total CIF | AN4: USDA | AO4: ICE | AP4: Total CERT | AQ4: Cash | AR4: Equity
B5: WTX | D5: {=AVERAGE(_xlfn._xlws.FILTER(PTS!I:I, (PTS!$E:$E="WTX") * ISNUMBER(PTS!I:I)))} -> 93.277193 | E5: {=AVERAGE(_xlfn._xlws.FILTER(PTS!J:J, (PTS!$E:$E="WTX") * ISNUMBER(PTS!J:J)))} -> 124.68421 | F5: {=AVERAGE(_xlfn._xlws.FILTER(PTS!K:K, (PTS!$E:$E="WTX") * ISNUMBER(PTS!K:K)))} -> 203.04912 | G5: {=AVERAGE(_xlfn._xlws.FILTER(PTS!L:L, (PTS!$E:$E="WTX") * ISNUMBER(PTS!L:L)))} -> 0 | H5: {=AVERAGE(_xlfn._xlws.FILTER(PTS!M:M, (PTS!$E:$E="WTX") * ISNUMBER(PTS!M:M)))} -> 4.5263158 | I5: {=AVERAGE(_xlfn._xlws.FILTER(PTS!N:N, (PTS!$E:$E="WTX") * ISNUMBER(PTS!N:N)))} -> 54.473684 | J5: {=AVERAGE(_xlfn._xlws.FILTER(PTS!O:O, (PTS!$E:$E="WTX") * ISNUMBER(PTS!O:O)))} -> 37.916667 | K5: {=AVERAGE(_xlfn._xlws.FILTER(PTS!P:P, (PTS!$E:$E="WTX") * ISNUMBER(PTS!P:P)))} -> 0 | L5: {=AVERAGE(_xlfn._xlws.FILTER(PTS!Q:Q, (PTS!$E:$E="WTX") * ISNUMBER(PTS!Q:Q)))} -> 518.74259 | M5: {=AVERAGE(_xlfn._xlws.FILTER(PTS!R:R, (PTS!$E:$E="WTX") * ISNUMBER(PTS!R:R)))} -> 307.52024 | N5: {=AVERAGE(_xlfn._xlws.FILTER(PTS!S:S, (PTS!$E:$E="WTX") * ISNUMBER(PTS!S:S)))} -> 4.9122807 | O5: {=AVERAGE(_xlfn._xlws.FILTER(PTS!T:T, (PTS!$E:$E="WTX") * ISNUMBER(PTS!T:T)))} -> 1.1403509 | P5: {=AVERAGE(_xlfn._xlws.FILTER(PTS!U:U, (PTS!$E:$E="WTX") * ISNUMBER(PTS!U:U)))} -> 186.05615 | R5: {=AVERAGE(_xlfn._xlws.FILTER(PTS!W:W, (PTS!$E:$E="WTX") * ISNUMBER(PTS!W:W)))} -> 192.33066 | S5: {=AVERAGE(_xlfn._xlws.FILTER(PTS!X:X, (PTS!$E:$E="WTX") * ISNUMBER(PTS!X:X)))} -> 54 | T5: {=AVERAGE(_xlfn._xlws.FILTER(PTS!Y:Y, (PTS!$E:$E="WTX") * ISNUMBER(PTS!Y:Y)))} -> 50.4 | U5: {=AVERAGE(_xlfn._xlws.FILTER(PTS!Z:Z, (PTS!$E:$E="WTX") * ISNUMBER(PTS!Z:Z)))} -> 26.25 | W5: {=AVERAGE(_xlfn._xlws.FILTER(PTS!AB:AB, (PTS!$E:$E="WTX") * ISNUMBER(PTS!AB:AB)))} -> 130.65 | X5: {=AVERAGE(_xlfn._xlws.FILTER(PTS!AC:AC, (PTS!$E:$E="WTX") * ISNUMBER(PTS!AC:AC)))} -> 162.5 | Y5: {=AVERAGE(_xlfn._xlws.FILTER(PTS!AD:AD, (PTS!$E:$E="WTX") * ISNUMBER(PTS!AD:AD)))} -> 268.18182 | AA5: {=AVERAGE(_xlfn._xlws.FILTER(PTS!AF:AF, (PTS!$E:$E="WTX") * ISNUMBER(PTS!AF:AF)))} -> 430.68182 | AB5: {=AVERAGE(_xlfn._xlws.FILTER(PTS!AG:AG, (PTS!$E:$E="WTX") * ISNUMBER(PTS!AG:AG)))} -> 28.8143 | AC5: {=AVERAGE(_xlfn._xlws.FILTER(PTS!AH:AH, (PTS!$E:$E="WTX") * ISNUMBER(PTS!AH:AH)))} -> 6.9731405 | AD5: {=AVERAGE(_xlfn._xlws.FILTER(PTS!AI:AI, (PTS!$E:$E="WTX") * ISNUMBER(PTS!AI:AI)))} -> 12.587317 | AE5: {=AVERAGE(_xlfn._xlws.FILTER(PTS!AJ:AJ, (PTS!$E:$E="WTX") * ISNUMBER(PTS!AJ:AJ)))} -> 6.7352 | AG5: {=AVERAGE(_xlfn._xlws.FILTER(PTS!AL:AL, (PTS!$E:$E="WTX") * ISNUMBER(PTS!AL:AL)))} -> 55.109958 | AH5: {=AVERAGE(_xlfn._xlws.FILTER(PTS!AM:AM, (PTS!$E:$E="WTX") * ISNUMBER(PTS!AM:AM)))} -> 80 | AI5: {=AVERAGE(_xlfn._xlws.FILTER(PTS!AN:AN, (PTS!$E:$E="WTX") * ISNUMBER(PTS!AN:AN)))} -> 26.178082 | AJ5: {=AVERAGE(_xlfn._xlws.FILTER(PTS!AO:AO, (PTS!$E:$E="WTX") * ISNUMBER(PTS!AO:AO)))} -> 0 | AM5: {=AVERAGE(_xlfn._xlws.FILTER(PTS!AR:AR, (PTS!$E:$E="WTX") * ISNUMBER(PTS!AR:AR)))} -> 106.17808 | AQ5: =M5+R5+W5+AA5+AG5+AM5 -> 1222.4708 | AR5: =L5+R5+W5+AA5+AG5+AM5 -> 1433.6931
B6: WTXH | D6: {=AVERAGE(_xlfn._xlws.FILTER(PTS!I:I, (PTS!$E:$E="WTXH") * ISNUMBER(PTS!I:I)))} -> 93.845283 | E6: {=AVERAGE(_xlfn._xlws.FILTER(PTS!J:J, (PTS!$E:$E="WTXH") * ISNUMBER(PTS!J:J)))} -> 120.41509 | F6: {=AVERAGE(_xlfn._xlws.FILTER(PTS!K:K, (PTS!$E:$E="WTXH") * ISNUMBER(PTS!K:K)))} -> 206.95849 | G6: {=AVERAGE(_xlfn._xlws.FILTER(PTS!L:L, (PTS!$E:$E="WTXH") * ISNUMBER(PTS!L:L)))} -> 0 | H6: {=AVERAGE(_xlfn._xlws.FILTER(PTS!M:M, (PTS!$E:$E="WTXH") * ISNUMBER(PTS!M:M)))} -> 4.8679245 | I6: {=AVERAGE(_xlfn._xlws.FILTER(PTS!N:N, (PTS!$E:$E="WTXH") * ISNUMBER(PTS!N:N)))} -> 53.622642 | J6: {=AVERAGE(_xlfn._xlws.FILTER(PTS!O:O, (PTS!$E:$E="WTXH") * ISNUMBER(PTS!O:O)))} -> 37.916667 | K6: {=AVERAGE(_xlfn._xlws.FILTER(PTS!P:P, (PTS!$E:$E="WTXH") * ISNUMBER(PTS!P:P)))} -> 0 | L6: {=AVERAGE(_xlfn._xlws.FILTER(PTS!Q:Q, (PTS!$E:$E="WTXH") * ISNUMBER(PTS!Q:Q)))} -> 517.6261 | M6: {=AVERAGE(_xlfn._xlws.FILTER(PTS!R:R, (PTS!$E:$E="WTXH") * ISNUMBER(PTS!R:R)))} -> 308.68205 | N6: {=AVERAGE(_xlfn._xlws.FILTER(PTS!S:S, (PTS!$E:$E="WTXH") * ISNUMBER(PTS!S:S)))} -> 4.5283019 | O6: {=AVERAGE(_xlfn._xlws.FILTER(PTS!T:T, (PTS!$E:$E="WTXH") * ISNUMBER(PTS!T:T)))} -> 1.1320755 | P6: {=AVERAGE(_xlfn._xlws.FILTER(PTS!U:U, (PTS!$E:$E="WTXH") * ISNUMBER(PTS!U:U)))} -> 288.72326 | R6: {=AVERAGE(_xlfn._xlws.FILTER(PTS!W:W, (PTS!$E:$E="WTXH") * ISNUMBER(PTS!W:W)))} -> 294.60561 | S6: {=AVERAGE(_xlfn._xlws.FILTER(PTS!X:X, (PTS!$E:$E="WTXH") * ISNUMBER(PTS!X:X)))} -> 54 | T6: {=AVERAGE(_xlfn._xlws.FILTER(PTS!Y:Y, (PTS!$E:$E="WTXH") * ISNUMBER(PTS!Y:Y)))} -> 50.4 | U6: {=AVERAGE(_xlfn._xlws.FILTER(PTS!Z:Z, (PTS!$E:$E="WTXH") * ISNUMBER(PTS!Z:Z)))} -> 26.25 | W6: {=AVERAGE(_xlfn._xlws.FILTER(PTS!AB:AB, (PTS!$E:$E="WTXH") * ISNUMBER(PTS!AB:AB)))} -> 130.65 | X6: {=AVERAGE(_xlfn._xlws.FILTER(PTS!AC:AC, (PTS!$E:$E="STEX") * ISNUMBER(PTS!AC:AC)))} -> 133.97335 | Y6: {=AVERAGE(_xlfn._xlws.FILTER(PTS!AD:AD, (PTS!$E:$E="WTXH") * ISNUMBER(PTS!AD:AD)))} -> 197.95455 | AA6: {=AVERAGE(_xlfn._xlws.FILTER(PTS!AF:AF, (PTS!$E:$E="WTXH") * ISNUMBER(PTS!AF:AF)))} -> 330.90909 | AB6: {=AVERAGE(_xlfn._xlws.FILTER(PTS!AG:AG, (PTS!$E:$E="WTXH") * ISNUMBER(PTS!AG:AG)))} -> 28.8143 | AC6: {=AVERAGE(_xlfn._xlws.FILTER(PTS!AH:AH, (PTS!$E:$E="WTXH") * ISNUMBER(PTS!AH:AH)))} -> 6.9731405 | AD6: {=AVERAGE(_xlfn._xlws.FILTER(PTS!AI:AI, (PTS!$E:$E="WTXH") * ISNUMBER(PTS!AI:AI)))} -> 12.587317 | AE6: {=AVERAGE(_xlfn._xlws.FILTER(PTS!AJ:AJ, (PTS!$E:$E="WTXH") * ISNUMBER(PTS!AJ:AJ)))} -> 6.7352 | AG6: {=AVERAGE(_xlfn._xlws.FILTER(PTS!AL:AL, (PTS!$E:$E="WTXH") * ISNUMBER(PTS!AL:AL)))} -> 55.109958 | AH6: {=AVERAGE(_xlfn._xlws.FILTER(PTS!AM:AM, (PTS!$E:$E="WTXH") * ISNUMBER(PTS!AM:AM)))} -> 80 | AI6: {=AVERAGE(_xlfn._xlws.FILTER(PTS!AN:AN, (PTS!$E:$E="WTXH") * ISNUMBER(PTS!AN:AN)))} -> 26.178082 | AJ6: {=AVERAGE(_xlfn._xlws.FILTER(PTS!AO:AO, (PTS!$E:$E="WTXH") * ISNUMBER(PTS!AO:AO)))} -> 0 | AM6: {=AVERAGE(_xlfn._xlws.FILTER(PTS!AR:AR, (PTS!$E:$E="WTXH") * ISNUMBER(PTS!AR:AR)))} -> 106.17808 | AQ6: =M6+R6+W6+AA6+AG6+AM6 -> 1226.1348 | AR6: =L6+R6+W6+AA6+AG6+AM6 -> 1435.0788
B7: STEX | D7: {=AVERAGE(_xlfn._xlws.FILTER(PTS!I:I, (PTS!$E:$E="STEX") * ISNUMBER(PTS!I:I)))} -> 94.034483 | E7: {=AVERAGE(_xlfn._xlws.FILTER(PTS!J:J, (PTS!$E:$E="STEX") * ISNUMBER(PTS!J:J)))} -> 203.10345 | F7: {=AVERAGE(_xlfn._xlws.FILTER(PTS!K:K, (PTS!$E:$E="STEX") * ISNUMBER(PTS!K:K)))} -> 136.96552 | G7: {=AVERAGE(_xlfn._xlws.FILTER(PTS!L:L, (PTS!$E:$E="STEX") * ISNUMBER(PTS!L:L)))} -> 2.0689655 | H7: {=AVERAGE(_xlfn._xlws.FILTER(PTS!M:M, (PTS!$E:$E="STEX") * ISNUMBER(PTS!M:M)))} -> 7.1034483 | I7: {=AVERAGE(_xlfn._xlws.FILTER(PTS!N:N, (PTS!$E:$E="STEX") * ISNUMBER(PTS!N:N)))} -> 76.586207 | J7: {=AVERAGE(_xlfn._xlws.FILTER(PTS!O:O, (PTS!$E:$E="STEX") * ISNUMBER(PTS!O:O)))} -> 37.916667 | K7: {=AVERAGE(_xlfn._xlws.FILTER(PTS!P:P, (PTS!$E:$E="STEX") * ISNUMBER(PTS!P:P)))} -> 0 | L7: {=AVERAGE(_xlfn._xlws.FILTER(PTS!Q:Q, (PTS!$E:$E="STEX") * ISNUMBER(PTS!Q:Q)))} -> 557.77874 | M7: {=AVERAGE(_xlfn._xlws.FILTER(PTS!R:R, (PTS!$E:$E="STEX") * ISNUMBER(PTS!R:R)))} -> 452.33046 | N7: {=AVERAGE(_xlfn._xlws.FILTER(PTS!S:S, (PTS!$E:$E="STEX") * ISNUMBER(PTS!S:S)))} -> 4.8275862 | O7: {=AVERAGE(_xlfn._xlws.FILTER(PTS!T:T, (PTS!$E:$E="STEX") * ISNUMBER(PTS!T:T)))} -> 0 | P7: {=AVERAGE(_xlfn._xlws.FILTER(PTS!U:U, (PTS!$E:$E="STEX") * ISNUMBER(PTS!U:U)))} -> 200.75758 | R7: {=AVERAGE(_xlfn._xlws.FILTER(PTS!W:W, (PTS!$E:$E="STEX") * ISNUMBER(PTS!W:W)))} -> 205.94276 | S7: {=AVERAGE(_xlfn._xlws.FILTER(PTS!X:X, (PTS!$E:$E="STEX") * ISNUMBER(PTS!X:X)))} -> 54 | T7: {=AVERAGE(_xlfn._xlws.FILTER(PTS!Y:Y, (PTS!$E:$E="STEX") * ISNUMBER(PTS!Y:Y)))} -> 50.4 | U7: {=AVERAGE(_xlfn._xlws.FILTER(PTS!Z:Z, (PTS!$E:$E="STEX") * ISNUMBER(PTS!Z:Z)))} -> 26.25 | W7: {=AVERAGE(_xlfn._xlws.FILTER(PTS!AB:AB, (PTS!$E:$E="STEX") * ISNUMBER(PTS!AB:AB)))} -> 130.65 | X7: {=AVERAGE(_xlfn._xlws.FILTER(PTS!AC:AC, (PTS!$E:$E="STEX") * ISNUMBER(PTS!AC:AC)))} -> 133.97335 | Y7: {=AVERAGE(_xlfn._xlws.FILTER(PTS!AD:AD, (PTS!$E:$E="STEX") * ISNUMBER(PTS!AD:AD)))} -> 200.37618 | AA7: {=AVERAGE(_xlfn._xlws.FILTER(PTS!AF:AF, (PTS!$E:$E="STEX") * ISNUMBER(PTS!AF:AF)))} -> 334.34953 | AB7: {=AVERAGE(_xlfn._xlws.FILTER(PTS!AG:AG, (PTS!$E:$E="STEX") * ISNUMBER(PTS!AG:AG)))} -> 28.8143 | AC7: {=AVERAGE(_xlfn._xlws.FILTER(PTS!AH:AH, (PTS!$E:$E="STEX") * ISNUMBER(PTS!AH:AH)))} -> 6.9731405 | AD7: {=AVERAGE(_xlfn._xlws.FILTER(PTS!AI:AI, (PTS!$E:$E="STEX") * ISNUMBER(PTS!AI:AI)))} -> 12.587317 | AE7: {=AVERAGE(_xlfn._xlws.FILTER(PTS!AJ:AJ, (PTS!$E:$E="STEX") * ISNUMBER(PTS!AJ:AJ)))} -> 6.7352 | AG7: {=AVERAGE(_xlfn._xlws.FILTER(PTS!AL:AL, (PTS!$E:$E="STEX") * ISNUMBER(PTS!AL:AL)))} -> 55.109958 | AH7: {=AVERAGE(_xlfn._xlws.FILTER(PTS!AM:AM, (PTS!$E:$E="STEX") * ISNUMBER(PTS!AM:AM)))} -> 80 | AI7: {=AVERAGE(_xlfn._xlws.FILTER(PTS!AN:AN, (PTS!$E:$E="STEX") * ISNUMBER(PTS!AN:AN)))} -> 26.178082 | AJ7: {=AVERAGE(_xlfn._xlws.FILTER(PTS!AO:AO, (PTS!$E:$E="STEX") * ISNUMBER(PTS!AO:AO)))} -> 0 | AM7: {=AVERAGE(_xlfn._xlws.FILTER(PTS!AR:AR, (PTS!$E:$E="STEX") * ISNUMBER(PTS!AR:AR)))} -> 106.17808 | AQ7: =M7+R7+W7+AA7+AG7+AM7 -> 1284.5608 | AR7: =L7+R7+W7+AA7+AG7+AM7 -> 1390.0091
B8: Memphis Rule 5 | D8: {=AVERAGE(_xlfn._xlws.FILTER(PTS!I:I, (PTS!$E:$E="Memphis Rule 5") * ISNUMBER(PTS!I:I)))} -> 45.986667 | E8: {=AVERAGE(_xlfn._xlws.FILTER(PTS!J:J, (PTS!$E:$E="Memphis Rule 5") * ISNUMBER(PTS!J:J)))} -> 224.21333 | F8: {=AVERAGE(_xlfn._xlws.FILTER(PTS!K:K, (PTS!$E:$E="Memphis Rule 5") * ISNUMBER(PTS!K:K)))} -> 77.626667 | G8: {=AVERAGE(_xlfn._xlws.FILTER(PTS!L:L, (PTS!$E:$E="Memphis Rule 5") * ISNUMBER(PTS!L:L)))} -> 36.6 | H8: {=AVERAGE(_xlfn._xlws.FILTER(PTS!M:M, (PTS!$E:$E="Memphis Rule 5") * ISNUMBER(PTS!M:M)))} -> 3.8933333 | I8: {=AVERAGE(_xlfn._xlws.FILTER(PTS!N:N, (PTS!$E:$E="Memphis Rule 5") * ISNUMBER(PTS!N:N)))} -> 68.733333 | J8: {=AVERAGE(_xlfn._xlws.FILTER(PTS!O:O, (PTS!$E:$E="Memphis Rule 5") * ISNUMBER(PTS!O:O)))} -> 37.916667 | K8: {=AVERAGE(_xlfn._xlws.FILTER(PTS!P:P, (PTS!$E:$E="Memphis Rule 5") * ISNUMBER(PTS!P:P)))} -> 0 | L8: {=AVERAGE(_xlfn._xlws.FILTER(PTS!Q:Q, (PTS!$E:$E="Memphis Rule 5") * ISNUMBER(PTS!Q:Q)))} -> 494.97 | M8: {=AVERAGE(_xlfn._xlws.FILTER(PTS!R:R, (PTS!$E:$E="Memphis Rule 5") * ISNUMBER(PTS!R:R)))} -> 106.65 | N8: {=AVERAGE(_xlfn._xlws.FILTER(PTS!S:S, (PTS!$E:$E="Memphis Rule 5") * ISNUMBER(PTS!S:S)))} -> 0.26666667 | O8: {=AVERAGE(_xlfn._xlws.FILTER(PTS!T:T, (PTS!$E:$E="Memphis Rule 5") * ISNUMBER(PTS!T:T)))} -> 0.73333333 | P8: {=AVERAGE(_xlfn._xlws.FILTER(PTS!U:U, (PTS!$E:$E="Memphis Rule 5") * ISNUMBER(PTS!U:U)))} -> 211.56873 | R8: {=AVERAGE(_xlfn._xlws.FILTER(PTS!W:W, (PTS!$E:$E="Memphis Rule 5") * ISNUMBER(PTS!W:W)))} -> 212.56873 | S8: {=AVERAGE(_xlfn._xlws.FILTER(PTS!X:X, (PTS!$E:$E="Memphis Rule 5") * ISNUMBER(PTS!X:X)))} -> 50.48 | T8: {=AVERAGE(_xlfn._xlws.FILTER(PTS!Y:Y, (PTS!$E:$E="Memphis Rule 5") * ISNUMBER(PTS!Y:Y)))} -> 35.616 | U8: {=AVERAGE(_xlfn._xlws.FILTER(PTS!Z:Z, (PTS!$E:$E="Memphis Rule 5") * ISNUMBER(PTS!Z:Z)))} -> 26.25 | W8: {=AVERAGE(_xlfn._xlws.FILTER(PTS!AB:AB, (PTS!$E:$E="Memphis Rule 5") * ISNUMBER(PTS!AB:AB)))} -> 112.346 | X8: {=AVERAGE(_xlfn._xlws.FILTER(PTS!AC:AC, (PTS!$E:$E="Memphis Rule 5") * ISNUMBER(PTS!AC:AC)))} -> 144.45455 | Y8: {=AVERAGE(_xlfn._xlws.FILTER(PTS!AD:AD, (PTS!$G:$G="Memphis") * ISNUMBER(PTS!AD:AD)))} -> 182.72727 | AA8: {=AVERAGE(_xlfn._xlws.FILTER(PTS!AF:AF, (PTS!$G:$G="Memphis") * ISNUMBER(PTS!AF:AF)))} -> 328.75 | AB8: {=AVERAGE(_xlfn._xlws.FILTER(PTS!AG:AG, (PTS!$E:$E="Memphis Rule 5") * ISNUMBER(PTS!AG:AG)))} -> 28.8143 | AC8: {=AVERAGE(_xlfn._xlws.FILTER(PTS!AH:AH, (PTS!$E:$E="Memphis Rule 5") * ISNUMBER(PTS!AH:AH)))} -> 6.9731405 | AD8: {=AVERAGE(_xlfn._xlws.FILTER(PTS!AI:AI, (PTS!$E:$E="Memphis Rule 5") * ISNUMBER(PTS!AI:AI)))} -> 12.587317 | AE8: {=AVERAGE(_xlfn._xlws.FILTER(PTS!AJ:AJ, (PTS!$E:$E="Memphis Rule 5") * ISNUMBER(PTS!AJ:AJ)))} -> 6.7352 | AG8: {=AVERAGE(_xlfn._xlws.FILTER(PTS!AL:AL, (PTS!$E:$E="Memphis Rule 5") * ISNUMBER(PTS!AL:AL)))} -> 55.109958 | AH8: {=AVERAGE(_xlfn._xlws.FILTER(PTS!AM:AM, (PTS!$E:$E="Memphis Rule 5") * ISNUMBER(PTS!AM:AM)))} -> 80 | AI8: {=AVERAGE(_xlfn._xlws.FILTER(PTS!AN:AN, (PTS!$E:$E="Memphis Rule 5") * ISNUMBER(PTS!AN:AN)))} -> 26.178082 | AJ8: {=AVERAGE(_xlfn._xlws.FILTER(PTS!AO:AO, (PTS!$E:$E="Memphis Rule 5") * ISNUMBER(PTS!AO:AO)))} -> 0 | AM8: {=AVERAGE(_xlfn._xlws.FILTER(PTS!AR:AR, (PTS!$E:$E="Memphis Rule 5") * ISNUMBER(PTS!AR:AR)))} -> 106.17808 | AQ8: =M8+R8+W8+AA8+AG8+AM8 -> 921.60277 | AR8: =L8+R8+W8+AA8+AG8+AM8 -> 1309.9228
B9: GA 30 Day | D9: {=AVERAGE(_xlfn._xlws.FILTER(PTS!I:I, (PTS!$E:$E="Memphis Rule 5") * ISNUMBER(PTS!I:I)))} -> 45.986667 | E9: {=AVERAGE(_xlfn._xlws.FILTER(PTS!J:J, (PTS!$E:$E="GA 30 Day") * ISNUMBER(PTS!J:J)))} -> 88.478261 | F9: {=AVERAGE(_xlfn._xlws.FILTER(PTS!K:K, (PTS!$E:$E="GA 30 Day") * ISNUMBER(PTS!K:K)))} -> 18.84058 | G9: {=AVERAGE(_xlfn._xlws.FILTER(PTS!L:L, (PTS!$E:$E="GA 30 Day") * ISNUMBER(PTS!L:L)))} -> 1.7681159 | H9: {=AVERAGE(_xlfn._xlws.FILTER(PTS!M:M, (PTS!$E:$E="GA 30 Day") * ISNUMBER(PTS!M:M)))} -> 12.782609 | I9: {=AVERAGE(_xlfn._xlws.FILTER(PTS!N:N, (PTS!$E:$E="GA 30 Day") * ISNUMBER(PTS!N:N)))} -> 57.318841 | J9: {=AVERAGE(_xlfn._xlws.FILTER(PTS!O:O, (PTS!$E:$E="GA 30 Day") * ISNUMBER(PTS!O:O)))} -> 37.916667 | K9: {=AVERAGE(_xlfn._xlws.FILTER(PTS!P:P, (PTS!$E:$E="GA 30 Day") * ISNUMBER(PTS!P:P)))} -> 0 | L9: {=AVERAGE(_xlfn._xlws.FILTER(PTS!Q:Q, (PTS!$E:$E="GA 30 Day") * ISNUMBER(PTS!Q:Q)))} -> 276.61232 | M9: {=AVERAGE(_xlfn._xlws.FILTER(PTS!R:R, (PTS!$E:$E="GA 30 Day") * ISNUMBER(PTS!R:R)))} -> 41.307971 | N9: {=AVERAGE(_xlfn._xlws.FILTER(PTS!S:S, (PTS!$E:$E="GA 30 Day") * ISNUMBER(PTS!S:S)))} -> 0 | O9: {=AVERAGE(_xlfn._xlws.FILTER(PTS!T:T, (PTS!$E:$E="GA 30 Day") * ISNUMBER(PTS!T:T)))} -> 0.82345191 | P9: {=AVERAGE(_xlfn._xlws.FILTER(PTS!U:U, (PTS!$E:$E="GA 30 Day") * ISNUMBER(PTS!U:U)))} -> 203.95335 | R9: {=AVERAGE(_xlfn._xlws.FILTER(PTS!W:W, (PTS!$E:$E="GA 30 Day") * ISNUMBER(PTS!W:W)))} -> 204.78891 | S9: {=AVERAGE(_xlfn._xlws.FILTER(PTS!X:X, (PTS!$E:$E="GA 30 Day") * ISNUMBER(PTS!X:X)))} -> 52 | T9: {=AVERAGE(_xlfn._xlws.FILTER(PTS!Y:Y, (PTS!$E:$E="GA 30 Day") * ISNUMBER(PTS!Y:Y)))} -> 50.4 | U9: {=AVERAGE(_xlfn._xlws.FILTER(PTS!Z:Z, (PTS!$E:$E="GA 30 Day") * ISNUMBER(PTS!Z:Z)))} -> 26.25 | W9: {=AVERAGE(_xlfn._xlws.FILTER(PTS!AB:AB, (PTS!$E:$E="GA 30 Day") * ISNUMBER(PTS!AB:AB)))} -> 128.65 | X9: {=AVERAGE(_xlfn._xlws.FILTER(PTS!AC:AC, (PTS!$E:$E="GA 30 Day") * ISNUMBER(PTS!AC:AC)))} -> 110.22727 | Y9: {=AVERAGE(_xlfn._xlws.FILTER(PTS!AD:AD, (PTS!$E:$E="GA 30 Day") * ISNUMBER(PTS!AD:AD)))} -> 107.04545 | AA9: {=AVERAGE(_xlfn._xlws.FILTER(PTS!AF:AF, (PTS!$E:$E="GA 30 Day") * ISNUMBER(PTS!AF:AF)))} -> 217.27273 | AB9: {=AVERAGE(_xlfn._xlws.FILTER(PTS!AG:AG, (PTS!$E:$E="GA 30 Day") * ISNUMBER(PTS!AG:AG)))} -> 28.8143 | AC9: {=AVERAGE(_xlfn._xlws.FILTER(PTS!AH:AH, (PTS!$E:$E="GA 30 Day") * ISNUMBER(PTS!AH:AH)))} -> 6.9731405 | AD9: {=AVERAGE(_xlfn._xlws.FILTER(PTS!AI:AI, (PTS!$E:$E="GA 30 Day") * ISNUMBER(PTS!AI:AI)))} -> 12.587317 | AE9: {=AVERAGE(_xlfn._xlws.FILTER(PTS!AJ:AJ, (PTS!$E:$E="GA 30 Day") * ISNUMBER(PTS!AJ:AJ)))} -> 6.7352 | AG9: {=AVERAGE(_xlfn._xlws.FILTER(PTS!AL:AL, (PTS!$E:$E="GA 30 Day") * ISNUMBER(PTS!AL:AL)))} -> 55.109958 | AH9: {=AVERAGE(_xlfn._xlws.FILTER(PTS!AM:AM, (PTS!$E:$E="GA 30 Day") * ISNUMBER(PTS!AM:AM)))} -> 80 | AI9: {=AVERAGE(_xlfn._xlws.FILTER(PTS!AN:AN, (PTS!$E:$E="GA 30 Day") * ISNUMBER(PTS!AN:AN)))} -> 26.178082 | AJ9: {=AVERAGE(_xlfn._xlws.FILTER(PTS!AO:AO, (PTS!$E:$E="GA 30 Day") * ISNUMBER(PTS!AO:AO)))} -> 0 | AM9: {=AVERAGE(_xlfn._xlws.FILTER(PTS!AR:AR, (PTS!$E:$E="GA 30 Day") * ISNUMBER(PTS!AR:AR)))} -> 106.17808 | AQ9: =M9+R9+W9+AA9+AG9+AM9 -> 753.30765 | AR9: =L9+R9+W9+AA9+AG9+AM9 -> 988.612
B10: Eastern Rule 5 | D10: {=AVERAGE(_xlfn._xlws.FILTER(PTS!I:I, (PTS!$E:$E="Eastern Rule 5") * ISNUMBER(PTS!I:I)))} -> 66.135802 | E10: {=AVERAGE(_xlfn._xlws.FILTER(PTS!J:J, (PTS!$E:$E="Eastern Rule 5") * ISNUMBER(PTS!J:J)))} -> 92.407407 | F10: {=AVERAGE(_xlfn._xlws.FILTER(PTS!K:K, (PTS!$E:$E="Eastern Rule 5") * ISNUMBER(PTS!K:K)))} -> 20.617284 | G10: {=AVERAGE(_xlfn._xlws.FILTER(PTS!L:L, (PTS!$E:$E="Eastern Rule 5") * ISNUMBER(PTS!L:L)))} -> 2.5308642 | H10: {=AVERAGE(_xlfn._xlws.FILTER(PTS!M:M, (PTS!$E:$E="Eastern Rule 5") * ISNUMBER(PTS!M:M)))} -> 9.617284 | I10: {=AVERAGE(_xlfn._xlws.FILTER(PTS!N:N, (PTS!$E:$E="Eastern Rule 5") * ISNUMBER(PTS!N:N)))} -> 48.120988 | J10: {=AVERAGE(_xlfn._xlws.FILTER(PTS!O:O, (PTS!$E:$E="Eastern Rule 5") * ISNUMBER(PTS!O:O)))} -> 37.916667 | K10: {=AVERAGE(_xlfn._xlws.FILTER(PTS!P:P, (PTS!$E:$E="Eastern Rule 5") * ISNUMBER(PTS!P:P)))} -> 0 | L10: {=AVERAGE(_xlfn._xlws.FILTER(PTS!Q:Q, (PTS!$E:$E="Eastern Rule 5") * ISNUMBER(PTS!Q:Q)))} -> 277.3463 | M10: {=AVERAGE(_xlfn._xlws.FILTER(PTS!R:R, (PTS!$E:$E="Eastern Rule 5") * ISNUMBER(PTS!R:R)))} -> 86.037654 | N10: {=AVERAGE(_xlfn._xlws.FILTER(PTS!S:S, (PTS!$E:$E="Eastern Rule 5") * ISNUMBER(PTS!S:S)))} -> 0 | O10: {=AVERAGE(_xlfn._xlws.FILTER(PTS!T:T, (PTS!$E:$E="Eastern Rule 5") * ISNUMBER(PTS!T:T)))} -> 0 | P10: {=AVERAGE(_xlfn._xlws.FILTER(PTS!U:U, (PTS!$E:$E="Eastern Rule 5") * ISNUMBER(PTS!U:U)))} -> 271.21305 | R10: {=AVERAGE(_xlfn._xlws.FILTER(PTS!W:W, (PTS!$G:$G="Savannah") * ISNUMBER(PTS!W:W)))} -> 241.12586 | S10: {=AVERAGE(_xlfn._xlws.FILTER(PTS!X:X, (PTS!$E:$E="Eastern Rule 5") * ISNUMBER(PTS!X:X)))} -> 51.802469 | T10: {=AVERAGE(_xlfn._xlws.FILTER(PTS!Y:Y, (PTS!$G:$G="Savannah") * ISNUMBER(PTS!Y:Y)))} -> 50.4 | U10: {=AVERAGE(_xlfn._xlws.FILTER(PTS!Z:Z, (PTS!$E:$E="Eastern Rule 5") * ISNUMBER(PTS!Z:Z)))} -> 26.25 | W10: {=AVERAGE(_xlfn._xlws.FILTER(PTS!AB:AB, (PTS!$E:$E="Eastern Rule 5") * ISNUMBER(PTS!AB:AB)))} -> 126.79321 | X10: {=AVERAGE(_xlfn._xlws.FILTER(PTS!AC:AC, (PTS!$E:$E="Eastern Rule 5") * ISNUMBER(PTS!AC:AC)))} -> 113.76263 | Y10: {=AVERAGE(_xlfn._xlws.FILTER(PTS!AD:AD, (PTS!$E:$E="Eastern Rule 5") * ISNUMBER(PTS!AD:AD)))} -> 114.5202 | AA10: {=AVERAGE(_xlfn._xlws.FILTER(PTS!AF:AF, (PTS!$E:$E="Eastern Rule 5") * ISNUMBER(PTS!AF:AF)))} -> 228.28283 | AB10: {=AVERAGE(_xlfn._xlws.FILTER(PTS!AG:AG, (PTS!$E:$E="Eastern Rule 5") * ISNUMBER(PTS!AG:AG)))} -> 28.8143 | AC10: {=AVERAGE(_xlfn._xlws.FILTER(PTS!AH:AH, (PTS!$E:$E="Eastern Rule 5") * ISNUMBER(PTS!AH:AH)))} -> 6.9731405 | AD10: {=AVERAGE(_xlfn._xlws.FILTER(PTS!AI:AI, (PTS!$E:$E="Eastern Rule 5") * ISNUMBER(PTS!AI:AI)))} -> 12.587317 | AE10: {=AVERAGE(_xlfn._xlws.FILTER(PTS!AJ:AJ, (PTS!$E:$E="Eastern Rule 5") * ISNUMBER(PTS!AJ:AJ)))} -> 6.7352 | AG10: {=AVERAGE(_xlfn._xlws.FILTER(PTS!AL:AL, (PTS!$E:$E="Eastern Rule 5") * ISNUMBER(PTS!AL:AL)))} -> 55.109958 | AH10: {=AVERAGE(_xlfn._xlws.FILTER(PTS!AM:AM, (PTS!$E:$E="Eastern Rule 5") * ISNUMBER(PTS!AM:AM)))} -> 80 | AI10: {=AVERAGE(_xlfn._xlws.FILTER(PTS!AN:AN, (PTS!$E:$E="Eastern Rule 5") * ISNUMBER(PTS!AN:AN)))} -> 26.178082 | AJ10: {=AVERAGE(_xlfn._xlws.FILTER(PTS!AO:AO, (PTS!$E:$E="Eastern Rule 5") * ISNUMBER(PTS!AO:AO)))} -> 0 | AM10: {=AVERAGE(_xlfn._xlws.FILTER(PTS!AR:AR, (PTS!$E:$E="Eastern Rule 5") * ISNUMBER(PTS!AR:AR)))} -> 106.17808 | AQ10: =M10+R10+W10+AA10+AG10+AM10 -> 843.52759 | AR10: =L10+R10+W10+AA10+AG10+AM10 -> 1034.8362
B11: WTEX Equity | D11: {=AVERAGE(_xlfn._xlws.FILTER(PTS!I:I, (PTS!$E:$E="WTX") * ISNUMBER(PTS!I:I)))} -> 93.277193 | E11: {=AVERAGE(_xlfn._xlws.FILTER(PTS!J:J, (PTS!$E:$E="WTX") * ISNUMBER(PTS!J:J)))} -> 124.68421 | F11: {=AVERAGE(_xlfn._xlws.FILTER(PTS!K:K, (PTS!$E:$E="WTX") * ISNUMBER(PTS!K:K)))} -> 203.04912 | G11: {=AVERAGE(_xlfn._xlws.FILTER(PTS!L:L, (PTS!$E:$E="WTX") * ISNUMBER(PTS!L:L)))} -> 0 | H11: {=AVERAGE(_xlfn._xlws.FILTER(PTS!M:M, (PTS!$E:$E="WTX") * ISNUMBER(PTS!M:M)))} -> 4.5263158 | I11: {=AVERAGE(_xlfn._xlws.FILTER(PTS!N:N, (PTS!$E:$E="WTX") * ISNUMBER(PTS!N:N)))} -> 54.473684 | J11: {=AVERAGE(_xlfn._xlws.FILTER(PTS!O:O, (PTS!$E:$E="WTX") * ISNUMBER(PTS!O:O)))} -> 37.916667 | K11: {=AVERAGE(_xlfn._xlws.FILTER(PTS!P:P, (PTS!$E:$E="WTX") * ISNUMBER(PTS!P:P)))} -> 0 | L11: {=AVERAGE(_xlfn._xlws.FILTER(PTS!Q:Q, (PTS!$E:$E="WTX") * ISNUMBER(PTS!Q:Q)))} -> 518.74259 | M11: {=AVERAGE(_xlfn._xlws.FILTER(PTS!R:R, (PTS!$E:$E="WTX") * ISNUMBER(PTS!R:R)))} -> 307.52024 | N11: {=AVERAGE(_xlfn._xlws.FILTER(PTS!S:S, (PTS!$E:$E="WTX") * ISNUMBER(PTS!S:S)))} -> 4.9122807 | O11: {=AVERAGE(_xlfn._xlws.FILTER(PTS!T:T, (PTS!$E:$E="WTX") * ISNUMBER(PTS!T:T)))} -> 1.1403509 | P11: {=AVERAGE(_xlfn._xlws.FILTER(PTS!U:U, (PTS!$E:$E="WTX") * ISNUMBER(PTS!U:U)))} -> 186.05615 | R11: {=AVERAGE(_xlfn._xlws.FILTER(PTS!W:W, (PTS!$E:$E="WTX") * ISNUMBER(PTS!W:W)))} -> 192.33066 | S11: {=AVERAGE(_xlfn._xlws.FILTER(PTS!X:X, (PTS!$E:$E="WTX") * ISNUMBER(PTS!X:X)))} -> 54 | T11: {=AVERAGE(_xlfn._xlws.FILTER(PTS!Y:Y, (PTS!$E:$E="WTX") * ISNUMBER(PTS!Y:Y)))} -> 50.4 | U11: {=AVERAGE(_xlfn._xlws.FILTER(PTS!Z:Z, (PTS!$E:$E="WTX") * ISNUMBER(PTS!Z:Z)))} -> 26.25 | W11: {=AVERAGE(_xlfn._xlws.FILTER(PTS!AB:AB, (PTS!$E:$E="WTX") * ISNUMBER(PTS!AB:AB)))} -> 130.65 | X11: {=AVERAGE(_xlfn._xlws.FILTER(PTS!AC:AC, (PTS!$E:$E="WTX") * ISNUMBER(PTS!AC:AC)))} -> 162.5 | Y11: {=AVERAGE(_xlfn._xlws.FILTER(PTS!AD:AD, (PTS!$E:$E="WTX") * ISNUMBER(PTS!AD:AD)))} -> 268.18182 | AA11: {=AVERAGE(_xlfn._xlws.FILTER(PTS!AF:AF, (PTS!$E:$E="WTX") * ISNUMBER(PTS!AF:AF)))} -> 430.68182 | AB11: {=AVERAGE(_xlfn._xlws.FILTER(PTS!AG:AG, (PTS!$E:$E="WTX") * ISNUMBER(PTS!AG:AG)))} -> 28.8143 | AC11: {=AVERAGE(_xlfn._xlws.FILTER(PTS!AH:AH, (PTS!$E:$E="WTX") * ISNUMBER(PTS!AH:AH)))} -> 6.9731405 | AD11: {=AVERAGE(_xlfn._xlws.FILTER(PTS!AI:AI, (PTS!$E:$E="WTX") * ISNUMBER(PTS!AI:AI)))} -> 12.587317 | AE11: {=AVERAGE(_xlfn._xlws.FILTER(PTS!AJ:AJ, (PTS!$E:$E="WTX") * ISNUMBER(PTS!AJ:AJ)))} -> 6.7352 | AG11: {=AVERAGE(_xlfn._xlws.FILTER(PTS!AL:AL, (PTS!$E:$E="WTX") * ISNUMBER(PTS!AL:AL)))} -> 55.109958 | AH11: {=AVERAGE(_xlfn._xlws.FILTER(PTS!AM:AM, (PTS!$E:$E="WTX") * ISNUMBER(PTS!AM:AM)))} -> 80 | AI11: {=AVERAGE(_xlfn._xlws.FILTER(PTS!AN:AN, (PTS!$E:$E="WTX") * ISNUMBER(PTS!AN:AN)))} -> 26.178082 | AJ11: {=AVERAGE(_xlfn._xlws.FILTER(PTS!AO:AO, (PTS!$E:$E="WTX") * ISNUMBER(PTS!AO:AO)))} -> 0 | AM11: {=AVERAGE(_xlfn._xlws.FILTER(PTS!AR:AR, (PTS!$E:$E="WTX") * ISNUMBER(PTS!AR:AR)))} -> 106.17808 | AQ11: =M11+R11+W11+AA11+AG11+AM11 -> 1222.4708 | AR11: =L11+R11+W11+AA11+AG11+AM11 -> 1433.6931
B12: STEX Equity | D12: {=AVERAGE(_xlfn._xlws.FILTER(PTS!I:I, (PTS!$E:$E="STEX") * ISNUMBER(PTS!I:I)))} -> 94.034483 | E12: {=AVERAGE(_xlfn._xlws.FILTER(PTS!J:J, (PTS!$E:$E="STEX") * ISNUMBER(PTS!J:J)))} -> 203.10345 | F12: {=AVERAGE(_xlfn._xlws.FILTER(PTS!K:K, (PTS!$E:$E="STEX") * ISNUMBER(PTS!K:K)))} -> 136.96552 | G12: {=AVERAGE(_xlfn._xlws.FILTER(PTS!L:L, (PTS!$E:$E="STEX") * ISNUMBER(PTS!L:L)))} -> 2.0689655 | H12: {=AVERAGE(_xlfn._xlws.FILTER(PTS!M:M, (PTS!$E:$E="STEX") * ISNUMBER(PTS!M:M)))} -> 7.1034483 | I12: {=AVERAGE(_xlfn._xlws.FILTER(PTS!N:N, (PTS!$E:$E="STEX") * ISNUMBER(PTS!N:N)))} -> 76.586207 | J12: {=AVERAGE(_xlfn._xlws.FILTER(PTS!O:O, (PTS!$E:$E="STEX") * ISNUMBER(PTS!O:O)))} -> 37.916667 | K12: {=AVERAGE(_xlfn._xlws.FILTER(PTS!P:P, (PTS!$E:$E="STEX") * ISNUMBER(PTS!P:P)))} -> 0 | L12: {=AVERAGE(_xlfn._xlws.FILTER(PTS!Q:Q, (PTS!$E:$E="STEX") * ISNUMBER(PTS!Q:Q)))} -> 557.77874 | M12: {=AVERAGE(_xlfn._xlws.FILTER(PTS!R:R, (PTS!$E:$E="STEX") * ISNUMBER(PTS!R:R)))} -> 452.33046 | N12: {=AVERAGE(_xlfn._xlws.FILTER(PTS!S:S, (PTS!$E:$E="STEX") * ISNUMBER(PTS!S:S)))} -> 4.8275862 | O12: {=AVERAGE(_xlfn._xlws.FILTER(PTS!T:T, (PTS!$E:$E="STEX") * ISNUMBER(PTS!T:T)))} -> 0 | P12: {=AVERAGE(_xlfn._xlws.FILTER(PTS!U:U, (PTS!$E:$E="STEX") * ISNUMBER(PTS!U:U)))} -> 200.75758 | R12: {=AVERAGE(_xlfn._xlws.FILTER(PTS!W:W, (PTS!$E:$E="STEX") * ISNUMBER(PTS!W:W)))} -> 205.94276 | S12: {=AVERAGE(_xlfn._xlws.FILTER(PTS!X:X, (PTS!$E:$E="STEX") * ISNUMBER(PTS!X:X)))} -> 54 | T12: {=AVERAGE(_xlfn._xlws.FILTER(PTS!Y:Y, (PTS!$E:$E="STEX") * ISNUMBER(PTS!Y:Y)))} -> 50.4 | U12: {=AVERAGE(_xlfn._xlws.FILTER(PTS!Z:Z, (PTS!$E:$E="STEX") * ISNUMBER(PTS!Z:Z)))} -> 26.25 | W12: {=AVERAGE(_xlfn._xlws.FILTER(PTS!AB:AB, (PTS!$E:$E="STEX") * ISNUMBER(PTS!AB:AB)))} -> 130.65 | X12: {=AVERAGE(_xlfn._xlws.FILTER(PTS!AC:AC, (PTS!$E:$E="STEX") * ISNUMBER(PTS!AC:AC)))} -> 133.97335 | Y12: {=AVERAGE(_xlfn._xlws.FILTER(PTS!AD:AD, (PTS!$E:$E="STEX") * ISNUMBER(PTS!AD:AD)))} -> 200.37618 | AA12: {=AVERAGE(_xlfn._xlws.FILTER(PTS!AF:AF, (PTS!$E:$E="STEX") * ISNUMBER(PTS!AF:AF)))} -> 334.34953 | AB12: {=AVERAGE(_xlfn._xlws.FILTER(PTS!AG:AG, (PTS!$E:$E="STEX") * ISNUMBER(PTS!AG:AG)))} -> 28.8143 | AC12: {=AVERAGE(_xlfn._xlws.FILTER(PTS!AH:AH, (PTS!$E:$E="STEX") * ISNUMBER(PTS!AH:AH)))} -> 6.9731405 | AD12: {=AVERAGE(_xlfn._xlws.FILTER(PTS!AI:AI, (PTS!$E:$E="STEX") * ISNUMBER(PTS!AI:AI)))} -> 12.587317 | AE12: {=AVERAGE(_xlfn._xlws.FILTER(PTS!AJ:AJ, (PTS!$E:$E="STEX") * ISNUMBER(PTS!AJ:AJ)))} -> 6.7352 | AG12: {=AVERAGE(_xlfn._xlws.FILTER(PTS!AL:AL, (PTS!$E:$E="STEX") * ISNUMBER(PTS!AL:AL)))} -> 55.109958 | AH12: {=AVERAGE(_xlfn._xlws.FILTER(PTS!AM:AM, (PTS!$E:$E="STEX") * ISNUMBER(PTS!AM:AM)))} -> 80 | AI12: {=AVERAGE(_xlfn._xlws.FILTER(PTS!AN:AN, (PTS!$E:$E="STEX") * ISNUMBER(PTS!AN:AN)))} -> 26.178082 | AJ12: {=AVERAGE(_xlfn._xlws.FILTER(PTS!AO:AO, (PTS!$E:$E="STEX") * ISNUMBER(PTS!AO:AO)))} -> 0 | AM12: {=AVERAGE(_xlfn._xlws.FILTER(PTS!AR:AR, (PTS!$E:$E="STEX") * ISNUMBER(PTS!AR:AR)))} -> 106.17808 | AQ12: =M12+R12+W12+AA12+AG12+AM12 -> 1284.5608 | AR12: =L12+R12+W12+AA12+AG12+AM12 -> 1390.0091
B13: Memphis Equity | D13: {=AVERAGE(_xlfn._xlws.FILTER(PTS!I:I, (PTS!$E:$E="STEX") * ISNUMBER(PTS!I:I)))} -> 94.034483 | E13: {=AVERAGE(_xlfn._xlws.FILTER(PTS!J:J, (PTS!$E:$E="Memphis Rule 5") * ISNUMBER(PTS!J:J)))} -> 224.21333 | F13: {=AVERAGE(_xlfn._xlws.FILTER(PTS!K:K, (PTS!$E:$E="Memphis Rule 5") * ISNUMBER(PTS!K:K)))} -> 77.626667 | G13: {=AVERAGE(_xlfn._xlws.FILTER(PTS!L:L, (PTS!$E:$E="Memphis Rule 5") * ISNUMBER(PTS!L:L)))} -> 36.6 | H13: {=AVERAGE(_xlfn._xlws.FILTER(PTS!M:M, (PTS!$E:$E="Memphis Rule 5") * ISNUMBER(PTS!M:M)))} -> 3.8933333 | I13: {=AVERAGE(_xlfn._xlws.FILTER(PTS!N:N, (PTS!$E:$E="Memphis Rule 5") * ISNUMBER(PTS!N:N)))} -> 68.733333 | J13: {=AVERAGE(_xlfn._xlws.FILTER(PTS!O:O, (PTS!$E:$E="Memphis Rule 5") * ISNUMBER(PTS!O:O)))} -> 37.916667 | K13: {=AVERAGE(_xlfn._xlws.FILTER(PTS!P:P, (PTS!$E:$E="Memphis Rule 5") * ISNUMBER(PTS!P:P)))} -> 0 | L13: {=AVERAGE(_xlfn._xlws.FILTER(PTS!Q:Q, (PTS!$E:$E="Memphis Rule 5") * ISNUMBER(PTS!Q:Q)))} -> 494.97 | M13: {=AVERAGE(_xlfn._xlws.FILTER(PTS!R:R, (PTS!$E:$E="Memphis Rule 5") * ISNUMBER(PTS!R:R)))} -> 106.65 | N13: {=AVERAGE(_xlfn._xlws.FILTER(PTS!S:S, (PTS!$E:$E="Memphis Rule 5") * ISNUMBER(PTS!S:S)))} -> 0.26666667 | O13: {=AVERAGE(_xlfn._xlws.FILTER(PTS!T:T, (PTS!$E:$E="Memphis Rule 5") * ISNUMBER(PTS!T:T)))} -> 0.73333333 | P13: {=AVERAGE(_xlfn._xlws.FILTER(PTS!U:U, (PTS!$E:$E="Memphis Rule 5") * ISNUMBER(PTS!U:U)))} -> 211.56873 | R13: {=AVERAGE(_xlfn._xlws.FILTER(PTS!W:W, (PTS!$E:$E="Memphis Rule 5") * ISNUMBER(PTS!W:W)))} -> 212.56873 | S13: {=AVERAGE(_xlfn._xlws.FILTER(PTS!X:X, (PTS!$E:$E="Memphis Rule 5") * ISNUMBER(PTS!X:X)))} -> 50.48 | T13: {=AVERAGE(_xlfn._xlws.FILTER(PTS!Y:Y, (PTS!$E:$E="Memphis Rule 5") * ISNUMBER(PTS!Y:Y)))} -> 35.616 | U13: {=AVERAGE(_xlfn._xlws.FILTER(PTS!Z:Z, (PTS!$E:$E="Memphis Rule 5") * ISNUMBER(PTS!Z:Z)))} -> 26.25 | W13: {=AVERAGE(_xlfn._xlws.FILTER(PTS!AB:AB, (PTS!$E:$E="Memphis Rule 5") * ISNUMBER(PTS!AB:AB)))} -> 112.346 | X13: {=AVERAGE(_xlfn._xlws.FILTER(PTS!AC:AC, (PTS!$E:$E="Memphis Rule 5") * ISNUMBER(PTS!AC:AC)))} -> 144.45455 | Y13: {=AVERAGE(_xlfn._xlws.FILTER(PTS!AD:AD, (PTS!$E:$E="Memphis Rule 5") * ISNUMBER(PTS!AD:AD)))} -> 184.55455 | AA13: {=AVERAGE(_xlfn._xlws.FILTER(PTS!AF:AF, (PTS!$E:$E="Memphis Rule 5") * ISNUMBER(PTS!AF:AF)))} -> 329.00909 | AB13: {=AVERAGE(_xlfn._xlws.FILTER(PTS!AG:AG, (PTS!$E:$E="Memphis Rule 5") * ISNUMBER(PTS!AG:AG)))} -> 28.8143 | AC13: {=AVERAGE(_xlfn._xlws.FILTER(PTS!AH:AH, (PTS!$E:$E="Memphis Rule 5") * ISNUMBER(PTS!AH:AH)))} -> 6.9731405 | AD13: {=AVERAGE(_xlfn._xlws.FILTER(PTS!AI:AI, (PTS!$E:$E="Memphis Rule 5") * ISNUMBER(PTS!AI:AI)))} -> 12.587317 | AE13: {=AVERAGE(_xlfn._xlws.FILTER(PTS!AJ:AJ, (PTS!$E:$E="Memphis Rule 5") * ISNUMBER(PTS!AJ:AJ)))} -> 6.7352 | AG13: {=AVERAGE(_xlfn._xlws.FILTER(PTS!AL:AL, (PTS!$E:$E="Memphis Rule 5") * ISNUMBER(PTS!AL:AL)))} -> 55.109958 | AH13: {=AVERAGE(_xlfn._xlws.FILTER(PTS!AM:AM, (PTS!$E:$E="Memphis Rule 5") * ISNUMBER(PTS!AM:AM)))} -> 80 | AI13: {=AVERAGE(_xlfn._xlws.FILTER(PTS!AN:AN, (PTS!$E:$E="Memphis Rule 5") * ISNUMBER(PTS!AN:AN)))} -> 26.178082 | AJ13: {=AVERAGE(_xlfn._xlws.FILTER(PTS!AO:AO, (PTS!$E:$E="Memphis Rule 5") * ISNUMBER(PTS!AO:AO)))} -> 0 | AM13: {=AVERAGE(_xlfn._xlws.FILTER(PTS!AR:AR, (PTS!$E:$E="Memphis Rule 5") * ISNUMBER(PTS!AR:AR)))} -> 106.17808 | AQ13: =M13+R13+W13+AA13+AG13+AM13 -> 921.86186 | AR13: =L13+R13+W13+AA13+AG13+AM13 -> 1310.1819
B14: Dallas
B15: Houston
B16: BRZ | M16: =EXPORT!O8 -> 0 | R16: =EXPORT!Z8 -> 0 | W16: =EXPORT!AK8 -> 0 | AA16: =EXPORT!AV8 -> 70.942575 | AG16: =EXPORT!BG8 -> 77.5752 | AM16: =EXPORT!BR8 -> 199.79452 | AQ16: =M16+R16+W16+AA16+AG16+AM16 -> 348.3123
B17: AUS
C19: Origin Warehouse | N19: Inland Logistics | S19: Consolidation | X19: Outbound Logistics | AB19: Documentation | AH19: CIF | AN19: Cert Costs | AQ19: Terms Total
C20: Terms | D20: Receiving | E20: Load Out | F20: Compression | G20: Class | H20: Marking | I20: Storage | J20: Interest | K20: Origin Commission | L20: Total Equity | M20: Total Origin | N20: Flatbed | O20: Late Loading | P20: Transit Truck | R20: Total Inland | S20: Block Handling | T20: Storage | U20: Interest | W20: Total Consol | X20: Dray | Y20: Ocean | AA20: Total Out | AB20: Sight LC | AC20: Forwarding | AD20: Controlling | AE20: Insurance | AG20: Total Doc | AH20: Destination Comission | AI20: Cost of Funds | AJ20: Qclaim | AK20: Interest | AM20: Total CIF | AN20: USDA | AO20: ICE | AP20: Total CERT | AQ20: Cash | AR20: Equity
B21: WTX-Dallas Cert-Block Out | F21: =$F$5 -> 203.04912 | I21: =I5 -> 54.473684 | J21: =J5 -> 37.916667 | M21: =M5 -> 307.52024 | N21: =N5 -> 4.9122807 | O21: =O5 -> 1.1403509 | P21: =P5 -> 186.05615 | R21: =R5 -> 192.33066 | S21: =S5 -> 54 | W21: =S21+T21+U21+V21 -> 54 | AN21: =COSTS!$X$17 -> 85 | AO21: =COSTS!$X$18 -> 40 | AP21: =AN21+AO21 -> 125 | AQ21: =M21+R21+W21+AP21 -> 678.8509
B22: WTX-Dallas Cert-Break Out | F22: =$F$5 -> 203.04912 | I22: =I6 -> 53.622642 | J22: =J5 -> 37.916667 | M22: =M5 -> 307.52024 | N22: =N5 -> 4.9122807 | O22: =O5 -> 1.1403509 | P22: =P5 -> 186.05615 | R22: =R5 -> 192.33066 | S22: =COSTS!X19 -> 127 | W22: =S22+T22+U22+V22 -> 127 | AN22: =COSTS!$X$17 -> 85 | AO22: =COSTS!$X$18 -> 40 | AP22: =AN22+AO22 -> 125 | AQ22: =M22+R22+W22+AP22 -> 751.8509
B23: WTX-Houston Cert-Block Out | F23: =$F$5 -> 203.04912 | I23: =$I$5 -> 54.473684 | J23: =J5 -> 37.916667 | M23: =M5 -> 307.52024 | N23: =N5 -> 4.9122807 | O23: =O5 -> 1.1403509 | P23: =P6 -> 288.72326 | R23: =R6 -> 294.60561 | S23: =S7 -> 54 | W23: =S23+T23+U23+V23 -> 54 | AN23: =COSTS!$X$17 -> 85 | AO23: =COSTS!$X$18 -> 40 | AP23: =AN23+AO23 -> 125 | AQ23: =M23+R23+W23+AP23 -> 781.12585
B24: WTX- Houston Cert-Break Out | F24: =$F$5 -> 203.04912 | I24: =$I$5 -> 54.473684 | J24: =J5 -> 37.916667 | M24: =M5 -> 307.52024 | N24: =N5 -> 4.9122807 | O24: =O5 -> 1.1403509 | P24: =P6 -> 288.72326 | R24: =R6 -> 294.60561 | S24: =COSTS!X19 -> 127 | W24: =S24+T24+U24+V24 -> 127 | AN24: =COSTS!$X$17 -> 85 | AO24: =COSTS!$X$18 -> 40 | AP24: =AN24+AO24 -> 125 | AQ24: =M24+R24+W24+AP24 -> 854.12585
B25: STX-Houston Cert-Block Out | E25: =E7 -> 203.10345 | F25: =F7 -> 136.96552 | G25: =G12 -> 2.0689655 | I25: =I7 -> 76.586207 | J25: =J7 -> 37.916667 | M25: =M7 -> 452.33046 | N25: =N7 -> 4.8275862 | O25: =O7 -> 0 | P25: =P7 -> 200.75758 | R25: =R7 -> 205.94276 | S25: =S7 -> 54 | W25: =S25+T25+U25+V25 -> 54 | AN25: =COSTS!$X$17 -> 85 | AO25: =COSTS!$X$18 -> 40 | AP25: =AN25+AO25 -> 125 | AQ25: =M25+R25+W25+AP25 -> 837.27322
B26: STX-Houston Cert-Break Out | E26: =E7 -> 203.10345 | F26: =F7 -> 136.96552 | G26: =G12 -> 2.0689655 | I26: =I7 -> 76.586207 | J26: =J7 -> 37.916667 | M26: =M7 -> 452.33046 | N26: =N7 -> 4.8275862 | O26: =O7 -> 0 | P26: =P7 -> 200.75758 | R26: =R7 -> 205.94276 | S26: =COSTS!X19 -> 127 | W26: =S26+T26+U26+V26 -> 127 | AN26: =COSTS!$X$17 -> 85 | AO26: =COSTS!$X$18 -> 40 | AP26: =AN26+AO26 -> 125 | AQ26: =M26+R26+W26+AP26 -> 910.27322
B27: ME-Memphis Cert-Block Out | I27: =I8 -> 68.733333 | J27: =J8 -> 37.916667 | M27: =M8 -> 106.65 | N27: =N8 -> 0.26666667 | O27: =O8 -> 0.73333333 | P27: =P8 -> 211.56873 | R27: =R13 -> 212.56873 | S27: =S8 -> 50.48 | W27: =S27+T27+U27+V27 -> 50.48 | AN27: =COSTS!$X$17 -> 85 | AO27: =COSTS!$X$18 -> 40 | AP27: =AN27+AO27 -> 125 | AQ27: =M27+R27+W27+AP27 -> 494.69873
B28: ME-Memphis Cert-Break Out | I28: =I8 -> 68.733333 | J28: =J8 -> 37.916667 | M28: =M8 -> 106.65 | N28: =N8 -> 0.26666667 | O28: =O8 -> 0.73333333 | P28: =P8 -> 211.56873 | R28: =R13 -> 212.56873 | S28: =COSTS!X19 -> 127 | W28: =S28+T28+U28+V28 -> 127 | AN28: =COSTS!$X$17 -> 85 | AO28: =COSTS!$X$18 -> 40 | AP28: =AN28+AO28 -> 125 | AQ28: =M28+R28+W28+AP28 -> 571.21873
B29: Savannah | I29: =I9 -> 57.318841 | J29: =J9 -> 37.916667 | M29: =M9 -> 41.307971 | N29: =N9 -> 0 | O29: =O9 -> 0.82345191 | P29: =P9 -> 203.95335 | R29: =R9 -> 204.78891 | S29: =S9 -> 52 | W29: =S29+T29+U29+V29 -> 52 | AN29: =COSTS!$X$17 -> 85 | AO29: =COSTS!$X$18 -> 40 | AP29: =AN29+AO29 -> 125 | AQ29: =M29+R29+W29+AP29 -> 423.09688
B30: Savannah | I30: =I9 -> 57.318841 | J30: =J9 -> 37.916667 | M30: =M9 -> 41.307971 | N30: =N9 -> 0 | O30: =O9 -> 0.82345191 | P30: =P9 -> 203.95335 | R30: =R9 -> 204.78891 | S30: =COSTS!X19 -> 127 | W30: =S30+T30+U30+V30 -> 127 | AN30: =COSTS!$X$17 -> 85 | AO30: =COSTS!$X$18 -> 40 | AP30: =AN30+AO30 -> 125 | AQ30: =M30+R30+W30+AP30 -> 498.09688
T33: *1 MONTHS OF STORAGE
C34: Origin Warehouse | N34: Inland Logistics | S34: Cert Storage Costs | X34: Outbound Logistics | AB34: Documentation | AH34: CIF | AN34: Cert Costs | AQ34: Terms Total
C35: Terms | D35: Receiving | E35: Load Out | F35: Compression | G35: Class | H35: Marking | I35: Storage | J35: Interest | K35: Origin Commission | L35: Total Equity | M35: Total Origin | N35: Flatbed | O35: Late Loading | P35: Transit Truck | R35: Total Inland | S35: Storage | T35: Interest | U35: Interest | W35: Total Cert | X35: Dray | Y35: Ocean | AA35: Total Out | AB35: Sight LC | AC35: Forwarding | AD35: Controlling | AE35: Insurance | AG35: Total Doc | AH35: Destination Comission | AI35: Cost of Funds | AJ35: Qclaim | AM35: Total CIF | AN35: USDA | AO35: ICE | AP35: Total CERT | AQ35: Cash | AR35: Equity
B36: Memphis Stop | S36: ='Cert Tariffs'!H3 -> 90.3125 | T36: ='Cert Tariffs'!I3 -> 40.625 | W36: =S36+T36+U36+V36 -> 130.9375 | X36: =X8 -> 144.45455 | Y36: =Y8 -> 182.72727 | AA36: =X36+Y36+Z36 -> 327.18182 | AB36: =AB8 -> 28.8143 | AC36: =AC8 -> 6.9731405 | AD36: =AD8 -> 12.587317 | AE36: =AE8 -> 6.7352 | AG36: =AB36+AC36+AD36+AE36+AF36 -> 55.109958 | AH36: =AH8 -> 80 | AI36: =AI8 -> 26.178082 | AJ36: =AJ8 -> 0 | AK36: =AK8 -> 0 | AM36: =AH36+AI36+AJ36+AK36+AL36 -> 106.17808 | AQ36: =W36+AA36+AG36+AM36 -> 619.40736
B37: Houston Stop | S37: ='Cert Tariffs'!M3 -> 97 | T37: ='Cert Tariffs'!N3 -> 40.625 | W37: =S37+T37+U37+V37 -> 137.625 | X37: =X7 -> 133.97335 | Y37: =Y6 -> 197.95455 | AA37: =X37+Y37+Z37 -> 331.9279 | AB37: =AB7 -> 28.8143 | AC37: =AC7 -> 6.9731405 | AD37: =AD7 -> 12.587317 | AE37: =AE7 -> 6.7352 | AG37: =AB37+AC37+AD37+AE37+AF37 -> 55.109958 | AH37: =AH7 -> 80 | AI37: =AI7 -> 26.178082 | AJ37: =AJ7 -> 0 | AK37: =AK7 -> 0 | AM37: =AH37+AI37+AJ37+AK37+AL37 -> 106.17808 | AQ37: =W37+AA37+AG37+AM37 -> 630.84094
B38: Dallas Stop | S38: ='Cert Tariffs'!R3 -> 100.6 | T38: ='Cert Tariffs'!S3 -> 40.625 | W38: =S38+T38+U38+V38 -> 141.225 | X38: =X5 -> 162.5 | Y38: =Y5 -> 268.18182 | AA38: =X38+Y38+Z38 -> 430.68182 | AB38: =AB5 -> 28.8143 | AC38: =AC5 -> 6.9731405 | AD38: =AD5 -> 12.587317 | AE38: =AE5 -> 6.7352 | AG38: =AB38+AC38+AD38+AE38+AF38 -> 55.109958 | AH38: =AH5 -> 80 | AI38: =AI5 -> 26.178082 | AJ38: =AJ5 -> 0 | AK38: =AK5 -> 0 | AM38: =AH38+AI38+AJ38+AK38+AL38 -> 106.17808 | AQ38: =W38+AA38+AG38+AM38 -> 733.19486
B39: Savannah Stop | S39: ='Cert Tariffs'!W3 -> 110 | T39: ='Cert Tariffs'!X3 -> 40.625 | W39: =S39+T39+U39+V39 -> 150.625 | X39: =X9 -> 110.22727 | Y39: =Y9 -> 107.04545 | AA39: =X39+Y39+Z39 -> 217.27273 | AB39: =AB9 -> 28.8143 | AC39: =AC9 -> 6.9731405 | AD39: =AD9 -> 12.587317 | AE39: =AE9 -> 6.7352 | AG39: =AB39+AC39+AD39+AE39+AF39 -> 55.109958 | AH39: =AH9 -> 80 | AI39: =AI9 -> 26.178082 | AJ39: =AJ9 -> 0 | AK39: =AK9 -> 0 | AM39: =AH39+AI39+AJ39+AK39+AL39 -> 106.17808 | AQ39: =W39+AA39+AG39+AM39 -> 529.18577

Sheet EXPORT
F2: ---annual (season)--- | Q2: ---quartly--- | AB2: ---annual (season)--- | AM2: ---varible by origin and destination--- | AX2: ---varies by desination only--- | BI2: ---varies by desination & underlying price--- | BT2: ---total costings per destination--- | CE2: ---pnd base cif---
F3: Origin | Q3: Inland Logistics | AB3: Consolidation | AM3: Outbound Logistics | AX3: Documentation/Execution | BI3: CIF COSTS | BT3: TOTAL COSTINGS | CE3: PREIMIUM AND DISCOUNTS
F4: Receiving | G4: Load Out | H4: Compression | I4: Class | J4: Marking | K4: Storage | L4: Interest | M4: Origin Comm | Q4: Flatbed | R4: Late Fee | S4: Transit Truck | AB4: Block Handling | AC4: Storage | AD4: Interest | AM4: Dray | AN4: Ocean | AX4: Sight LC | AY4: Forwarding | AZ4: Controlling | BA4: Insurance | BI4: Dest Comission | BJ4: High Seas | BK4: Qclaim | BL4: Interest
AM5: Dallas | AN5: Houston | AO5: Houston | AP5: Memphis | AQ5: Savannah
C6: TT | D6: FT | F6: WTX | G6: WTXH | H6: STX | I6: MR5 | J6: ER5 | K6: EMOT | L6: ME | M6: HOU | N6: DAL | O6: BRZ | P6: AUS | Q6: WTX | R6: WTXH | S6: STX | T6: MR5 | U6: ER5 | V6: EMOT | W6: ME | X6: HOU | Y6: DAL | Z6: BRZ | AA6: AUS | AB6: WTX | AC6: WTXH | AD6: STX | AE6: MR5 | AF6: ER5 | AG6: EMOT | AH6: ME | AI6: HOU | AJ6: DAL | AK6: BRZ | AL6: AUS | AM6: WTX | AN6: WTXH | AO6: STX | AP6: MR5 | AQ6: ER5 | AR6: EMOT | AS6: ME | AT6: HOU | AU6: DAL | AV6: BRZ | AW6: AUS | AX6: WTX | AY6: WTXH | AZ6: STX | BA6: MR5 | BB6: ER5 | BC6: EMOT | BD6: ME | BE6: HOU | BF6: DAL | BG6: BRZ | BH6: AUS | BI6: WTX | BJ6: WTXH | BK6: STX | BL6: MR5 | BM6: ER5 | BN6: EMOT | BO6: ME | BP6: HOU | BQ6: DAL | BR6: BRZ | BS6: AUS | BT6: WTX | BU6: WTXH | BV6: STX | BW6: MR5 | BX6: ER5 | BY6: EMOT | BZ6: ME | CA6: HOU | CB6: DAL | CC6: BRZ | CD6: AUS | CE6: WTX | CF6: WTXH | CG6: STX | CH6: MR5 | CI6: ER5 | CJ6: EMOT | CK6: ME | CL6: HOU | CM6: DAL | CN6: BRZ | CO6: AUS
A7: Base | E7: CIF FE | F7: =CIF!M5 -> 307.52024 | G7: =CIF!M6 -> 308.68205 | H7: =CIF!M7 -> 452.33046 | I7: =CIF!M8 -> 106.65 | J7: =AVERAGE(CIF!M9,CIF!M10) -> 63.672813 | K7: =AVERAGE(CIF!M5,CIF!M7,CIF!M8,CIF!M9,CIF!M10) -> 198.76926 | L7: =AVERAGE(CIF!M8:M10) -> 77.998542 | Q7: =CIF!R5 -> 192.33066 | R7: =CIF!R6 -> 294.60561 | S7: =CIF!R7 -> 205.94276 | T7: =CIF!R8 -> 212.56873 | U7: =AVERAGE(CIF!R9,CIF!R10) -> 222.95739 | V7: =AVERAGE(CIF!R5,CIF!R7,CIF!R8,CIF!R9,CIF!R10) -> 211.35138 | W7: =AVERAGE(CIF!R9,CIF!R10,CIF!R8) -> 219.4945 | AB7: =CIF!W5 -> 130.65 | AC7: =CIF!W6 -> 130.65 | AD7: =CIF!W7 -> 130.65 | AE7: =CIF!W8 -> 112.346 | AF7: =AVERAGE(CIF!W9:W10) -> 127.7216 | AG7: =AVERAGE(CIF!W5,CIF!W7,CIF!W8,CIF!W9,CIF!W10) -> 125.81784 | AH7: =AVERAGE(CIF!W8,CIF!W9,CIF!W10) -> 122.5964 | AI7: =CIF!W15 -> 0 | AJ7: =CIF!W14 -> 0 | AM7: =CIF!$X$5+VLOOKUP($AM$5&$E7,OCEAN!$E:$J,5,FALSE) -> 430.68182 | AN7: =CIF!$X$6+VLOOKUP($AN$5&$E7,OCEAN!$E:$J,5,FALSE) -> 331.9279 | AO7: =CIF!$X$7+VLOOKUP($AO$5&$E7,OCEAN!$E:$J,5,FALSE) -> 331.9279 | AP7: =CIF!$X$8+VLOOKUP($AP$5&$E7,OCEAN!$E:$J,5,FALSE) -> 327.18182 | AQ7: =CIF!$X$9+VLOOKUP($AQ$5&$E7,OCEAN!$E:$J,5,FALSE) -> 217.27273 | AR7: =AVERAGE(AM7,AO7,AP7,AQ7) -> 326.76607 | AS7: =AVERAGE(AP7,AQ7) -> 272.22727 | AX7: =CIF!AG5 -> 55.109958 | AY7: =CIF!AG6 -> 55.109958 | AZ7: =CIF!AG7 -> 55.109958 | BA7: =CIF!AG8 -> 55.109958 | BB7: =CIF!AG9 -> 55.109958 | BC7: =AVERAGE(CIF!AG5,CIF!AG7,CIF!AG8,CIF!AG9,CIF!AG10) -> 55.109958 | BD7: =AVERAGE(CIF!AG8:AG10) -> 55.109958 | BI7: =CIF!$AM5 -> 106.17808 | BJ7: =CIF!$AM6 -> 106.17808 | BK7: =CIF!$AM7 -> 106.17808 | BL7: =CIF!$AM8 -> 106.17808 | BM7: =CIF!$AM9 -> 106.17808 | BN7: =AVERAGE(CIF!AM5,CIF!AM7,CIF!AM8,CIF!AM9,CIF!AM10) -> 106.17808 | BO7: =AVERAGE(CIF!AM8:AM10) -> 106.17808 | BP7: =CIF!AM15 -> 0 | BQ7: =CIF!AM14 -> 0 | BT7: =CIF!AQ5 -> 1222.4708 | BU7: =CIF!$AQ6 -> 1226.1348 | BV7: =CIF!$AQ7 -> 1284.5608 | BW7: =CIF!$AQ8 -> 921.60277 | BX7: =J7+U7+AF7+AQ7+BB7+BM7 -> 792.91257 | BY7: =K7+V7+AG7+AR7+BC7+BN7 -> 1023.9926 | BZ7: =L7+W7+AH7+AS7+BD7+BO7 -> 853.60476 | CC7: 348 | CD7: 284 | CE7: =BT7-CIF!AQ5 -> 0 | CF7: =BU7-CIF!AQ6 -> 0 | CG7: =BV7-CIF!AQ7 -> 0 | CH7: =BW7-CIF!AQ8 -> 0 | CI7: 0 | CJ7: 0 | CK7: 0 | CL7: 0 | CM7: 0
A8: China | B8: CN | C8: 38 | D8: 18 | E8: Qingdao | F8: =$F$7 -> 307.52024 | G8: =$G$7 -> 308.68205 | H8: =$H$7 -> 452.33046 | I8: =$I$7 -> 106.65 | J8: =$J$7 -> 63.672813 | K8: =$K$7 -> 198.76926 | L8: =$L$7 -> 77.998542 | Q8: =$Q$7 -> 192.33066 | R8: =$R$7 -> 294.60561 | S8: =$S$7 -> 205.94276 | T8: =$T$7 -> 212.56873 | U8: =$U$7 -> 222.95739 | V8: =$V$7 -> 211.35138 | W8: =$W$7 -> 219.4945 | AB8: =$AB$7 -> 130.65 | AC8: =$AC$7 -> 130.65 | AD8: =$AD$7 -> 130.65 | AE8: =$AE$7 -> 112.346 | AF8: =$AF$7 -> 127.7216 | AG8: =$AG$7 -> 125.81784 | AH8: =$AH$7 -> 122.5964 | AI8: =$AI$7 -> 0 | AJ8: =$AJ$7 -> 0 | AM8: =CIF!$X$5+VLOOKUP($AM$5&$E8,OCEAN!$E:$J,5,FALSE) -> 430.68182 | AN8: =CIF!$X$6+VLOOKUP($AN$5&$E8,OCEAN!$E:$J,5,FALSE) -> 331.9279 | AO8: =CIF!$X$7+VLOOKUP($AO$5&$E8,OCEAN!$E:$J,5,FALSE) -> 331.9279 | AP8: =CIF!$X$8+VLOOKUP($AP$5&$E8,OCEAN!$E:$J,5,FALSE) -> 327.18182 | AQ8: =CIF!$X$9+VLOOKUP($AQ$5&$E8,OCEAN!$E:$J,5,FALSE) -> 217.27273 | AR8: =AVERAGE(IF(ISNUMBER(AM8),AM8,""),IF(ISNUMBER(AO8),AO8,""),IF(ISNUMBER(AP8),AP8,""),IF(ISNUMBER(AQ8),AQ8,"")) -> 326.76607 | AS8: =AVERAGE(IF(ISNUMBER(AP8),AP8,""),IF(ISNUMBER(AQ8),AQ8,"")) -> 272.22727 | AV8: =CIF!$X$16+VLOOKUP($AV$6&$E8,OCEAN!$E:$J,5,FALSE) -> 70.942575 | AW8: =CIF!$X$17+VLOOKUP($AW$6&$E8,OCEAN!$E:$J,5,FALSE) -> 35.924884 | AX8: =$AX$7 -> 55.109958 | AY8: =$AY$7 -> 55.109958 | AZ8: =$AY$8 -> 55.109958 | BA8: =$BA$7 -> 55.109958 | BB8: =$BB$7 -> 55.109958 | BC8: =$BB$7 -> 55.109958 | BD8: =$BB$7 -> 55.109958 | BE8: =$BB$7 -> 55.109958 | BF8: =$BB$7 -> 55.109958 | BG8: =COSTS!I5+COSTS!J5+COSTS!K5 -> 77.5752 | BH8: =COSTS!O5+COSTS!P5+COSTS!Q5 -> 48.0888 | BI8: =COSTS!F5+COSTS!G5+COSTS!H5 -> 106.17808 | BJ8: =COSTS!F5+COSTS!G5+COSTS!H5 -> 106.17808 | BK8: =COSTS!F5+COSTS!G5+COSTS!H5 -> 106.17808 | BL8: =COSTS!F5+COSTS!G5+COSTS!H5 -> 106.17808 | BM8: =COSTS!F5+COSTS!G5+COSTS!H5 -> 106.17808 | BN8: =COSTS!F5+COSTS!G5+COSTS!H5 -> 106.17808 | BO8: =COSTS!F5+COSTS!G5+COSTS!H5 -> 106.17808 | BP8: =COSTS!F5+COSTS!G5+COSTS!H5 -> 106.17808 | BQ8: =COSTS!F5+COSTS!G5+COSTS!H5 -> 106.17808 | BR8: =COSTS!L5+COSTS!M5+COSTS!N5 -> 199.79452 | BS8: =COSTS!R5+COSTS!S5+COSTS!T5 -> 199 | BT8: =F8+Q8+AB8+AM8+AX8+BI8 -> 1222.4708 | BU8: =G8+R8+AC8+AN8+AY8+BJ8 -> 1227.1536 | BV8: =H8+S8+AD8+AO8+AZ8+BK8 -> 1282.1392 | BW8: =I8+T8+AE8+AP8+BA8+BL8 -> 920.03459 | BX8: =J8+U8+AF8+AQ8+BB8+BM8 -> 792.91257 | BY8: =K8+V8+AG8+AR8+BC8+BN8 -> 1023.9926 | BZ8: =L8+W8+AH8+AS8+BD8+BO8 -> 853.60476 | CA8: =M8+X8+AI8+AT8+BE8+BP8 -> 161.28804 | ... CD8: =P8+AA8+AL8+AW8+BH8+BS8 -> 283.01368 | CE8: =BT8-$BT$7 -> 0 | CF8: =BU8-$BU$7 -> 1.0188088 | CG8: =BV8-$BV$7 -> -2.4216301 | CH8: =BW8-$BW$7 -> -1.5681818 | CI8: =BX8-$BX$7 -> 0 | CJ8: =BY8-$BY$7 -> 0 | CK8: =BZ8-$BZ$7 -> 0 | CN8: =CC8-$CC$7 -> 0.31229516 | CO8: =CD8-$CD$7 -> -0.98631567
E9: Xiamen | F9: =$F$7 -> 307.52024 | G9: =$G$7 -> 308.68205 | H9: =$H$7 -> 452.33046 | I9: =$I$7 -> 106.65 | J9: =$J$7 -> 63.672813 | K9: =$K$7 -> 198.76926 | L9: =$L$7 -> 77.998542 | Q9: =$Q$7 -> 192.33066 | R9: =$R$7 -> 294.60561 | S9: =$S$7 -> 205.94276 | T9: =$T$7 -> 212.56873 | U9: =$U$7 -> 222.95739 | V9: =$V$7 -> 211.35138 | W9: =$W$7 -> 219.4945 | AB9: =$AB$7 -> 130.65 | AC9: =$AC$7 -> 130.65 | AD9: =$AD$7 -> 130.65 | AE9: =$AE$7 -> 112.346 | AF9: =$AF$7 -> 127.7216 | AG9: =$AG$7 -> 125.81784 | AH9: =$AH$7 -> 122.5964 | AI9: =$AI$7 -> 0 | AJ9: =$AJ$7 -> 0 | AM9: =CIF!$X$5+VLOOKUP($AM$5&$E9,OCEAN!$E:$J,5,FALSE) -> 378.40909 | AN9: =CIF!$X$6+VLOOKUP($AN$5&$E9,OCEAN!$E:$J,5,FALSE) -> 304.4279 | AO9: =CIF!$X$7+VLOOKUP($AO$5&$E9,OCEAN!$E:$J,5,FALSE) -> 304.4279 | AP9: =CIF!$X$8+VLOOKUP($AP$5&$E9,OCEAN!$E:$J,5,FALSE) -> 292.18182 | AQ9: =CIF!$X$9+VLOOKUP($AQ$5&$E9,OCEAN!$E:$J,5,FALSE) -> 258.18182 | AR9: =AVERAGE(IF(ISNUMBER(AM9),AM9,""),IF(ISNUMBER(AO9),AO9,""),IF(ISNUMBER(AP9),AP9,""),IF(ISNUMBER(AQ9),AQ9,"")) -> 308.30016 | AS9: =AVERAGE(IF(ISNUMBER(AP9),AP9,""),IF(ISNUMBER(AQ9),AQ9,"")) -> 275.18182 | AV9: =CIF!$X$16+VLOOKUP($AV$6&$E9,OCEAN!$E:$J,5,FALSE) -> 153.31579 | AW9: =CIF!$X$17+VLOOKUP($AW$6&$E9,OCEAN!$E:$J,5,FALSE) -> 63.866461 | AX9: =$AX$7 -> 55.109958 | AY9: =$AY$7 -> 55.109958 | AZ9: =$AY$8 -> 55.109958 | BA9: =$BA$7 -> 55.109958 | BB9: =$BB$7 -> 55.109958 | BC9: =$BB$7 -> 55.109958 | BD9: =$BB$7 -> 55.109958 | BE9: =$BB$7 -> 55.109958 | BF9: =$BB$7 -> 55.109958 | BG9: =COSTS!I5+COSTS!J5+COSTS!K5 -> 77.5752 | BH9: =COSTS!O5+COSTS!P5+COSTS!Q5 -> 48.0888 | BI9: =COSTS!F5+COSTS!G5+COSTS!H5 -> 106.17808 | BJ9: =COSTS!F5+COSTS!G5+COSTS!H5 -> 106.17808 | BK9: =COSTS!F5+COSTS!G5+COSTS!H5 -> 106.17808 | BL9: =COSTS!F5+COSTS!G5+COSTS!H5 -> 106.17808 | BM9: =COSTS!F5+COSTS!G5+COSTS!H5 -> 106.17808 | BN9: =COSTS!F5+COSTS!G5+COSTS!H5 -> 106.17808 | BO9: =COSTS!F5+COSTS!G5+COSTS!H5 -> 106.17808 | BP9: =COSTS!F5+COSTS!G5+COSTS!H5 -> 106.17808 | BQ9: =COSTS!F5+COSTS!G5+COSTS!H5 -> 106.17808 | BR9: =COSTS!L5+COSTS!M5+COSTS!N5 -> 199.79452 | BS9: =COSTS!R5+COSTS!S5+COSTS!T5 -> 199 | BT9: =F9+Q9+AB9+AM9+AX9+BI9 -> 1170.198 | BU9: =G9+R9+AC9+AN9+AY9+BJ9 -> 1199.6536 | BV9: =H9+S9+AD9+AO9+AZ9+BK9 -> 1254.6392 | BW9: =I9+T9+AE9+AP9+BA9+BL9 -> 885.03459 | BX9: =J9+U9+AF9+AQ9+BB9+BM9 -> 833.82166 | BY9: =K9+V9+AG9+AR9+BC9+BN9 -> 1005.5267 | BZ9: =L9+W9+AH9+AS9+BD9+BO9 -> 856.5593 | CA9: =M9+X9+AI9+AT9+BE9+BP9 -> 161.28804 | ... CD9: =P9+AA9+AL9+AW9+BH9+BS9 -> 310.95526 | CE9: =BT9-$BT$7 -> -52.272727 | CF9: =BU9-$BU$7 -> -26.481191 | CG9: =BV9-$BV$7 -> -29.92163 | CH9: =BW9-$BW$7 -> -36.568182 | CI9: =BX9-$BX$7 -> 40.909091 | CJ9: =BY9-$BY$7 -> -18.465909 | CK9: =BZ9-$BZ$7 -> 2.9545455 | CN9: =CC9-$CC$7 -> 82.685515 | CO9: =CD9-$CD$7 -> 26.955261
E10: Lianyungang | F10: =$F$7 -> 307.52024 | G10: =$G$7 -> 308.68205 | H10: =$H$7 -> 452.33046 | I10: =$I$7 -> 106.65 | J10: =$J$7 -> 63.672813 | K10: =$K$7 -> 198.76926 | L10: =$L$7 -> 77.998542 | Q10: =$Q$7 -> 192.33066 | R10: =$R$7 -> 294.60561 | S10: =$S$7 -> 205.94276 | T10: =$T$7 -> 212.56873 | U10: =$U$7 -> 222.95739 | V10: =$V$7 -> 211.35138 | W10: =$W$7 -> 219.4945 | AB10: =$AB$7 -> 130.65 | AC10: =$AC$7 -> 130.65 | AD10: =$AD$7 -> 130.65 | AE10: =$AE$7 -> 112.346 | AF10: =$AF$7 -> 127.7216 | AG10: =$AG$7 -> 125.81784 | AH10: =$AH$7 -> 122.5964 | AI10: =$AI$7 -> 0 | AJ10: =$AJ$7 -> 0 | AM10: =CIF!$X$5+VLOOKUP($AM$5&$E10,OCEAN!$E:$J,5,FALSE) -> 560.22727 | AN10: =CIF!$X$6+VLOOKUP($AN$5&$E10,OCEAN!$E:$J,5,FALSE) -> 338.74608 | AO10: =CIF!$X$7+VLOOKUP($AO$5&$E10,OCEAN!$E:$J,5,FALSE) -> 338.74608 | AP10: =CIF!$X$8+VLOOKUP($AP$5&$E10,OCEAN!$E:$J,5,FALSE) -> 401.27273 | AQ10: =CIF!$X$9+VLOOKUP($AQ$5&$E10,OCEAN!$E:$J,5,FALSE) -> 271.81818 | AR10: =AVERAGE(IF(ISNUMBER(AM10),AM10,""),IF(ISNUMBER(AO10),AO10,""),IF(ISNUMBER(AP10),AP10,""),IF(ISNUMBER(AQ10),AQ10,"")) -> 393.01607 | AS10: =AVERAGE(IF(ISNUMBER(AP10),AP10,""),IF(ISNUMBER(AQ10),AQ10,"")) -> 336.54545 | AV10: =CIF!$X$16+VLOOKUP($AV$6&$E10,OCEAN!$E:$J,5,FALSE) -> 143.5181 | AW10: =CIF!$X$17+VLOOKUP($AW$6&$E10,OCEAN!$E:$J,5,FALSE) -> #N/A | AX10: =$AX$7 -> 55.109958 | AY10: =$AY$7 -> 55.109958 | AZ10: =$AY$8 -> 55.109958 | BA10: =$BA$7 -> 55.109958 | BB10: =$BB$7 -> 55.109958 | BC10: =$BB$7 -> 55.109958 | BD10: =$BB$7 -> 55.109958 | BE10: =$BB$7 -> 55.109958 | BF10: =$BB$7 -> 55.109958 | BG10: =COSTS!I5+COSTS!J5+COSTS!K5 -> 77.5752 | BH10: =COSTS!O5+COSTS!P5+COSTS!Q5 -> 48.0888 | BI10: =COSTS!F5+COSTS!G5+COSTS!H5 -> 106.17808 | BJ10: =COSTS!F5+COSTS!G5+COSTS!H5 -> 106.17808 | BK10: =COSTS!F5+COSTS!G5+COSTS!H5 -> 106.17808 | BL10: =COSTS!F5+COSTS!G5+COSTS!H5 -> 106.17808 | BM10: =COSTS!F5+COSTS!G5+COSTS!H5 -> 106.17808 | BN10: =COSTS!F5+COSTS!G5+COSTS!H5 -> 106.17808 | BO10: =COSTS!F5+COSTS!G5+COSTS!H5 -> 106.17808 | BP10: =COSTS!F5+COSTS!G5+COSTS!H5 -> 106.17808 | BQ10: =COSTS!F5+COSTS!G5+COSTS!H5 -> 106.17808 | BR10: =COSTS!L5+COSTS!M5+COSTS!N5 -> 199.79452 | BS10: =COSTS!R5+COSTS!S5+COSTS!T5 -> 199 | BT10: =F10+Q10+AB10+AM10+AX10+BI10 -> 1352.0162 | BU10: =G10+R10+AC10+AN10+AY10+BJ10 -> 1233.9718 | BV10: =H10+S10+AD10+AO10+AZ10+BK10 -> 1288.9573 | BW10: =I10+T10+AE10+AP10+BA10+BL10 -> 994.12549 | BX10: =J10+U10+AF10+AQ10+BB10+BM10 -> 847.45802 | BY10: =K10+V10+AG10+AR10+BC10+BN10 -> 1090.2426 | BZ10: =L10+W10+AH10+AS10+BD10+BO10 -> 917.92294 | CA10: =M10+X10+AI10+AT10+BE10+BP10 -> 161.28804 | ... CD10: =P10+AA10+AL10+AW10+BH10+BS10 -> #N/A | CE10: =BT10-$BT$7 -> 129.54545 | CF10: =BU10-$BU$7 -> 7.8369906 | CG10: =BV10-$BV$7 -> 4.3965517 | CH10: =BW10-$BW$7 -> 72.522727 | CI10: =BX10-$BX$7 -> 54.545455 | CJ10: =BY10-$BY$7 -> 66.25 | CK10: =BZ10-$BZ$7 -> 64.318182 | CN10: =CC10-$CC$7 -> 72.887819 | CO10: =CD10-$CD$7 -> #N/A
A11: Vietnam | B11: VN | C11: 50 | D11: 14 | E11: Ho Chi Minh | F11: =$F$7 -> 307.52024 | G11: =$G$7 -> 308.68205 | H11: =$H$7 -> 452.33046 | I11: =$I$7 -> 106.65 | J11: =$J$7 -> 63.672813 | K11: =$K$7 -> 198.76926 | L11: =$L$7 -> 77.998542 | Q11: =$Q$7 -> 192.33066 | R11: =$R$7 -> 294.60561 | S11: =$S$7 -> 205.94276 | T11: =$T$7 -> 212.56873 | U11: =$U$7 -> 222.95739 | V11: =$V$7 -> 211.35138 | W11: =$W$7 -> 219.4945 | AB11: =$AB$7 -> 130.65 | AC11: =$AC$7 -> 130.65 | AD11: =$AD$7 -> 130.65 | AE11: =$AE$7 -> 112.346 | AF11: =$AF$7 -> 127.7216 | AG11: =$AG$7 -> 125.81784 | AH11: =$AH$7 -> 122.5964 | AI11: =$AI$7 -> 0 | AJ11: =$AJ$7 -> 0 | AM11: =CIF!$X$5+VLOOKUP($AM$5&$E11,OCEAN!$E:$J,5,FALSE) -> 449.31818 | AN11: =CIF!$X$6+VLOOKUP($AN$5&$E11,OCEAN!$E:$J,5,FALSE) -> 358.97335 | AO11: =CIF!$X$7+VLOOKUP($AO$5&$E11,OCEAN!$E:$J,5,FALSE) -> 358.97335 | AP11: =CIF!$X$8+VLOOKUP($AP$5&$E11,OCEAN!$E:$J,5,FALSE) -> 408.54545 | AQ11: =CIF!$X$9+VLOOKUP($AQ$5&$E11,OCEAN!$E:$J,5,FALSE) -> 256.81818 | AR11: =AVERAGE(IF(ISNUMBER(AM11),AM11,""),IF(ISNUMBER(AO11),AO11,""),IF(ISNUMBER(AP11),AP11,""),IF(ISNUMBER(AQ11),AQ11,"")) -> 368.41379 | AS11: =AVERAGE(IF(ISNUMBER(AP11),AP11,""),IF(ISNUMBER(AQ11),AQ11,"")) -> 332.68182 | AV11: =CIF!$X$16+VLOOKUP($AV$6&$E11,OCEAN!$E:$J,5,FALSE) -> 72.575524 | AW11: =CIF!$X$17+VLOOKUP($AW$6&$E11,OCEAN!$E:$J,5,FALSE) -> 90.900844 | AX11: =COSTS!C6+COSTS!D6+COSTS!E6 -> 67.416591 | AY11: =COSTS!C6+COSTS!D6+COSTS!E6 -> 67.416591 | AZ11: =COSTS!C6+COSTS!D6+COSTS!E6 -> 67.416591 | BA11: =COSTS!C6+COSTS!D6+COSTS!E6 -> 67.416591 | BB11: =COSTS!C6+COSTS!D6+COSTS!E6 -> 67.416591 | BC11: =COSTS!D6+COSTS!E6+COSTS!F6 -> 98.301924 | BD11: =COSTS!E6+COSTS!F6+COSTS!G6 -> 117.74481 | BE11: =COSTS!F6+COSTS!G6+COSTS!H6 -> 106.17808 | BF11: =COSTS!G6+COSTS!H6+COSTS!I6 -> 80.178082 | BG11: =COSTS!I6+COSTS!J6+COSTS!K6 -> 81 | BH11: =COSTS!O6+COSTS!P6+COSTS!Q6 -> 64.0888 | BI11: =COSTS!F6+COSTS!G6+COSTS!H6 -> 106.17808 | BJ11: =COSTS!F6+COSTS!G6+COSTS!H6 -> 106.17808 | BK11: =COSTS!F6+COSTS!G6+COSTS!H6 -> 106.17808 | BL11: =COSTS!F6+COSTS!G6+COSTS!H6 -> 106.17808 | BM11: =COSTS!F6+COSTS!G6+COSTS!H6 -> 106.17808 | BN11: =COSTS!F6+COSTS!G6+COSTS!H6 -> 106.17808 | BO11: =COSTS!F6+COSTS!G6+COSTS!H6 -> 106.17808 | BP11: =COSTS!F6+COSTS!G6+COSTS!H6 -> 106.17808 | BQ11: =COSTS!F6+COSTS!G6+COSTS!H6 -> 106.17808 | BR11: =COSTS!L6+COSTS!M6+COSTS!N6 -> 174.79452 | BS11: =COSTS!R6+COSTS!S6+COSTS!T6 -> 174 | BT11: =F11+Q11+AB11+AM11+AX11+BI11 -> 1253.4138 | BU11: =G11+R11+AC11+AN11+AY11+BJ11 -> 1266.5057 | BV11: =H11+S11+AD11+AO11+AZ11+BK11 -> 1321.4912 | BW11: =I11+T11+AE11+AP11+BA11+BL11 -> 1013.7049 | BX11: =J11+U11+AF11+AQ11+BB11+BM11 -> 844.76466 | BY11: =K11+V11+AG11+AR11+BC11+BN11 -> 1108.8323 | BZ11: =L11+W11+AH11+AS11+BD11+BO11 -> 976.69415 | CA11: =M11+X11+AI11+AT11+BE11+BP11 -> 212.35616 | ... CD11: =P11+AA11+AL11+AW11+BH11+BS11 -> 328.98964 | CE11: =BT11-$BT$7 -> 30.942997 | CF11: =BU11-$BU$7 -> 40.370896 | CG11: =BV11-$BV$7 -> 36.930457 | CH11: =BW11-$BW$7 -> 92.102087 | CI11: =BX11-$BX$7 -> 51.852087 | CJ11: =BY11-$BY$7 -> 84.839693 | CK11: =BZ11-$BZ$7 -> 123.08939 | CN11: =CC11-$CC$7 -> -19.629956 | CO11: =CD11-$CD$7 -> 44.989644
E12: DaNang | F12: =$F$7 -> 307.52024 | G12: =$G$7 -> 308.68205 | H12: =$H$7 -> 452.33046 | I12: =$I$7 -> 106.65 | J12: =$J$7 -> 63.672813 | K12: =$K$7 -> 198.76926 | L12: =$L$7 -> 77.998542 | Q12: =$Q$7 -> 192.33066 | R12: =$R$7 -> 294.60561 | S12: =$S$7 -> 205.94276 | T12: =$T$7 -> 212.56873 | U12: =$U$7 -> 222.95739 | V12: =$V$7 -> 211.35138 | W12: =$W$7 -> 219.4945 | AB12: =$AB$7 -> 130.65 | AC12: =$AC$7 -> 130.65 | AD12: =$AD$7 -> 130.65 | AE12: =$AE$7 -> 112.346 | AF12: =$AF$7 -> 127.7216 | AG12: =$AG$7 -> 125.81784 | AH12: =$AH$7 -> 122.5964 | AI12: =$AI$7 -> 0 | AJ12: =$AJ$7 -> 0 | AM12: =CIF!$X$5+VLOOKUP($AM$5&$E12,OCEAN!$E:$J,5,FALSE) -> 562.04545 | AN12: =CIF!$X$6+VLOOKUP($AN$5&$E12,OCEAN!$E:$J,5,FALSE) -> 435.79154 | AO12: =CIF!$X$7+VLOOKUP($AO$5&$E12,OCEAN!$E:$J,5,FALSE) -> 435.79154 | AP12: =CIF!$X$8+VLOOKUP($AP$5&$E12,OCEAN!$E:$J,5,FALSE) -> 489.90909 | AQ12: =CIF!$X$9+VLOOKUP($AQ$5&$E12,OCEAN!$E:$J,5,FALSE) -> 314.77273 | AR12: =AVERAGE(IF(ISNUMBER(AM12),AM12,""),IF(ISNUMBER(AO12),AO12,""),IF(ISNUMBER(AP12),AP12,""),IF(ISNUMBER(AQ12),AQ12,"")) -> 450.6297 | AS12: =AVERAGE(IF(ISNUMBER(AP12),AP12,""),IF(ISNUMBER(AQ12),AQ12,"")) -> 402.34091 | AV12: =CIF!$X$16+VLOOKUP($AV$6&$E12,OCEAN!$E:$J,5,FALSE) -> 36.287762 | AW12: =CIF!$X$17+VLOOKUP($AW$6&$E12,OCEAN!$E:$J,5,FALSE) -> 99.791345 | AX12: =COSTS!C6+COSTS!D6+COSTS!E6 -> 67.416591 | AY12: =COSTS!C6+COSTS!D6+COSTS!E6 -> 67.416591 | AZ12: =COSTS!C6+COSTS!D6+COSTS!E6 -> 67.416591 | BA12: =COSTS!C6+COSTS!D6+COSTS!E6 -> 67.416591 | BB12: =COSTS!C6+COSTS!D6+COSTS!E6 -> 67.416591 | BC12: =COSTS!D6+COSTS!E6+COSTS!F6 -> 98.301924 | BD12: =COSTS!E6+COSTS!F6+COSTS!G6 -> 117.74481 | BE12: =COSTS!F6+COSTS!G6+COSTS!H6 -> 106.17808 | BF12: =COSTS!G6+COSTS!H6+COSTS!I6 -> 80.178082 | BG12: =COSTS!I6+COSTS!J6+COSTS!K6 -> 81 | BH12: =COSTS!O6+COSTS!P6+COSTS!Q6 -> 64.0888 | BI12: =COSTS!F6+COSTS!G6+COSTS!H6 -> 106.17808 | BJ12: =COSTS!F6+COSTS!G6+COSTS!H6 -> 106.17808 | BK12: =COSTS!F6+COSTS!G6+COSTS!H6 -> 106.17808 | BL12: =COSTS!F6+COSTS!G6+COSTS!H6 -> 106.17808 | BM12: =COSTS!F6+COSTS!G6+COSTS!H6 -> 106.17808 | BN12: =COSTS!F6+COSTS!G6+COSTS!H6 -> 106.17808 | BO12: =COSTS!F6+COSTS!G6+COSTS!H6 -> 106.17808 | BP12: =COSTS!F6+COSTS!G6+COSTS!H6 -> 106.17808 | BQ12: =COSTS!F6+COSTS!G6+COSTS!H6 -> 106.17808 | BR12: =COSTS!L6+COSTS!M6+COSTS!N6 -> 174.79452 | BS12: =COSTS!R6+COSTS!S6+COSTS!T6 -> 174 | BT12: =F12+Q12+AB12+AM12+AX12+BI12 -> 1366.141 | BU12: =G12+R12+AC12+AN12+AY12+BJ12 -> 1343.3239 | BV12: =H12+S12+AD12+AO12+AZ12+BK12 -> 1398.3094 | BW12: =I12+T12+AE12+AP12+BA12+BL12 -> 1095.0685 | BX12: =J12+U12+AF12+AQ12+BB12+BM12 -> 902.7192 | BY12: =K12+V12+AG12+AR12+BC12+BN12 -> 1191.0482 | BZ12: =L12+W12+AH12+AS12+BD12+BO12 -> 1046.3532 | CA12: =M12+X12+AI12+AT12+BE12+BP12 -> 212.35616 | ... CD12: =P12+AA12+AL12+AW12+BH12+BS12 -> 337.88015 | CE12: =BT12-$BT$7 -> 143.67027 | CF12: =BU12-$BU$7 -> 117.18908 | CG12: =BV12-$BV$7 -> 113.74864 | CH12: =BW12-$BW$7 -> 173.46572 | CI12: =BX12-$BX$7 -> 109.80663 | CJ12: =BY12-$BY$7 -> 167.0556 | CK12: =BZ12-$BZ$7 -> 192.74848 | CN12: =CC12-$CC$7 -> -55.917717 | CO12: =CD12-$CD$7 -> 53.880145
E13: Haiphong | F13: =$F$7 -> 307.52024 | G13: =$G$7 -> 308.68205 | H13: =$H$7 -> 452.33046 | I13: =$I$7 -> 106.65 | J13: =$J$7 -> 63.672813 | K13: =$K$7 -> 198.76926 | L13: =$L$7 -> 77.998542 | Q13: =$Q$7 -> 192.33066 | R13: =$R$7 -> 294.60561 | S13: =$S$7 -> 205.94276 | T13: =$T$7 -> 212.56873 | U13: =$U$7 -> 222.95739 | V13: =$V$7 -> 211.35138 | W13: =$W$7 -> 219.4945 | AB13: =$AB$7 -> 130.65 | AC13: =$AC$7 -> 130.65 | AD13: =$AD$7 -> 130.65 | AE13: =$AE$7 -> 112.346 | AF13: =$AF$7 -> 127.7216 | AG13: =$AG$7 -> 125.81784 | AH13: =$AH$7 -> 122.5964 | AI13: =$AI$7 -> 0 | AJ13: =$AJ$7 -> 0 | AM13: =CIF!$X$5+VLOOKUP($AM$5&$E13,OCEAN!$E:$J,5,FALSE) -> 443.63636 | AN13: =CIF!$X$6+VLOOKUP($AN$5&$E13,OCEAN!$E:$J,5,FALSE) -> 344.88245 | AO13: =CIF!$X$7+VLOOKUP($AO$5&$E13,OCEAN!$E:$J,5,FALSE) -> 344.88245 | AP13: =CIF!$X$8+VLOOKUP($AP$5&$E13,OCEAN!$E:$J,5,FALSE) -> 402.63636 | AQ13: =CIF!$X$9+VLOOKUP($AQ$5&$E13,OCEAN!$E:$J,5,FALSE) -> 254.77273 | AR13: =AVERAGE(IF(ISNUMBER(AM13),AM13,""),IF(ISNUMBER(AO13),AO13,""),IF(ISNUMBER(AP13),AP13,""),IF(ISNUMBER(AQ13),AQ13,"")) -> 361.48197 | AS13: =AVERAGE(IF(ISNUMBER(AP13),AP13,""),IF(ISNUMBER(AQ13),AQ13,"")) -> 328.70455 | AV13: =CIF!$X$16+VLOOKUP($AV$6&$E13,OCEAN!$E:$J,5,FALSE) -> 72.575524 | AW13: =CIF!$X$17+VLOOKUP($AW$6&$E13,OCEAN!$E:$J,5,FALSE) -> 90.900844 | AX13: =COSTS!C6+COSTS!D6+COSTS!E6 -> 67.416591 | AY13: =COSTS!C6+COSTS!D6+COSTS!E6 -> 67.416591 | AZ13: =COSTS!C6+COSTS!D6+COSTS!E6 -> 67.416591 | BA13: =COSTS!C6+COSTS!D6+COSTS!E6 -> 67.416591 | BB13: =COSTS!C6+COSTS!D6+COSTS!E6 -> 67.416591 | BC13: =COSTS!D6+COSTS!E6+COSTS!F6 -> 98.301924 | BD13: =COSTS!E6+COSTS!F6+COSTS!G6 -> 117.74481 | BE13: =COSTS!F6+COSTS!G6+COSTS!H6 -> 106.17808 | BF13: =COSTS!G6+COSTS!H6+COSTS!I6 -> 80.178082 | BG13: =COSTS!I6+COSTS!J6+COSTS!K6 -> 81 | BH13: =COSTS!O6+COSTS!P6+COSTS!Q6 -> 64.0888 | BI13: =COSTS!F6+COSTS!G6+COSTS!H6 -> 106.17808 | BJ13: =COSTS!F6+COSTS!G6+COSTS!H6 -> 106.17808 | BK13: =COSTS!F6+COSTS!G6+COSTS!H6 -> 106.17808 | BL13: =COSTS!F6+COSTS!G6+COSTS!H6 -> 106.17808 | BM13: =COSTS!F6+COSTS!G6+COSTS!H6 -> 106.17808 | BN13: =COSTS!F6+COSTS!G6+COSTS!H6 -> 106.17808 | BO13: =COSTS!F6+COSTS!G6+COSTS!H6 -> 106.17808 | BP13: =COSTS!F6+COSTS!G6+COSTS!H6 -> 106.17808 | BQ13: =COSTS!F6+COSTS!G6+COSTS!H6 -> 106.17808 | BR13: =COSTS!L6+COSTS!M6+COSTS!N6 -> 174.79452 | BS13: =COSTS!R6+COSTS!S6+COSTS!T6 -> 174 | BT13: =F13+Q13+AB13+AM13+AX13+BI13 -> 1247.7319 | BU13: =G13+R13+AC13+AN13+AY13+BJ13 -> 1252.4148 | BV13: =H13+S13+AD13+AO13+AZ13+BK13 -> 1307.4003 | BW13: =I13+T13+AE13+AP13+BA13+BL13 -> 1007.7958 | BX13: =J13+U13+AF13+AQ13+BB13+BM13 -> 842.7192 | BY13: =K13+V13+AG13+AR13+BC13+BN13 -> 1101.9005 | BZ13: =L13+W13+AH13+AS13+BD13+BO13 -> 972.71688 | CA13: =M13+X13+AI13+AT13+BE13+BP13 -> 212.35616 | ... CD13: =P13+AA13+AL13+AW13+BH13+BS13 -> 328.98964 | CE13: =BT13-$BT$7 -> 25.261178 | CF13: =BU13-$BU$7 -> 26.279987 | CG13: =BV13-$BV$7 -> 22.839548 | CH13: =BW13-$BW$7 -> 86.192997 | CI13: =BX13-$BX$7 -> 49.806633 | CJ13: =BY13-$BY$7 -> 77.907875 | CK13: =BZ13-$BZ$7 -> 119.11212 | CN13: =CC13-$CC$7 -> -19.629956 | CO13: =CD13-$CD$7 -> 44.989644
A14: Korea | B14: KO | C14: 46 | D14: 18 | E14: Busan | F14: =$F$7 -> 307.52024 | G14: =$G$7 -> 308.68205 | H14: =$H$7 -> 452.33046 | I14: =$I$7 -> 106.65 | J14: =$J$7 -> 63.672813 | K14: =$K$7 -> 198.76926 | L14: =$L$7 -> 77.998542 | Q14: =$Q$7 -> 192.33066 | R14: =$R$7 -> 294.60561 | S14: =$S$7 -> 205.94276 | T14: =$T$7 -> 212.56873 | U14: =$U$7 -> 222.95739 | V14: =$V$7 -> 211.35138 | W14: =$W$7 -> 219.4945 | AB14: =$AB$7 -> 130.65 | AC14: =$AC$7 -> 130.65 | AD14: =$AD$7 -> 130.65 | AE14: =$AE$7 -> 112.346 | AF14: =$AF$7 -> 127.7216 | AG14: =$AG$7 -> 125.81784 | AH14: =$AH$7 -> 122.5964 | AI14: =$AI$7 -> 0 | AJ14: =$AJ$7 -> 0 | AM14: =CIF!$X$5+VLOOKUP($AM$5&$E14,OCEAN!$E:$J,5,FALSE) -> 411.13636 | AN14: =CIF!$X$6+VLOOKUP($AN$5&$E14,OCEAN!$E:$J,5,FALSE) -> 303.74608 | AO14: =CIF!$X$7+VLOOKUP($AO$5&$E14,OCEAN!$E:$J,5,FALSE) -> 303.74608 | AP14: =CIF!$X$8+VLOOKUP($AP$5&$E14,OCEAN!$E:$J,5,FALSE) -> 339.45455 | AQ14: =CIF!$X$9+VLOOKUP($AQ$5&$E14,OCEAN!$E:$J,5,FALSE) -> 205.68182 | AR14: =AVERAGE(IF(ISNUMBER(AM14),AM14,""),IF(ISNUMBER(AO14),AO14,""),IF(ISNUMBER(AP14),AP14,""),IF(ISNUMBER(AQ14),AQ14,"")) -> 315.0047 | AS14: =AVERAGE(IF(ISNUMBER(AP14),AP14,""),IF(ISNUMBER(AQ14),AQ14,"")) -> 272.56818 | AV14: =CIF!$X$16+VLOOKUP($AV$6&$E14,OCEAN!$E:$J,5,FALSE) -> 76.2043 | AW14: =CIF!$X$17+VLOOKUP($AW$6&$E14,OCEAN!$E:$J,5,FALSE) -> 90.900844 | AX14: =COSTS!C7+COSTS!D7+COSTS!E7 -> 37.941382 | AY14: =COSTS!C7+COSTS!D7+COSTS!E7 -> 37.941382 | AZ14: =COSTS!C7+COSTS!D7+COSTS!E7 -> 37.941382 | BA14: =COSTS!C7+COSTS!D7+COSTS!E7 -> 37.941382 | BB14: =COSTS!C7+COSTS!D7+COSTS!E7 -> 37.941382 | BC14: =COSTS!D7+COSTS!E7+COSTS!F7 -> 99.662715 | BD14: =COSTS!E7+COSTS!F7+COSTS!G7 -> 119.1056 | BE14: =COSTS!F7+COSTS!G7+COSTS!H7 -> 106.17808 | BF14: =COSTS!G7+COSTS!H7+COSTS!I7 -> 80.178082 | BG14: =COSTS!I7+COSTS!J7+COSTS!K7 -> 74 | BH14: =COSTS!O7+COSTS!P7+COSTS!Q7 -> 41 | BI14: =COSTS!F7+COSTS!G7+COSTS!H7 -> 106.17808 | BJ14: =COSTS!F7+COSTS!G7+COSTS!H7 -> 106.17808 | BK14: =COSTS!F7+COSTS!G7+COSTS!H7 -> 106.17808 | BL14: =COSTS!F7+COSTS!G7+COSTS!H7 -> 106.17808 | BM14: =COSTS!F7+COSTS!G7+COSTS!H7 -> 106.17808 | BN14: =COSTS!F7+COSTS!G7+COSTS!H7 -> 106.17808 | BO14: =COSTS!F7+COSTS!G7+COSTS!H7 -> 106.17808 | BP14: =COSTS!F7+COSTS!G7+COSTS!H7 -> 106.17808 | BQ14: =COSTS!F7+COSTS!G7+COSTS!H7 -> 106.17808 | BR14: =COSTS!L7+COSTS!M7+COSTS!N7 -> 174.79452 | BS14: =COSTS!R7+COSTS!S7+COSTS!T7 -> 174 | BT14: =F14+Q14+AB14+AM14+AX14+BI14 -> 1185.7567 | BU14: =G14+R14+AC14+AN14+AY14+BJ14 -> 1181.8032 | BV14: =H14+S14+AD14+AO14+AZ14+BK14 -> 1236.7888 | BW14: =I14+T14+AE14+AP14+BA14+BL14 -> 915.13874 | BX14: =J14+U14+AF14+AQ14+BB14+BM14 -> 764.15309 | BY14: =K14+V14+AG14+AR14+BC14+BN14 -> 1056.784 | BZ14: =L14+W14+AH14+AS14+BD14+BO14 -> 917.94131 | CA14: =M14+X14+AI14+AT14+BE14+BP14 -> 212.35616 | ... CD14: =P14+AA14+AL14+AW14+BH14+BS14 -> 305.90084 | CE14: =BT14-$BT$7 -> -36.714031 | CF14: =BU14-$BU$7 -> -44.331585 | CG14: =BV14-$BV$7 -> -47.772024 | CH14: =BW14-$BW$7 -> -6.4640306 | CI14: =BX14-$BX$7 -> -28.759485 | CJ14: =BY14-$BY$7 -> 32.791394 | CK14: =BZ14-$BZ$7 -> 64.336549 | CN14: =CC14-$CC$7 -> -23.001179 | CO14: =CD14-$CD$7 -> 21.900844
E15: Kwangyang | F15: =$F$7 -> 307.52024 | G15: =$G$7 -> 308.68205 | H15: =$H$7 -> 452.33046 | I15: =$I$7 -> 106.65 | J15: =$J$7 -> 63.672813 | K15: =$K$7 -> 198.76926 | L15: =$L$7 -> 77.998542 | Q15: =$Q$7 -> 192.33066 | R15: =$R$7 -> 294.60561 | S15: =$S$7 -> 205.94276 | T15: =$T$7 -> 212.56873 | U15: =$U$7 -> 222.95739 | V15: =$V$7 -> 211.35138 | W15: =$W$7 -> 219.4945 | AB15: =$AB$7 -> 130.65 | AC15: =$AC$7 -> 130.65 | AD15: =$AD$7 -> 130.65 | AE15: =$AE$7 -> 112.346 | AF15: =$AF$7 -> 127.7216 | AG15: =$AG$7 -> 125.81784 | AH15: =$AH$7 -> 122.5964 | AI15: =$AI$7 -> 0 | AJ15: =$AJ$7 -> 0 | AM15: =CIF!$X$5+VLOOKUP($AM$5&$E15,OCEAN!$E:$J,5,FALSE) -> 473.86364 | AN15: =CIF!$X$6+VLOOKUP($AN$5&$E15,OCEAN!$E:$J,5,FALSE) -> 386.24608 | AO15: =CIF!$X$7+VLOOKUP($AO$5&$E15,OCEAN!$E:$J,5,FALSE) -> 386.24608 | AP15: =CIF!$X$8+VLOOKUP($AP$5&$E15,OCEAN!$E:$J,5,FALSE) -> 401.95455 | AQ15: =CIF!$X$9+VLOOKUP($AQ$5&$E15,OCEAN!$E:$J,5,FALSE) -> 282.27273 | AR15: =AVERAGE(IF(ISNUMBER(AM15),AM15,""),IF(ISNUMBER(AO15),AO15,""),IF(ISNUMBER(AP15),AP15,""),IF(ISNUMBER(AQ15),AQ15,"")) -> 386.08425 | AS15: =AVERAGE(IF(ISNUMBER(AP15),AP15,""),IF(ISNUMBER(AQ15),AQ15,"")) -> 342.11364 | AV15: =CIF!$X$16+VLOOKUP($AV$6&$E15,OCEAN!$E:$J,5,FALSE) -> 76.2043 | AW15: =CIF!$X$17+VLOOKUP($AW$6&$E15,OCEAN!$E:$J,5,FALSE) -> 90.900844 | AX15: =COSTS!C7+COSTS!D6+COSTS!E6 -> 36.580591 | AY15: =COSTS!C7+COSTS!D7+COSTS!E7 -> 37.941382 | AZ15: =COSTS!C7+COSTS!D7+COSTS!E7 -> 37.941382 | BA15: =COSTS!C7+COSTS!D7+COSTS!E7 -> 37.941382 | BB15: =COSTS!C7+COSTS!D7+COSTS!E7 -> 37.941382 | BC15: =COSTS!D7+COSTS!E7+COSTS!F7 -> 99.662715 | BD15: =COSTS!E7+COSTS!F7+COSTS!G7 -> 119.1056 | BE15: =COSTS!F7+COSTS!G7+COSTS!H7 -> 106.17808 | BF15: =COSTS!G7+COSTS!H7+COSTS!I7 -> 80.178082 | BG15: =COSTS!I7+COSTS!J7+COSTS!K7 -> 74 | BH15: =COSTS!O7+COSTS!P7+COSTS!Q7 -> 41 | BI15: =COSTS!F7+COSTS!G7+COSTS!H7 -> 106.17808 | BJ15: =COSTS!F7+COSTS!G7+COSTS!H7 -> 106.17808 | BK15: =COSTS!F7+COSTS!G7+COSTS!H7 -> 106.17808 | BL15: =COSTS!F7+COSTS!G7+COSTS!H7 -> 106.17808 | BM15: =COSTS!F7+COSTS!G7+COSTS!H7 -> 106.17808 | BN15: =COSTS!F7+COSTS!G7+COSTS!H7 -> 106.17808 | BO15: =COSTS!F7+COSTS!G7+COSTS!H7 -> 106.17808 | BP15: =COSTS!F7+COSTS!G7+COSTS!H7 -> 106.17808 | BQ15: =COSTS!F7+COSTS!G7+COSTS!H7 -> 106.17808 | BR15: =COSTS!L7+COSTS!M7+COSTS!N7 -> 174.79452 | BS15: =COSTS!R7+COSTS!S7+COSTS!T7 -> 174 | BT15: =F15+Q15+AB15+AM15+AX15+BI15 -> 1247.1232 | BU15: =G15+R15+AC15+AN15+AY15+BJ15 -> 1264.3032 | BV15: =H15+S15+AD15+AO15+AZ15+BK15 -> 1319.2888 | BW15: =I15+T15+AE15+AP15+BA15+BL15 -> 977.63874 | BX15: =J15+U15+AF15+AQ15+BB15+BM15 -> 840.74399 | BY15: =K15+V15+AG15+AR15+BC15+BN15 -> 1127.8635 | BZ15: =L15+W15+AH15+AS15+BD15+BO15 -> 987.48676 | CA15: =M15+X15+AI15+AT15+BE15+BP15 -> 212.35616 | ... CD15: =P15+AA15+AL15+AW15+BH15+BS15 -> 305.90084 | CE15: =BT15-$BT$7 -> 24.652451 | CF15: =BU15-$BU$7 -> 38.168415 | CG15: =BV15-$BV$7 -> 34.727976 | CH15: =BW15-$BW$7 -> 56.035969 | CI15: =BX15-$BX$7 -> 47.831424 | CJ15: =BY15-$BY$7 -> 103.87094 | CK15: =BZ15-$BZ$7 -> 133.882 | CN15: =CC15-$CC$7 -> -23.001179 | CO15: =CD15-$CD$7 -> 21.900844
A16: Japan | B16: JP | C16: 43 | D16: 14 | E16: Osaka | F16: =$F$7 -> 307.52024 | G16: =$G$7 -> 308.68205 | H16: =$H$7 -> 452.33046 | I16: =$I$7 -> 106.65 | J16: =$J$7 -> 63.672813 | K16: =$K$7 -> 198.76926 | L16: =$L$7 -> 77.998542 | Q16: =$Q$7 -> 192.33066 | R16: =$R$7 -> 294.60561 | S16: =$S$7 -> 205.94276 | T16: =$T$7 -> 212.56873 | U16: =$U$7 -> 222.95739 | V16: =$V$7 -> 211.35138 | W16: =$W$7 -> 219.4945 | AB16: =$AB$7 -> 130.65 | AC16: =$AC$7 -> 130.65 | AD16: =$AD$7 -> 130.65 | AE16: =$AE$7 -> 112.346 | AF16: =$AF$7 -> 127.7216 | AG16: =$AG$7 -> 125.81784 | AH16: =$AH$7 -> 122.5964 | AI16: =$AI$7 -> 0 | AJ16: =$AJ$7 -> 0 | AM16: =CIF!$X$5+VLOOKUP($AM$5&$E16,OCEAN!$E:$J,5,FALSE) -> 467.95455 | AN16: =CIF!$X$6+VLOOKUP($AN$5&$E16,OCEAN!$E:$J,5,FALSE) -> 418.06426 | AO16: =CIF!$X$7+VLOOKUP($AO$5&$E16,OCEAN!$E:$J,5,FALSE) -> 418.06426 | AP16: =CIF!$X$8+VLOOKUP($AP$5&$E16,OCEAN!$E:$J,5,FALSE) -> 428.54545 | AQ16: =CIF!$X$9+VLOOKUP($AQ$5&$E16,OCEAN!$E:$J,5,FALSE) -> 332.95455 | AR16: =AVERAGE(IF(ISNUMBER(AM16),AM16,""),IF(ISNUMBER(AO16),AO16,""),IF(ISNUMBER(AP16),AP16,""),IF(ISNUMBER(AQ16),AQ16,"")) -> 411.8797 | AS16: =AVERAGE(IF(ISNUMBER(AP16),AP16,""),IF(ISNUMBER(AQ16),AQ16,"")) -> 380.75 | AV16: =CIF!$X$16+VLOOKUP($AV$6&$E16,OCEAN!$E:$J,5,FALSE) -> #N/A | AW16: =CIF!$X$17+VLOOKUP($AW$6&$E16,OCEAN!$E:$J,5,FALSE) -> #N/A | AX16: =COSTS!C8+COSTS!D8+COSTS!E8 -> 14.7352 | AY16: =COSTS!C8+COSTS!D8+COSTS!E8 -> 14.7352 | AZ16: =COSTS!C8+COSTS!D8+COSTS!E8 -> 14.7352 | BA16: =COSTS!C8+COSTS!D8+COSTS!E8 -> 14.7352 | BB16: =COSTS!C8+COSTS!D8+COSTS!E8 -> 14.7352 | BC16: =COSTS!D8+COSTS!E8+COSTS!F8 -> 86.7352 | BD16: =COSTS!E8+COSTS!F8+COSTS!G8 -> 106.17808 | BE16: =COSTS!F8+COSTS!G8+COSTS!H8 -> 106.17808 | BF16: =COSTS!G8+COSTS!H8+COSTS!I8 -> 85.178082 | BG16: =COSTS!I8+COSTS!J8+COSTS!K8 -> 86 | BH16: =COSTS!O8+COSTS!P8+COSTS!Q8 -> 48.0888 | BI16: =COSTS!F8+COSTS!G8+COSTS!H8 -> 106.17808 | BJ16: =COSTS!F8+COSTS!G8+COSTS!H8 -> 106.17808 | BK16: =COSTS!F8+COSTS!G8+COSTS!H8 -> 106.17808 | BL16: =COSTS!F8+COSTS!G8+COSTS!H8 -> 106.17808 | BM16: =COSTS!F8+COSTS!G8+COSTS!H8 -> 106.17808 | BN16: =COSTS!F8+COSTS!G8+COSTS!H8 -> 106.17808 | BO16: =COSTS!F8+COSTS!G8+COSTS!H8 -> 106.17808 | BP16: =COSTS!F8+COSTS!G8+COSTS!H8 -> 106.17808 | BQ16: =COSTS!F8+COSTS!G8+COSTS!H8 -> 106.17808 | BR16: =COSTS!L8+COSTS!M8+COSTS!N8 -> 174.79452 | BS16: =COSTS!R8+COSTS!S8+COSTS!T8 -> 174 | BT16: =F16+Q16+AB16+AM16+AX16+BI16 -> 1219.3687 | BU16: =G16+R16+AC16+AN16+AY16+BJ16 -> 1272.9152 | BV16: =H16+S16+AD16+AO16+AZ16+BK16 -> 1327.9008 | BW16: =I16+T16+AE16+AP16+BA16+BL16 -> 981.02346 | BX16: =J16+U16+AF16+AQ16+BB16+BM16 -> 868.21963 | BY16: =K16+V16+AG16+AR16+BC16+BN16 -> 1140.7315 | BZ16: =L16+W16+AH16+AS16+BD16+BO16 -> 1013.1956 | CA16: =M16+X16+AI16+AT16+BE16+BP16 -> 212.35616 | ... CD16: =P16+AA16+AL16+AW16+BH16+BS16 -> #N/A | CE16: =BT16-$BT$7 -> -3.1020307 | CF16: =BU16-$BU$7 -> 46.780414 | CG16: =BV16-$BV$7 -> 43.339976 | CH16: =BW16-$BW$7 -> 59.420697 | CI16: =BX16-$BX$7 -> 75.30706 | CJ16: =BY16-$BY$7 -> 116.73888 | CK16: =BZ16-$BZ$7 -> 159.59085 | CN16: =CC16-$CC$7 -> #N/A | CO16: =CD16-$CD$7 -> #N/A
E17: Kobe | F17: =$F$7 -> 307.52024 | G17: =$G$7 -> 308.68205 | H17: =$H$7 -> 452.33046 | I17: =$I$7 -> 106.65 | J17: =$J$7 -> 63.672813 | K17: =$K$7 -> 198.76926 | L17: =$L$7 -> 77.998542 | Q17: =$Q$7 -> 192.33066 | R17: =$R$7 -> 294.60561 | S17: =$S$7 -> 205.94276 | T17: =$T$7 -> 212.56873 | U17: =$U$7 -> 222.95739 | V17: =$V$7 -> 211.35138 | W17: =$W$7 -> 219.4945 | AB17: =$AB$7 -> 130.65 | AC17: =$AC$7 -> 130.65 | AD17: =$AD$7 -> 130.65 | AE17: =$AE$7 -> 112.346 | AF17: =$AF$7 -> 127.7216 | AG17: =$AG$7 -> 125.81784 | AH17: =$AH$7 -> 122.5964 | AI17: =$AI$7 -> 0 | AJ17: =$AJ$7 -> 0 | AM17: =CIF!$X$5+VLOOKUP($AM$5&$E17,OCEAN!$E:$J,5,FALSE) -> 423.86364 | AN17: =CIF!$X$6+VLOOKUP($AN$5&$E17,OCEAN!$E:$J,5,FALSE) -> 361.24608 | AO17: =CIF!$X$7+VLOOKUP($AO$5&$E17,OCEAN!$E:$J,5,FALSE) -> 361.24608 | AP17: =CIF!$X$8+VLOOKUP($AP$5&$E17,OCEAN!$E:$J,5,FALSE) -> 428.54545 | AQ17: =CIF!$X$9+VLOOKUP($AQ$5&$E17,OCEAN!$E:$J,5,FALSE) -> 248.40909 | AR17: =AVERAGE(IF(ISNUMBER(AM17),AM17,""),IF(ISNUMBER(AO17),AO17,""),IF(ISNUMBER(AP17),AP17,""),IF(ISNUMBER(AQ17),AQ17,"")) -> 365.51607 | AS17: =AVERAGE(IF(ISNUMBER(AP17),AP17,""),IF(ISNUMBER(AQ17),AQ17,"")) -> 338.47727 | AV17: =CIF!$X$16+VLOOKUP($AV$6&$E17,OCEAN!$E:$J,5,FALSE) -> 111.58487 | AW17: =CIF!$X$17+VLOOKUP($AW$6&$E17,OCEAN!$E:$J,5,FALSE) -> 172.72975 | AX17: =COSTS!C8+COSTS!D8+COSTS!E8 -> 14.7352 | AY17: =COSTS!C8+COSTS!D8+COSTS!E8 -> 14.7352 | AZ17: =COSTS!C8+COSTS!D8+COSTS!E8 -> 14.7352 | BA17: =COSTS!C8+COSTS!D8+COSTS!E8 -> 14.7352 | BB17: =COSTS!C8+COSTS!D8+COSTS!E8 -> 14.7352 | BC17: =COSTS!D8+COSTS!E8+COSTS!F8 -> 86.7352 | BD17: =COSTS!E8+COSTS!F8+COSTS!G8 -> 106.17808 | BE17: =COSTS!F8+COSTS!G8+COSTS!H8 -> 106.17808 | BF17: =COSTS!G8+COSTS!H8+COSTS!I8 -> 85.178082 | BG17: =COSTS!I8+COSTS!J8+COSTS!K8 -> 86 | BH17: =COSTS!O8+COSTS!P8+COSTS!Q8 -> 48.0888 | BI17: =COSTS!F8+COSTS!G8+COSTS!H8 -> 106.17808 | BJ17: =COSTS!F8+COSTS!G8+COSTS!H8 -> 106.17808 | BK17: =COSTS!F8+COSTS!G8+COSTS!H8 -> 106.17808 | BL17: =COSTS!F8+COSTS!G8+COSTS!H8 -> 106.17808 | BM17: =COSTS!F8+COSTS!G8+COSTS!H8 -> 106.17808 | BN17: =COSTS!F8+COSTS!G8+COSTS!H8 -> 106.17808 | BO17: =COSTS!F8+COSTS!G8+COSTS!H8 -> 106.17808 | BP17: =COSTS!F8+COSTS!G8+COSTS!H8 -> 106.17808 | BQ17: =COSTS!F8+COSTS!G8+COSTS!H8 -> 106.17808 | BR17: =COSTS!L8+COSTS!M8+COSTS!N8 -> 174.79452 | BS17: =COSTS!R8+COSTS!S8+COSTS!T8 -> 174 | BT17: =F17+Q17+AB17+AM17+AX17+BI17 -> 1175.2778 | BU17: =G17+R17+AC17+AN17+AY17+BJ17 -> 1216.097 | BV17: =H17+S17+AD17+AO17+AZ17+BK17 -> 1271.0826 | BW17: =I17+T17+AE17+AP17+BA17+BL17 -> 981.02346 | BX17: =J17+U17+AF17+AQ17+BB17+BM17 -> 783.67418 | BY17: =K17+V17+AG17+AR17+BC17+BN17 -> 1094.3678 | BZ17: =L17+W17+AH17+AS17+BD17+BO17 -> 970.92288 | CA17: =M17+X17+AI17+AT17+BE17+BP17 -> 212.35616 | ... CD17: =P17+AA17+AL17+AW17+BH17+BS17 -> 394.81855 | CE17: =BT17-$BT$7 -> -47.19294 | CF17: =BU17-$BU$7 -> -10.037767 | CG17: =BV17-$BV$7 -> -13.478206 | CH17: =BW17-$BW$7 -> 59.420697 | CI17: =BX17-$BX$7 -> -9.2383943 | CJ17: =BY17-$BY$7 -> 70.375242 | CK17: =BZ17-$BZ$7 -> 117.31812 | CN17: =CC17-$CC$7 -> 24.379389 | CO17: =CD17-$CD$7 -> 110.81855
E18: Nagoya | F18: =$F$7 -> 307.52024 | G18: =$G$7 -> 308.68205 | H18: =$H$7 -> 452.33046 | I18: =$I$7 -> 106.65 | J18: =$J$7 -> 63.672813 | K18: =$K$7 -> 198.76926 | L18: =$L$7 -> 77.998542 | Q18: =$Q$7 -> 192.33066 | R18: =$R$7 -> 294.60561 | S18: =$S$7 -> 205.94276 | T18: =$T$7 -> 212.56873 | U18: =$U$7 -> 222.95739 | V18: =$V$7 -> 211.35138 | W18: =$W$7 -> 219.4945 | AB18: =$AB$7 -> 130.65 | AC18: =$AC$7 -> 130.65 | AD18: =$AD$7 -> 130.65 | AE18: =$AE$7 -> 112.346 | AF18: =$AF$7 -> 127.7216 | AG18: =$AG$7 -> 125.81784 | AH18: =$AH$7 -> 122.5964 | AI18: =$AI$7 -> 0 | AJ18: =$AJ$7 -> 0 | AM18: =CIF!$X$5+VLOOKUP($AM$5&$E18,OCEAN!$E:$J,5,FALSE) -> 423.86364 | AN18: =CIF!$X$6+VLOOKUP($AN$5&$E18,OCEAN!$E:$J,5,FALSE) -> 361.24608 | AO18: =CIF!$X$7+VLOOKUP($AO$5&$E18,OCEAN!$E:$J,5,FALSE) -> 361.24608 | AP18: =CIF!$X$8+VLOOKUP($AP$5&$E18,OCEAN!$E:$J,5,FALSE) -> 428.54545 | AQ18: =CIF!$X$9+VLOOKUP($AQ$5&$E18,OCEAN!$E:$J,5,FALSE) -> 247.95455 | AR18: =AVERAGE(IF(ISNUMBER(AM18),AM18,""),IF(ISNUMBER(AO18),AO18,""),IF(ISNUMBER(AP18),AP18,""),IF(ISNUMBER(AQ18),AQ18,"")) -> 365.40243 | AS18: =AVERAGE(IF(ISNUMBER(AP18),AP18,""),IF(ISNUMBER(AQ18),AQ18,"")) -> 338.25 | AV18: =CIF!$X$16+VLOOKUP($AV$6&$E18,OCEAN!$E:$J,5,FALSE) -> 111.58487 | AW18: =CIF!$X$17+VLOOKUP($AW$6&$E18,OCEAN!$E:$J,5,FALSE) -> 172.72975 | AX18: =COSTS!C8+COSTS!D8+COSTS!E8 -> 14.7352 | AY18: =COSTS!C8+COSTS!D8+COSTS!E8 -> 14.7352 | AZ18: =COSTS!C8+COSTS!D8+COSTS!E8 -> 14.7352 | BA18: =COSTS!C8+COSTS!D8+COSTS!E8 -> 14.7352 | BB18: =COSTS!C8+COSTS!D8+COSTS!E8 -> 14.7352 | BC18: =COSTS!D8+COSTS!E8+COSTS!F8 -> 86.7352 | BD18: =COSTS!E8+COSTS!F8+COSTS!G8 -> 106.17808 | BE18: =COSTS!F8+COSTS!G8+COSTS!H8 -> 106.17808 | BF18: =COSTS!G8+COSTS!H8+COSTS!I8 -> 85.178082 | BG18: =COSTS!I8+COSTS!J8+COSTS!K8 -> 86 | BH18: =COSTS!O8+COSTS!P8+COSTS!Q8 -> 48.0888 | BI18: =COSTS!F8+COSTS!G8+COSTS!H8 -> 106.17808 | BJ18: =COSTS!F8+COSTS!G8+COSTS!H8 -> 106.17808 | BK18: =COSTS!F8+COSTS!G8+COSTS!H8 -> 106.17808 | BL18: =COSTS!F8+COSTS!G8+COSTS!H8 -> 106.17808 | BM18: =COSTS!F8+COSTS!G8+COSTS!H8 -> 106.17808 | BN18: =COSTS!F8+COSTS!G8+COSTS!H8 -> 106.17808 | BO18: =COSTS!F8+COSTS!G8+COSTS!H8 -> 106.17808 | BP18: =COSTS!F8+COSTS!G8+COSTS!H8 -> 106.17808 | BQ18: =COSTS!F8+COSTS!G8+COSTS!H8 -> 106.17808 | BR18: =COSTS!L8+COSTS!M8+COSTS!N8 -> 174.79452 | BS18: =COSTS!R8+COSTS!S8+COSTS!T8 -> 174 | BT18: =F18+Q18+AB18+AM18+AX18+BI18 -> 1175.2778 | BU18: =G18+R18+AC18+AN18+AY18+BJ18 -> 1216.097 | BV18: =H18+S18+AD18+AO18+AZ18+BK18 -> 1271.0826 | BW18: =I18+T18+AE18+AP18+BA18+BL18 -> 981.02346 | BX18: =J18+U18+AF18+AQ18+BB18+BM18 -> 783.21963 | BY18: =K18+V18+AG18+AR18+BC18+BN18 -> 1094.2542 | BZ18: =L18+W18+AH18+AS18+BD18+BO18 -> 970.69561 | CA18: =M18+X18+AI18+AT18+BE18+BP18 -> 212.35616 | ... CD18: =P18+AA18+AL18+AW18+BH18+BS18 -> 394.81855 | CE18: =BT18-$BT$7 -> -47.19294 | CF18: =BU18-$BU$7 -> -10.037767 | CG18: =BV18-$BV$7 -> -13.478206 | CH18: =BW18-$BW$7 -> 59.420697 | CI18: =BX18-$BX$7 -> -9.6929397 | CJ18: =BY18-$BY$7 -> 70.261606 | CK18: =BZ18-$BZ$7 -> 117.09085 | CN18: =CC18-$CC$7 -> 24.379389 | CO18: =CD18-$CD$7 -> 110.81855
A19: Malaysia | B19: MA | C19: 40 | D19: 14 | E19: Tanjung Pelepas | F19: =$F$7 -> 307.52024 | G19: =$G$7 -> 308.68205 | H19: =$H$7 -> 452.33046 | I19: =$I$7 -> 106.65 | J19: =$J$7 -> 63.672813 | K19: =$K$7 -> 198.76926 | L19: =$L$7 -> 77.998542 | Q19: =$Q$7 -> 192.33066 | R19: =$R$7 -> 294.60561 | S19: =$S$7 -> 205.94276 | T19: =$T$7 -> 212.56873 | U19: =$U$7 -> 222.95739 | V19: =$V$7 -> 211.35138 | W19: =$W$7 -> 219.4945 | AB19: =$AB$7 -> 130.65 | AC19: =$AC$7 -> 130.65 | AD19: =$AD$7 -> 130.65 | AE19: =$AE$7 -> 112.346 | AF19: =$AF$7 -> 127.7216 | AG19: =$AG$7 -> 125.81784 | AH19: =$AH$7 -> 122.5964 | AI19: =$AI$7 -> 0 | AJ19: =$AJ$7 -> 0 | AM19: =CIF!$X$5+VLOOKUP($AM$5&$E19,OCEAN!$E:$J,5,FALSE) -> 644.54545 | AN19: =CIF!$X$6+VLOOKUP($AN$5&$E19,OCEAN!$E:$J,5,FALSE) -> 432.60972 | AO19: =CIF!$X$7+VLOOKUP($AO$5&$E19,OCEAN!$E:$J,5,FALSE) -> 432.60972 | AP19: =CIF!$X$8+VLOOKUP($AP$5&$E19,OCEAN!$E:$J,5,FALSE) -> 478.31818 | AQ19: =CIF!$X$9+VLOOKUP($AQ$5&$E19,OCEAN!$E:$J,5,FALSE) -> 325.22727 | AR19: =AVERAGE(IF(ISNUMBER(AM19),AM19,""),IF(ISNUMBER(AO19),AO19,""),IF(ISNUMBER(AP19),AP19,""),IF(ISNUMBER(AQ19),AQ19,"")) -> 470.17516 | AS19: =AVERAGE(IF(ISNUMBER(AP19),AP19,""),IF(ISNUMBER(AQ19),AQ19,"")) -> 401.77273 | AV19: =CIF!$X$16+VLOOKUP($AV$6&$E19,OCEAN!$E:$J,5,FALSE) -> 162.38773 | AW19: =CIF!$X$17+VLOOKUP($AW$6&$E19,OCEAN!$E:$J,5,FALSE) -> #N/A | AX19: =COSTS!C9+COSTS!D9+COSTS!E9 -> 30.928614 | AY19: =COSTS!C9+COSTS!D9+COSTS!E9 -> 30.928614 | AZ19: =COSTS!C9+COSTS!D9+COSTS!E9 -> 30.928614 | BA19: =COSTS!C9+COSTS!D9+COSTS!E9 -> 30.928614 | BB19: =COSTS!C9+COSTS!D9+COSTS!E9 -> 30.928614 | BC19: =COSTS!C9+COSTS!D9+COSTS!E9 -> 30.928614 | BD19: =COSTS!C9+COSTS!D9+COSTS!E9 -> 30.928614 | BE19: =COSTS!C9+COSTS!D9+COSTS!E9 -> 30.928614 | BF19: =COSTS!C9+COSTS!D9+COSTS!E9 -> 30.928614 | BG19: =COSTS!I9+COSTS!J9+COSTS!K9 -> 78 | BH19: =COSTS!O9+COSTS!P9+COSTS!Q9 -> 45 | BI19: =COSTS!F9+COSTS!G9+COSTS!H9 -> 106.17808 | BJ19: =COSTS!F9+COSTS!G9+COSTS!H9 -> 106.17808 | BK19: =COSTS!F9+COSTS!G9+COSTS!H9 -> 106.17808 | BL19: =COSTS!F9+COSTS!G9+COSTS!H9 -> 106.17808 | BM19: =COSTS!F9+COSTS!G9+COSTS!H9 -> 106.17808 | BN19: =COSTS!F9+COSTS!G9+COSTS!H9 -> 106.17808 | BO19: =COSTS!F9+COSTS!G9+COSTS!H9 -> 106.17808 | BP19: =COSTS!F9+COSTS!G9+COSTS!H9 -> 106.17808 | BQ19: =COSTS!F9+COSTS!G9+COSTS!H9 -> 106.17808 | BR19: =COSTS!L9+COSTS!M9+COSTS!N9 -> 174.79452 | BS19: =COSTS!R9+COSTS!S9+COSTS!T9 -> 174 | BT19: =F19+Q19+AB19+AM19+AX19+BI19 -> 1412.153 | BU19: =G19+R19+AC19+AN19+AY19+BJ19 -> 1303.6541 | BV19: =H19+S19+AD19+AO19+AZ19+BK19 -> 1358.6396 | BW19: =I19+T19+AE19+AP19+BA19+BL19 -> 1046.9896 | BX19: =J19+U19+AF19+AQ19+BB19+BM19 -> 876.68577 | BY19: =K19+V19+AG19+AR19+BC19+BN19 -> 1143.2203 | BZ19: =L19+W19+AH19+AS19+BD19+BO19 -> 958.96887 | CA19: =M19+X19+AI19+AT19+BE19+BP19 -> 137.1067 | ... CD19: =P19+AA19+AL19+AW19+BH19+BS19 -> #N/A | CE19: =BT19-$BT$7 -> 189.68229 | CF19: =BU19-$BU$7 -> 77.519283 | CG19: =BV19-$BV$7 -> 74.078844 | CH19: =BW19-$BW$7 -> 125.38684 | CI19: =BX19-$BX$7 -> 83.773201 | CJ19: =BY19-$BY$7 -> 119.22775 | CK19: =BZ19-$BZ$7 -> 105.36411 | CN19: =CC19-$CC$7 -> 67.182255 | CO19: =CD19-$CD$7 -> #N/A
E20: Penang | F20: =$F$7 -> 307.52024 | G20: =$G$7 -> 308.68205 | H20: =$H$7 -> 452.33046 | I20: =$I$7 -> 106.65 | J20: =$J$7 -> 63.672813 | K20: =$K$7 -> 198.76926 | L20: =$L$7 -> 77.998542 | Q20: =$Q$7 -> 192.33066 | R20: =$R$7 -> 294.60561 | S20: =$S$7 -> 205.94276 | T20: =$T$7 -> 212.56873 | U20: =$U$7 -> 222.95739 | V20: =$V$7 -> 211.35138 | W20: =$W$7 -> 219.4945 | AB20: =$AB$7 -> 130.65 | AC20: =$AC$7 -> 130.65 | AD20: =$AD$7 -> 130.65 | AE20: =$AE$7 -> 112.346 | AF20: =$AF$7 -> 127.7216 | AG20: =$AG$7 -> 125.81784 | AH20: =$AH$7 -> 122.5964 | AI20: =$AI$7 -> 0 | AJ20: =$AJ$7 -> 0 | AM20: =CIF!$X$5+VLOOKUP($AM$5&$E20,OCEAN!$E:$J,5,FALSE) -> 433.86364 | AN20: =CIF!$X$6+VLOOKUP($AN$5&$E20,OCEAN!$E:$J,5,FALSE) -> 460.56426 | AO20: =CIF!$X$7+VLOOKUP($AO$5&$E20,OCEAN!$E:$J,5,FALSE) -> 460.56426 | AP20: =CIF!$X$8+VLOOKUP($AP$5&$E20,OCEAN!$E:$J,5,FALSE) -> 511.27273 | AQ20: =CIF!$X$9+VLOOKUP($AQ$5&$E20,OCEAN!$E:$J,5,FALSE) -> 282.95455 | AR20: =AVERAGE(IF(ISNUMBER(AM20),AM20,""),IF(ISNUMBER(AO20),AO20,""),IF(ISNUMBER(AP20),AP20,""),IF(ISNUMBER(AQ20),AQ20,"")) -> 422.16379 | AS20: =AVERAGE(IF(ISNUMBER(AP20),AP20,""),IF(ISNUMBER(AQ20),AQ20,"")) -> 397.11364 | AV20: =CIF!$X$16+VLOOKUP($AV$6&$E20,OCEAN!$E:$J,5,FALSE) -> 162.38773 | AW20: =CIF!$X$17+VLOOKUP($AW$6&$E20,OCEAN!$E:$J,5,FALSE) -> #N/A | AX20: =COSTS!C9+COSTS!D9+COSTS!E9 -> 30.928614 | AY20: =COSTS!C9+COSTS!D9+COSTS!E9 -> 30.928614 | AZ20: =COSTS!C9+COSTS!D9+COSTS!E9 -> 30.928614 | BA20: =COSTS!C9+COSTS!D9+COSTS!E9 -> 30.928614 | BB20: =COSTS!C9+COSTS!D9+COSTS!E9 -> 30.928614 | BC20: =COSTS!C9+COSTS!D9+COSTS!E9 -> 30.928614 | BD20: =COSTS!C9+COSTS!D9+COSTS!E9 -> 30.928614 | BE20: =COSTS!C9+COSTS!D9+COSTS!E9 -> 30.928614 | BF20: =COSTS!C9+COSTS!D9+COSTS!E9 -> 30.928614 | BG20: =COSTS!I9+COSTS!J9+COSTS!K9 -> 78 | BH20: =COSTS!O9+COSTS!P9+COSTS!Q9 -> 45 | BI20: =COSTS!F9+COSTS!G9+COSTS!H9 -> 106.17808 | BJ20: =COSTS!F9+COSTS!G9+COSTS!H9 -> 106.17808 | BK20: =COSTS!F9+COSTS!G9+COSTS!H9 -> 106.17808 | BL20: =COSTS!F9+COSTS!G9+COSTS!H9 -> 106.17808 | BM20: =COSTS!F9+COSTS!G9+COSTS!H9 -> 106.17808 | BN20: =COSTS!F9+COSTS!G9+COSTS!H9 -> 106.17808 | BO20: =COSTS!F9+COSTS!G9+COSTS!H9 -> 106.17808 | BP20: =COSTS!F9+COSTS!G9+COSTS!H9 -> 106.17808 | BQ20: =COSTS!F9+COSTS!G9+COSTS!H9 -> 106.17808 | BR20: =COSTS!L9+COSTS!M9+COSTS!N9 -> 174.79452 | BS20: =COSTS!R9+COSTS!S9+COSTS!T9 -> 174 | BT20: =F20+Q20+AB20+AM20+AX20+BI20 -> 1201.4712 | BU20: =G20+R20+AC20+AN20+AY20+BJ20 -> 1331.6086 | BV20: =H20+S20+AD20+AO20+AZ20+BK20 -> 1386.5942 | BW20: =I20+T20+AE20+AP20+BA20+BL20 -> 1079.9442 | BX20: =J20+U20+AF20+AQ20+BB20+BM20 -> 834.41304 | BY20: =K20+V20+AG20+AR20+BC20+BN20 -> 1095.209 | BZ20: =L20+W20+AH20+AS20+BD20+BO20 -> 954.30978 | CA20: =M20+X20+AI20+AT20+BE20+BP20 -> 137.1067 | ... CD20: =P20+AA20+AL20+AW20+BH20+BS20 -> #N/A | CE20: =BT20-$BT$7 -> -20.999526 | CF20: =BU20-$BU$7 -> 105.47383 | CG20: =BV20-$BV$7 -> 102.03339 | CH20: =BW20-$BW$7 -> 158.34138 | CI20: =BX20-$BX$7 -> 41.500474 | CJ20: =BY20-$BY$7 -> 71.216383 | CK20: =BZ20-$BZ$7 -> 100.70502 | CN20: =CC20-$CC$7 -> 67.182255 | CO20: =CD20-$CD$7 -> #N/A
E21: Port Klang | F21: =$F$7 -> 307.52024 | G21: =$G$7 -> 308.68205 | H21: =$H$7 -> 452.33046 | I21: =$I$7 -> 106.65 | J21: =$J$7 -> 63.672813 | K21: =$K$7 -> 198.76926 | L21: =$L$7 -> 77.998542 | Q21: =$Q$7 -> 192.33066 | R21: =$R$7 -> 294.60561 | S21: =$S$7 -> 205.94276 | T21: =$T$7 -> 212.56873 | U21: =$U$7 -> 222.95739 | V21: =$V$7 -> 211.35138 | W21: =$W$7 -> 219.4945 | AB21: =$AB$7 -> 130.65 | AC21: =$AC$7 -> 130.65 | AD21: =$AD$7 -> 130.65 | AE21: =$AE$7 -> 112.346 | AF21: =$AF$7 -> 127.7216 | AG21: =$AG$7 -> 125.81784 | AH21: =$AH$7 -> 122.5964 | AI21: =$AI$7 -> 0 | AJ21: =$AJ$7 -> 0 | AM21: =CIF!$X$5+VLOOKUP($AM$5&$E21,OCEAN!$E:$J,5,FALSE) -> 420.22727 | AN21: =CIF!$X$6+VLOOKUP($AN$5&$E21,OCEAN!$E:$J,5,FALSE) -> 349.88245 | AO21: =CIF!$X$7+VLOOKUP($AO$5&$E21,OCEAN!$E:$J,5,FALSE) -> 349.88245 | AP21: =CIF!$X$8+VLOOKUP($AP$5&$E21,OCEAN!$E:$J,5,FALSE) -> 413.54545 | AQ21: =CIF!$X$9+VLOOKUP($AQ$5&$E21,OCEAN!$E:$J,5,FALSE) -> 261.13636 | AR21: =AVERAGE(IF(ISNUMBER(AM21),AM21,""),IF(ISNUMBER(AO21),AO21,""),IF(ISNUMBER(AP21),AP21,""),IF(ISNUMBER(AQ21),AQ21,"")) -> 361.19788 | AS21: =AVERAGE(IF(ISNUMBER(AP21),AP21,""),IF(ISNUMBER(AQ21),AQ21,"")) -> 337.34091 | AV21: =CIF!$X$16+VLOOKUP($AV$6&$E21,OCEAN!$E:$J,5,FALSE) -> 99.791345 | AW21: =CIF!$X$17+VLOOKUP($AW$6&$E21,OCEAN!$E:$J,5,FALSE) -> 90.900844 | AX21: =COSTS!C9+COSTS!D9+COSTS!E9 -> 30.928614 | AY21: =COSTS!C9+COSTS!D9+COSTS!E9 -> 30.928614 | AZ21: =COSTS!C9+COSTS!D9+COSTS!E9 -> 30.928614 | BA21: =COSTS!C9+COSTS!D9+COSTS!E9 -> 30.928614 | BB21: =COSTS!C9+COSTS!D9+COSTS!E9 -> 30.928614 | BC21: =COSTS!C9+COSTS!D9+COSTS!E9 -> 30.928614 | BD21: =COSTS!C9+COSTS!D9+COSTS!E9 -> 30.928614 | BE21: =COSTS!C9+COSTS!D9+COSTS!E9 -> 30.928614 | BF21: =COSTS!C9+COSTS!D9+COSTS!E9 -> 30.928614 | BG21: =COSTS!I9+COSTS!J9+COSTS!K9 -> 78 | BH21: =COSTS!O9+COSTS!P9+COSTS!Q9 -> 45 | BI21: =COSTS!F9+COSTS!G9+COSTS!H9 -> 106.17808 | BJ21: =COSTS!F9+COSTS!G9+COSTS!H9 -> 106.17808 | BK21: =COSTS!F9+COSTS!G9+COSTS!H9 -> 106.17808 | BL21: =COSTS!F9+COSTS!G9+COSTS!H9 -> 106.17808 | BM21: =COSTS!F9+COSTS!G9+COSTS!H9 -> 106.17808 | BN21: =COSTS!F9+COSTS!G9+COSTS!H9 -> 106.17808 | BO21: =COSTS!F9+COSTS!G9+COSTS!H9 -> 106.17808 | BP21: =COSTS!F9+COSTS!G9+COSTS!H9 -> 106.17808 | BQ21: =COSTS!F9+COSTS!G9+COSTS!H9 -> 106.17808 | BR21: =COSTS!L9+COSTS!M9+COSTS!N9 -> 174.79452 | BS21: =COSTS!R9+COSTS!S9+COSTS!T9 -> 174 | BT21: =F21+Q21+AB21+AM21+AX21+BI21 -> 1187.8349 | BU21: =G21+R21+AC21+AN21+AY21+BJ21 -> 1220.9268 | BV21: =H21+S21+AD21+AO21+AZ21+BK21 -> 1275.9124 | BW21: =I21+T21+AE21+AP21+BA21+BL21 -> 982.21688 | BX21: =J21+U21+AF21+AQ21+BB21+BM21 -> 812.59486 | BY21: =K21+V21+AG21+AR21+BC21+BN21 -> 1034.2431 | BZ21: =L21+W21+AH21+AS21+BD21+BO21 -> 894.53705 | CA21: =M21+X21+AI21+AT21+BE21+BP21 -> 137.1067 | ... CD21: =P21+AA21+AL21+AW21+BH21+BS21 -> 309.90084 | CE21: =BT21-$BT$7 -> -34.63589 | CF21: =BU21-$BU$7 -> -5.2079899 | CG21: =BV21-$BV$7 -> -8.6484288 | CH21: =BW21-$BW$7 -> 60.61411 | CI21: =BX21-$BX$7 -> 19.682292 | CJ21: =BY21-$BY$7 -> 10.250474 | CK21: =BZ21-$BZ$7 -> 40.932292 | CN21: =CC21-$CC$7 -> 4.5858659 | CO21: =CD21-$CD$7 -> 25.900844
A22: Taiwan | B22: TW | C22: 45 | D22: 21 | E22: Keelung | F22: =$F$7 -> 307.52024 | G22: =$G$7 -> 308.68205 | H22: =$H$7 -> 452.33046 | I22: =$I$7 -> 106.65 | J22: =$J$7 -> 63.672813 | K22: =$K$7 -> 198.76926 | L22: =$L$7 -> 77.998542 | Q22: =$Q$7 -> 192.33066 | R22: =$R$7 -> 294.60561 | S22: =$S$7 -> 205.94276 | T22: =$T$7 -> 212.56873 | U22: =$U$7 -> 222.95739 | V22: =$V$7 -> 211.35138 | W22: =$W$7 -> 219.4945 | AB22: =$AB$7 -> 130.65 | AC22: =$AC$7 -> 130.65 | AD22: =$AD$7 -> 130.65 | AE22: =$AE$7 -> 112.346 | AF22: =$AF$7 -> 127.7216 | AG22: =$AG$7 -> 125.81784 | AH22: =$AH$7 -> 122.5964 | AI22: =$AI$7 -> 0 | AJ22: =$AJ$7 -> 0 | AM22: =CIF!$X$5+VLOOKUP($AM$5&$E22,OCEAN!$E:$J,5,FALSE) -> 423.86364 | AN22: =CIF!$X$6+VLOOKUP($AN$5&$E22,OCEAN!$E:$J,5,FALSE) -> 304.4279 | AO22: =CIF!$X$7+VLOOKUP($AO$5&$E22,OCEAN!$E:$J,5,FALSE) -> 304.4279 | AP22: =CIF!$X$8+VLOOKUP($AP$5&$E22,OCEAN!$E:$J,5,FALSE) -> 428.31818 | AQ22: =CIF!$X$9+VLOOKUP($AQ$5&$E22,OCEAN!$E:$J,5,FALSE) -> 259.77273 | AR22: =AVERAGE(IF(ISNUMBER(AM22),AM22,""),IF(ISNUMBER(AO22),AO22,""),IF(ISNUMBER(AP22),AP22,""),IF(ISNUMBER(AQ22),AQ22,"")) -> 354.09561 | AS22: =AVERAGE(IF(ISNUMBER(AP22),AP22,""),IF(ISNUMBER(AQ22),AQ22,"")) -> 344.04545 | AV22: =CIF!$X$16+VLOOKUP($AV$6&$E22,OCEAN!$E:$J,5,FALSE) -> 127.00717 | AW22: =CIF!$X$17+VLOOKUP($AW$6&$E22,OCEAN!$E:$J,5,FALSE) -> 135.71623 | AX22: =COSTS!C10+COSTS!D10+COSTS!E10 -> 41.115486 | AY22: =COSTS!C10+COSTS!D10+COSTS!E10 -> 41.115486 | AZ22: =COSTS!C10+COSTS!D10+COSTS!E10 -> 41.115486 | BA22: =COSTS!C10+COSTS!D10+COSTS!E10 -> 41.115486 | BB22: =COSTS!C10+COSTS!D10+COSTS!E10 -> 41.115486 | BC22: =COSTS!C10+COSTS!D10+COSTS!E10 -> 41.115486 | BD22: =COSTS!C10+COSTS!D10+COSTS!E10 -> 41.115486 | BE22: =COSTS!C10+COSTS!D10+COSTS!E10 -> 41.115486 | BF22: =COSTS!C10+COSTS!D10+COSTS!E10 -> 41.115486 | BG22: =COSTS!I10+COSTS!J10+COSTS!K10 -> 74 | BH22: =COSTS!O10+COSTS!P10+COSTS!Q10 -> 51.0888 | BI22: =COSTS!F10+COSTS!G10+COSTS!H10 -> 106.17808 | BJ22: =COSTS!F10+COSTS!G10+COSTS!H10 -> 106.17808 | BK22: =COSTS!F10+COSTS!G10+COSTS!H10 -> 106.17808 | BL22: =COSTS!F10+COSTS!G10+COSTS!H10 -> 106.17808 | BM22: =COSTS!F10+COSTS!G10+COSTS!H10 -> 106.17808 | BN22: =COSTS!F10+COSTS!G10+COSTS!H10 -> 106.17808 | BO22: =COSTS!F10+COSTS!G10+COSTS!H10 -> 106.17808 | BP22: =COSTS!F10+COSTS!G10+COSTS!H10 -> 106.17808 | BQ22: =COSTS!F10+COSTS!G10+COSTS!H10 -> 106.17808 | BR22: =COSTS!L10+COSTS!M10+COSTS!N10 -> 174.79452 | BS22: =COSTS!R10+COSTS!S10+COSTS!T10 -> 174 | BT22: =F22+Q22+AB22+AM22+AX22+BI22 -> 1201.6581 | BU22: =G22+R22+AC22+AN22+AY22+BJ22 -> 1185.6591 | BV22: =H22+S22+AD22+AO22+AZ22+BK22 -> 1240.6447 | BW22: =I22+T22+AE22+AP22+BA22+BL22 -> 1007.1765 | BX22: =J22+U22+AF22+AQ22+BB22+BM22 -> 821.4181 | BY22: =K22+V22+AG22+AR22+BC22+BN22 -> 1037.3277 | BZ22: =L22+W22+AH22+AS22+BD22+BO22 -> 911.42847 | CA22: =M22+X22+AI22+AT22+BE22+BP22 -> 147.29357 | ... CD22: =P22+AA22+AL22+AW22+BH22+BS22 -> 360.80503 | CE22: =BT22-$BT$7 -> -20.812653 | CF22: =BU22-$BU$7 -> -40.475663 | CG22: =BV22-$BV$7 -> -43.916102 | CH22: =BW22-$BW$7 -> 85.57371 | CI22: =BX22-$BX$7 -> 28.505528 | CJ22: =BY22-$BY$7 -> 13.335074 | CK22: =BZ22-$BZ$7 -> 57.82371 | CN22: =CC22-$CC$7 -> 27.801687 | CO22: =CD22-$CD$7 -> 76.80503
E23: Taichung | F23: =$F$7 -> 307.52024 | G23: =$G$7 -> 308.68205 | H23: =$H$7 -> 452.33046 | I23: =$I$7 -> 106.65 | J23: =$J$7 -> 63.672813 | K23: =$K$7 -> 198.76926 | L23: =$L$7 -> 77.998542 | Q23: =$Q$7 -> 192.33066 | R23: =$R$7 -> 294.60561 | S23: =$S$7 -> 205.94276 | T23: =$T$7 -> 212.56873 | U23: =$U$7 -> 222.95739 | V23: =$V$7 -> 211.35138 | W23: =$W$7 -> 219.4945 | AB23: =$AB$7 -> 130.65 | AC23: =$AC$7 -> 130.65 | AD23: =$AD$7 -> 130.65 | AE23: =$AE$7 -> 112.346 | AF23: =$AF$7 -> 127.7216 | AG23: =$AG$7 -> 125.81784 | AH23: =$AH$7 -> 122.5964 | AI23: =$AI$7 -> 0 | AJ23: =$AJ$7 -> 0 | AM23: =CIF!$X$5+VLOOKUP($AM$5&$E23,OCEAN!$E:$J,5,FALSE) -> 435 | AN23: =CIF!$X$6+VLOOKUP($AN$5&$E23,OCEAN!$E:$J,5,FALSE) -> 281.70063 | AO23: =CIF!$X$7+VLOOKUP($AO$5&$E23,OCEAN!$E:$J,5,FALSE) -> 281.70063 | AP23: =CIF!$X$8+VLOOKUP($AP$5&$E23,OCEAN!$E:$J,5,FALSE) -> 407.18182 | AQ23: =CIF!$X$9+VLOOKUP($AQ$5&$E23,OCEAN!$E:$J,5,FALSE) -> 225.68182 | AR23: =AVERAGE(IF(ISNUMBER(AM23),AM23,""),IF(ISNUMBER(AO23),AO23,""),IF(ISNUMBER(AP23),AP23,""),IF(ISNUMBER(AQ23),AQ23,"")) -> 337.39107 | AS23: =AVERAGE(IF(ISNUMBER(AP23),AP23,""),IF(ISNUMBER(AQ23),AQ23,"")) -> 316.43182 | AV23: =CIF!$X$16+VLOOKUP($AV$6&$E23,OCEAN!$E:$J,5,FALSE) -> 180.53162 | AW23: =CIF!$X$17+VLOOKUP($AW$6&$E23,OCEAN!$E:$J,5,FALSE) -> #N/A | AX23: =COSTS!C10+COSTS!D10+COSTS!E10 -> 41.115486 | AY23: =COSTS!C10+COSTS!D10+COSTS!E10 -> 41.115486 | AZ23: =COSTS!C10+COSTS!D10+COSTS!E10 -> 41.115486 | BA23: =COSTS!C10+COSTS!D10+COSTS!E10 -> 41.115486 | BB23: =COSTS!C10+COSTS!D10+COSTS!E10 -> 41.115486 | BC23: =COSTS!C10+COSTS!D10+COSTS!E10 -> 41.115486 | BD23: =COSTS!C10+COSTS!D10+COSTS!E10 -> 41.115486 | BE23: =COSTS!C10+COSTS!D10+COSTS!E10 -> 41.115486 | BF23: =COSTS!C10+COSTS!D10+COSTS!E10 -> 41.115486 | BG23: =COSTS!I10+COSTS!J10+COSTS!K10 -> 74 | BH23: =COSTS!O10+COSTS!P10+COSTS!Q10 -> 51.0888 | BI23: =COSTS!F10+COSTS!G10+COSTS!H10 -> 106.17808 | BJ23: =COSTS!F10+COSTS!G10+COSTS!H10 -> 106.17808 | BK23: =COSTS!F10+COSTS!G10+COSTS!H10 -> 106.17808 | BL23: =COSTS!F10+COSTS!G10+COSTS!H10 -> 106.17808 | BM23: =COSTS!F10+COSTS!G10+COSTS!H10 -> 106.17808 | BN23: =COSTS!F10+COSTS!G10+COSTS!H10 -> 106.17808 | BO23: =COSTS!F10+COSTS!G10+COSTS!H10 -> 106.17808 | BP23: =COSTS!F10+COSTS!G10+COSTS!H10 -> 106.17808 | BQ23: =COSTS!F10+COSTS!G10+COSTS!H10 -> 106.17808 | BR23: =COSTS!L10+COSTS!M10+COSTS!N10 -> 174.79452 | BS23: =COSTS!R10+COSTS!S10+COSTS!T10 -> 174 | BT23: =F23+Q23+AB23+AM23+AX23+BI23 -> 1212.7945 | BU23: =G23+R23+AC23+AN23+AY23+BJ23 -> 1162.9319 | BV23: =H23+S23+AD23+AO23+AZ23+BK23 -> 1217.9174 | BW23: =I23+T23+AE23+AP23+BA23+BL23 -> 986.04011 | BX23: =J23+U23+AF23+AQ23+BB23+BM23 -> 787.32719 | BY23: =K23+V23+AG23+AR23+BC23+BN23 -> 1020.6231 | BZ23: =L23+W23+AH23+AS23+BD23+BO23 -> 883.81483 | CA23: =M23+X23+AI23+AT23+BE23+BP23 -> 147.29357 | ... CD23: =P23+AA23+AL23+AW23+BH23+BS23 -> #N/A | CE23: =BT23-$BT$7 -> -9.6762898 | CF23: =BU23-$BU$7 -> -63.202936 | CG23: =BV23-$BV$7 -> -66.643374 | CH23: =BW23-$BW$7 -> 64.437347 | CI23: =BX23-$BX$7 -> -5.5853807 | CJ23: =BY23-$BY$7 -> -3.3694716 | CK23: =BZ23-$BZ$7 -> 30.210074 | CN23: =CC23-$CC$7 -> 81.326136 | CO23: =CD23-$CD$7 -> #N/A
E24: Kaohsiung | F24: =$F$7 -> 307.52024 | G24: =$G$7 -> 308.68205 | H24: =$H$7 -> 452.33046 | I24: =$I$7 -> 106.65 | J24: =$J$7 -> 63.672813 | K24: =$K$7 -> 198.76926 | L24: =$L$7 -> 77.998542 | Q24: =$Q$7 -> 192.33066 | R24: =$R$7 -> 294.60561 | S24: =$S$7 -> 205.94276 | T24: =$T$7 -> 212.56873 | U24: =$U$7 -> 222.95739 | V24: =$V$7 -> 211.35138 | W24: =$W$7 -> 219.4945 | AB24: =$AB$7 -> 130.65 | AC24: =$AC$7 -> 130.65 | AD24: =$AD$7 -> 130.65 | AE24: =$AE$7 -> 112.346 | AF24: =$AF$7 -> 127.7216 | AG24: =$AG$7 -> 125.81784 | AH24: =$AH$7 -> 122.5964 | AI24: =$AI$7 -> 0 | AJ24: =$AJ$7 -> 0 | AM24: =CIF!$X$5+VLOOKUP($AM$5&$E24,OCEAN!$E:$J,5,FALSE) -> 411.13636 | AN24: =CIF!$X$6+VLOOKUP($AN$5&$E24,OCEAN!$E:$J,5,FALSE) -> 270.33699 | AO24: =CIF!$X$7+VLOOKUP($AO$5&$E24,OCEAN!$E:$J,5,FALSE) -> 270.33699 | AP24: =CIF!$X$8+VLOOKUP($AP$5&$E24,OCEAN!$E:$J,5,FALSE) -> 339.45455 | AQ24: =CIF!$X$9+VLOOKUP($AQ$5&$E24,OCEAN!$E:$J,5,FALSE) -> 214.31818 | AR24: =AVERAGE(IF(ISNUMBER(AM24),AM24,""),IF(ISNUMBER(AO24),AO24,""),IF(ISNUMBER(AP24),AP24,""),IF(ISNUMBER(AQ24),AQ24,"")) -> 308.81152 | AS24: =AVERAGE(IF(ISNUMBER(AP24),AP24,""),IF(ISNUMBER(AQ24),AQ24,"")) -> 276.88636 | AV24: =CIF!$X$16+VLOOKUP($AV$6&$E24,OCEAN!$E:$J,5,FALSE) -> 180.53162 | AW24: =CIF!$X$17+VLOOKUP($AW$6&$E24,OCEAN!$E:$J,5,FALSE) -> #N/A | AX24: =COSTS!C10+COSTS!D10+COSTS!E10 -> 41.115486 | AY24: =COSTS!C10+COSTS!D10+COSTS!E10 -> 41.115486 | AZ24: =COSTS!C10+COSTS!D10+COSTS!E10 -> 41.115486 | BA24: =COSTS!C10+COSTS!D10+COSTS!E10 -> 41.115486 | BB24: =COSTS!C10+COSTS!D10+COSTS!E10 -> 41.115486 | BC24: =COSTS!C10+COSTS!D10+COSTS!E10 -> 41.115486 | BD24: =COSTS!C10+COSTS!D10+COSTS!E10 -> 41.115486 | BE24: =COSTS!C10+COSTS!D10+COSTS!E10 -> 41.115486 | BF24: =COSTS!C10+COSTS!D10+COSTS!E10 -> 41.115486 | BG24: =COSTS!I10+COSTS!J10+COSTS!K10 -> 74 | BH24: =COSTS!O10+COSTS!P10+COSTS!Q10 -> 51.0888 | BI24: =COSTS!F10+COSTS!G10+COSTS!H10 -> 106.17808 | BJ24: =COSTS!F10+COSTS!G10+COSTS!H10 -> 106.17808 | BK24: =COSTS!F10+COSTS!G10+COSTS!H10 -> 106.17808 | BL24: =COSTS!F10+COSTS!G10+COSTS!H10 -> 106.17808 | BM24: =COSTS!F10+COSTS!G10+COSTS!H10 -> 106.17808 | BN24: =COSTS!F10+COSTS!G10+COSTS!H10 -> 106.17808 | BO24: =COSTS!F10+COSTS!G10+COSTS!H10 -> 106.17808 | BP24: =COSTS!F10+COSTS!G10+COSTS!H10 -> 106.17808 | BQ24: =COSTS!F10+COSTS!G10+COSTS!H10 -> 106.17808 | BR24: =COSTS!L10+COSTS!M10+COSTS!N10 -> 174.79452 | BS24: =COSTS!R10+COSTS!S10+COSTS!T10 -> 174 | BT24: =F24+Q24+AB24+AM24+AX24+BI24 -> 1188.9308 | BU24: =G24+R24+AC24+AN24+AY24+BJ24 -> 1151.5682 | BV24: =H24+S24+AD24+AO24+AZ24+BK24 -> 1206.5538 | BW24: =I24+T24+AE24+AP24+BA24+BL24 -> 918.31284 | BX24: =J24+U24+AF24+AQ24+BB24+BM24 -> 775.96355 | BY24: =K24+V24+AG24+AR24+BC24+BN24 -> 992.04358 | BZ24: =L24+W24+AH24+AS24+BD24+BO24 -> 844.26938 | CA24: =M24+X24+AI24+AT24+BE24+BP24 -> 147.29357 | ... CD24: =P24+AA24+AL24+AW24+BH24+BS24 -> #N/A | CE24: =BT24-$BT$7 -> -33.539926 | CF24: =BU24-$BU$7 -> -74.566572 | CG24: =BV24-$BV$7 -> -78.007011 | CH24: =BW24-$BW$7 -> -3.2899261 | CI24: =BX24-$BX$7 -> -16.949017 | CJ24: =BY24-$BY$7 -> -31.949017 | CK24: =BZ24-$BZ$7 -> -9.3353807 | CN24: =CC24-$CC$7 -> 81.326136 | CO24: =CD24-$CD$7 -> #N/A
E25: Tao Yuan | F25: =$F$7 -> 307.52024 | G25: =$G$7 -> 308.68205 | H25: =$H$7 -> 452.33046 | I25: =$I$7 -> 106.65 | J25: =$J$7 -> 63.672813 | K25: =$K$7 -> 198.76926 | L25: =$L$7 -> 77.998542 | Q25: =$Q$7 -> 192.33066 | R25: =$R$7 -> 294.60561 | S25: =$S$7 -> 205.94276 | T25: =$T$7 -> 212.56873 | U25: =$U$7 -> 222.95739 | V25: =$V$7 -> 211.35138 | W25: =$W$7 -> 219.4945 | AB25: =$AB$7 -> 130.65 | AC25: =$AC$7 -> 130.65 | AD25: =$AD$7 -> 130.65 | AE25: =$AE$7 -> 112.346 | AF25: =$AF$7 -> 127.7216 | AG25: =$AG$7 -> 125.81784 | AH25: =$AH$7 -> 122.5964 | AI25: =$AI$7 -> 0 | AJ25: =$AJ$7 -> 0 | AM25: =CIF!$X$5+VLOOKUP($AM$5&$E25,OCEAN!$E:$J,5,FALSE) -> 446.59091 | AN25: =CIF!$X$6+VLOOKUP($AN$5&$E25,OCEAN!$E:$J,5,FALSE) -> 372.60972 | AO25: =CIF!$X$7+VLOOKUP($AO$5&$E25,OCEAN!$E:$J,5,FALSE) -> 372.60972 | AP25: =CIF!$X$8+VLOOKUP($AP$5&$E25,OCEAN!$E:$J,5,FALSE) -> 451.27273 | AQ25: =CIF!$X$9+VLOOKUP($AQ$5&$E25,OCEAN!$E:$J,5,FALSE) -> 263.40909 | AR25: =AVERAGE(IF(ISNUMBER(AM25),AM25,""),IF(ISNUMBER(AO25),AO25,""),IF(ISNUMBER(AP25),AP25,""),IF(ISNUMBER(AQ25),AQ25,"")) -> 383.47061 | AS25: =AVERAGE(IF(ISNUMBER(AP25),AP25,""),IF(ISNUMBER(AQ25),AQ25,"")) -> 357.34091 | AV25: =CIF!$X$16+VLOOKUP($AV$6&$E25,OCEAN!$E:$J,5,FALSE) -> #N/A | AW25: =CIF!$X$17+VLOOKUP($AW$6&$E25,OCEAN!$E:$J,5,FALSE) -> #N/A | AX25: =COSTS!C10+COSTS!D10+COSTS!E10 -> 41.115486 | AY25: =COSTS!C10+COSTS!D10+COSTS!E10 -> 41.115486 | AZ25: =COSTS!C10+COSTS!D10+COSTS!E10 -> 41.115486 | BA25: =COSTS!C10+COSTS!D10+COSTS!E10 -> 41.115486 | BB25: =COSTS!C10+COSTS!D10+COSTS!E10 -> 41.115486 | BC25: =COSTS!C10+COSTS!D10+COSTS!E10 -> 41.115486 | BD25: =COSTS!C10+COSTS!D10+COSTS!E10 -> 41.115486 | BE25: =COSTS!C10+COSTS!D10+COSTS!E10 -> 41.115486 | BF25: =COSTS!C10+COSTS!D10+COSTS!E10 -> 41.115486 | BG25: =COSTS!I10+COSTS!J10+COSTS!K10 -> 74 | BH25: =COSTS!O10+COSTS!P10+COSTS!Q10 -> 51.0888 | BI25: =COSTS!F10+COSTS!G10+COSTS!H10 -> 106.17808 | BJ25: =COSTS!F10+COSTS!G10+COSTS!H10 -> 106.17808 | BK25: =COSTS!F10+COSTS!G10+COSTS!H10 -> 106.17808 | BL25: =COSTS!F10+COSTS!G10+COSTS!H10 -> 106.17808 | BM25: =COSTS!F10+COSTS!G10+COSTS!H10 -> 106.17808 | BN25: =COSTS!F10+COSTS!G10+COSTS!H10 -> 106.17808 | BO25: =COSTS!F10+COSTS!G10+COSTS!H10 -> 106.17808 | BP25: =COSTS!F10+COSTS!G10+COSTS!H10 -> 106.17808 | BQ25: =COSTS!F10+COSTS!G10+COSTS!H10 -> 106.17808 | BR25: =COSTS!L10+COSTS!M10+COSTS!N10 -> 174.79452 | BS25: =COSTS!R10+COSTS!S10+COSTS!T10 -> 174 | BT25: =F25+Q25+AB25+AM25+AX25+BI25 -> 1224.3854 | BU25: =G25+R25+AC25+AN25+AY25+BJ25 -> 1253.841 | BV25: =H25+S25+AD25+AO25+AZ25+BK25 -> 1308.8265 | BW25: =I25+T25+AE25+AP25+BA25+BL25 -> 1030.131 | BX25: =J25+U25+AF25+AQ25+BB25+BM25 -> 825.05446 | BY25: =K25+V25+AG25+AR25+BC25+BN25 -> 1066.7027 | BZ25: =L25+W25+AH25+AS25+BD25+BO25 -> 924.72392 | CA25: =M25+X25+AI25+AT25+BE25+BP25 -> 147.29357 | ... CD25: =P25+AA25+AL25+AW25+BH25+BS25 -> #N/A | CE25: =BT25-$BT$7 -> 1.9146193 | CF25: =BU25-$BU$7 -> 27.706155 | CG25: =BV25-$BV$7 -> 24.265716 | CH25: =BW25-$BW$7 -> 108.52826 | CI25: =BX25-$BX$7 -> 32.141892 | CJ25: =BY25-$BY$7 -> 42.710074 | CK25: =BZ25-$BZ$7 -> 71.119165 | CN25: =CC25-$CC$7 -> #N/A | CO25: =CD25-$CD$7 -> #N/A
A26: Indonesia | B26: ID | C26: 38 | D26: 14 | E26: Jakarta | F26: =$F$7 -> 307.52024 | G26: =$G$7 -> 308.68205 | H26: =$H$7 -> 452.33046 | I26: =$I$7 -> 106.65 | J26: =$J$7 -> 63.672813 | K26: =$K$7 -> 198.76926 | L26: =$L$7 -> 77.998542 | Q26: =$Q$7 -> 192.33066 | R26: =$R$7 -> 294.60561 | S26: =$S$7 -> 205.94276 | T26: =$T$7 -> 212.56873 | U26: =$U$7 -> 222.95739 | V26: =$V$7 -> 211.35138 | W26: =$W$7 -> 219.4945 | AB26: =$AB$7 -> 130.65 | AC26: =$AC$7 -> 130.65 | AD26: =$AD$7 -> 130.65 | AE26: =$AE$7 -> 112.346 | AF26: =$AF$7 -> 127.7216 | AG26: =$AG$7 -> 125.81784 | AH26: =$AH$7 -> 122.5964 | AI26: =$AI$7 -> 0 | AJ26: =$AJ$7 -> 0 | AM26: =CIF!$X$5+VLOOKUP($AM$5&$E26,OCEAN!$E:$J,5,FALSE) -> 469.31818 | AN26: =CIF!$X$6+VLOOKUP($AN$5&$E26,OCEAN!$E:$J,5,FALSE) -> 402.60972 | AO26: =CIF!$X$7+VLOOKUP($AO$5&$E26,OCEAN!$E:$J,5,FALSE) -> 402.60972 | AP26: =CIF!$X$8+VLOOKUP($AP$5&$E26,OCEAN!$E:$J,5,FALSE) -> 461.5 | AQ26: =CIF!$X$9+VLOOKUP($AQ$5&$E26,OCEAN!$E:$J,5,FALSE) -> 327.95455 | AR26: =AVERAGE(IF(ISNUMBER(AM26),AM26,""),IF(ISNUMBER(AO26),AO26,""),IF(ISNUMBER(AP26),AP26,""),IF(ISNUMBER(AQ26),AQ26,"")) -> 415.34561 | AS26: =AVERAGE(IF(ISNUMBER(AP26),AP26,""),IF(ISNUMBER(AQ26),AQ26,"")) -> 394.72727 | AV26: =CIF!$X$16+VLOOKUP($AV$6&$E26,OCEAN!$E:$J,5,FALSE) -> 36.287762 | AW26: =CIF!$X$17+VLOOKUP($AW$6&$E26,OCEAN!$E:$J,5,FALSE) -> 99.791345 | AX26: =COSTS!C11+COSTS!D11+COSTS!E11 -> 49.376721 | AY26: =COSTS!C11+COSTS!D11+COSTS!E11 -> 49.376721 | AZ26: =COSTS!C11+COSTS!D11+COSTS!E11 -> 49.376721 | BA26: =COSTS!C11+COSTS!D11+COSTS!E11 -> 49.376721 | BB26: =COSTS!C11+COSTS!D11+COSTS!E11 -> 49.376721 | BC26: =COSTS!C11+COSTS!D11+COSTS!E11 -> 49.376721 | BD26: =COSTS!C11+COSTS!D11+COSTS!E11 -> 49.376721 | BE26: =COSTS!C11+COSTS!D11+COSTS!E11 -> 49.376721 | BF26: =COSTS!C11+COSTS!D11+COSTS!E11 -> 49.376721 | BG26: =COSTS!I11+COSTS!J11+COSTS!K11 -> 76 | BH26: =COSTS!O11+COSTS!P11+COSTS!Q11 -> 44 | BI26: =COSTS!F11+COSTS!G11+COSTS!H11 -> 106.17808 | BJ26: =COSTS!F11+COSTS!G11+COSTS!H11 -> 106.17808 | BK26: =COSTS!F11+COSTS!G11+COSTS!H11 -> 106.17808 | BL26: =COSTS!F11+COSTS!G11+COSTS!H11 -> 106.17808 | BM26: =COSTS!F11+COSTS!G11+COSTS!H11 -> 106.17808 | BN26: =COSTS!F11+COSTS!G11+COSTS!H11 -> 106.17808 | BO26: =COSTS!F11+COSTS!G11+COSTS!H11 -> 106.17808 | BP26: =COSTS!F11+COSTS!G11+COSTS!H11 -> 106.17808 | BQ26: =COSTS!F11+COSTS!G11+COSTS!H11 -> 106.17808 | BR26: =COSTS!L11+COSTS!M11+COSTS!N11 -> 174.79452 | BS26: =COSTS!R11+COSTS!S11+COSTS!T11 -> 174 | BT26: =F26+Q26+AB26+AM26+AX26+BI26 -> 1255.3739 | BU26: =G26+R26+AC26+AN26+AY26+BJ26 -> 1292.1022 | BV26: =H26+S26+AD26+AO26+AZ26+BK26 -> 1347.0877 | BW26: =I26+T26+AE26+AP26+BA26+BL26 -> 1048.6195 | BX26: =J26+U26+AF26+AQ26+BB26+BM26 -> 897.86115 | BY26: =K26+V26+AG26+AR26+BC26+BN26 -> 1106.8389 | BZ26: =L26+W26+AH26+AS26+BD26+BO26 -> 970.37152 | CA26: =M26+X26+AI26+AT26+BE26+BP26 -> 155.5548 | ... CD26: =P26+AA26+AL26+AW26+BH26+BS26 -> 317.79135 | CE26: =BT26-$BT$7 -> 32.903127 | CF26: =BU26-$BU$7 -> 65.96739 | CG26: =BV26-$BV$7 -> 62.526951 | CH26: =BW26-$BW$7 -> 127.01676 | CI26: =BX26-$BX$7 -> 104.94858 | CJ26: =BY26-$BY$7 -> 82.846308 | CK26: =BZ26-$BZ$7 -> 116.76676 | CN26: =CC26-$CC$7 -> -60.917717 | CO26: =CD26-$CD$7 -> 33.791345
E27: Semarang | F27: =$F$7 -> 307.52024 | G27: =$G$7 -> 308.68205 | H27: =$H$7 -> 452.33046 | I27: =$I$7 -> 106.65 | J27: =$J$7 -> 63.672813 | K27: =$K$7 -> 198.76926 | L27: =$L$7 -> 77.998542 | Q27: =$Q$7 -> 192.33066 | R27: =$R$7 -> 294.60561 | S27: =$S$7 -> 205.94276 | T27: =$T$7 -> 212.56873 | U27: =$U$7 -> 222.95739 | V27: =$V$7 -> 211.35138 | W27: =$W$7 -> 219.4945 | AB27: =$AB$7 -> 130.65 | AC27: =$AC$7 -> 130.65 | AD27: =$AD$7 -> 130.65 | AE27: =$AE$7 -> 112.346 | AF27: =$AF$7 -> 127.7216 | AG27: =$AG$7 -> 125.81784 | AH27: =$AH$7 -> 122.5964 | AI27: =$AI$7 -> 0 | AJ27: =$AJ$7 -> 0 | AM27: =CIF!$X$5+VLOOKUP($AM$5&$E27,OCEAN!$E:$J,5,FALSE) -> 535 | AN27: =CIF!$X$6+VLOOKUP($AN$5&$E27,OCEAN!$E:$J,5,FALSE) -> 402.60972 | AO27: =CIF!$X$7+VLOOKUP($AO$5&$E27,OCEAN!$E:$J,5,FALSE) -> 402.60972 | AP27: =CIF!$X$8+VLOOKUP($AP$5&$E27,OCEAN!$E:$J,5,FALSE) -> 461.5 | AQ27: =CIF!$X$9+VLOOKUP($AQ$5&$E27,OCEAN!$E:$J,5,FALSE) -> 368.86364 | AR27: =AVERAGE(IF(ISNUMBER(AM27),AM27,""),IF(ISNUMBER(AO27),AO27,""),IF(ISNUMBER(AP27),AP27,""),IF(ISNUMBER(AQ27),AQ27,"")) -> 441.99334 | AS27: =AVERAGE(IF(ISNUMBER(AP27),AP27,""),IF(ISNUMBER(AQ27),AQ27,"")) -> 415.18182 | AV27: =CIF!$X$16+VLOOKUP($AV$6&$E27,OCEAN!$E:$J,5,FALSE) -> 87.090629 | AW27: =CIF!$X$17+VLOOKUP($AW$6&$E27,OCEAN!$E:$J,5,FALSE) -> 117.75379 | AX27: =COSTS!C11+COSTS!D11+COSTS!E11 -> 49.376721 | AY27: =COSTS!C11+COSTS!D11+COSTS!E11 -> 49.376721 | AZ27: =COSTS!C11+COSTS!D11+COSTS!E11 -> 49.376721 | BA27: =COSTS!C11+COSTS!D11+COSTS!E11 -> 49.376721 | BB27: =COSTS!C11+COSTS!D11+COSTS!E11 -> 49.376721 | BC27: =COSTS!C11+COSTS!D11+COSTS!E11 -> 49.376721 | BD27: =COSTS!C11+COSTS!D11+COSTS!E11 -> 49.376721 | BE27: =COSTS!C11+COSTS!D11+COSTS!E11 -> 49.376721 | BF27: =COSTS!C11+COSTS!D11+COSTS!E11 -> 49.376721 | BG27: =COSTS!I11+COSTS!J11+COSTS!K11 -> 76 | BH27: =COSTS!O11+COSTS!P11+COSTS!Q11 -> 44 | BI27: =COSTS!F11+COSTS!G11+COSTS!H11 -> 106.17808 | BJ27: =COSTS!F11+COSTS!G11+COSTS!H11 -> 106.17808 | BK27: =COSTS!F11+COSTS!G11+COSTS!H11 -> 106.17808 | BL27: =COSTS!F11+COSTS!G11+COSTS!H11 -> 106.17808 | BM27: =COSTS!F11+COSTS!G11+COSTS!H11 -> 106.17808 | BN27: =COSTS!F11+COSTS!G11+COSTS!H11 -> 106.17808 | BO27: =COSTS!F11+COSTS!G11+COSTS!H11 -> 106.17808 | BP27: =COSTS!F11+COSTS!G11+COSTS!H11 -> 106.17808 | BQ27: =COSTS!F11+COSTS!G11+COSTS!H11 -> 106.17808 | BR27: =COSTS!L11+COSTS!M11+COSTS!N11 -> 174.79452 | BS27: =COSTS!R11+COSTS!S11+COSTS!T11 -> 174 | BT27: =F27+Q27+AB27+AM27+AX27+BI27 -> 1321.0557 | BU27: =G27+R27+AC27+AN27+AY27+BJ27 -> 1292.1022 | BV27: =H27+S27+AD27+AO27+AZ27+BK27 -> 1347.0877 | BW27: =I27+T27+AE27+AP27+BA27+BL27 -> 1048.6195 | BX27: =J27+U27+AF27+AQ27+BB27+BM27 -> 938.77024 | BY27: =K27+V27+AG27+AR27+BC27+BN27 -> 1133.4866 | BZ27: =L27+W27+AH27+AS27+BD27+BO27 -> 990.82607 | CA27: =M27+X27+AI27+AT27+BE27+BP27 -> 155.5548 | ... CD27: =P27+AA27+AL27+AW27+BH27+BS27 -> 335.75379 | CE27: =BT27-$BT$7 -> 98.584945 | CF27: =BU27-$BU$7 -> 65.96739 | CG27: =BV27-$BV$7 -> 62.526951 | CH27: =BW27-$BW$7 -> 127.01676 | CI27: =BX27-$BX$7 -> 145.85767 | CJ27: =BY27-$BY$7 -> 109.49404 | CK27: =BZ27-$BZ$7 -> 137.22131 | CN27: =CC27-$CC$7 -> -10.114851 | CO27: =CD27-$CD$7 -> 51.753788
E28: Cikarang | F28: =$F$7 -> 307.52024 | G28: =$G$7 -> 308.68205 | H28: =$H$7 -> 452.33046 | I28: =$I$7 -> 106.65 | J28: =$J$7 -> 63.672813 | K28: =$K$7 -> 198.76926 | L28: =$L$7 -> 77.998542 | Q28: =$Q$7 -> 192.33066 | R28: =$R$7 -> 294.60561 | S28: =$S$7 -> 205.94276 | T28: =$T$7 -> 212.56873 | U28: =$U$7 -> 222.95739 | V28: =$V$7 -> 211.35138 | W28: =$W$7 -> 219.4945 | AB28: =$AB$7 -> 130.65 | AC28: =$AC$7 -> 130.65 | AD28: =$AD$7 -> 130.65 | AE28: =$AE$7 -> 112.346 | AF28: =$AF$7 -> 127.7216 | AG28: =$AG$7 -> 125.81784 | AH28: =$AH$7 -> 122.5964 | AI28: =$AI$7 -> 0 | AJ28: =$AJ$7 -> 0 | AM28: =CIF!$X$5+VLOOKUP($AM$5&$E28,OCEAN!$E:$J,5,FALSE) -> 580.45455 | AN28: =CIF!$X$6+VLOOKUP($AN$5&$E28,OCEAN!$E:$J,5,FALSE) -> 622.60972 | AO28: =CIF!$X$7+VLOOKUP($AO$5&$E28,OCEAN!$E:$J,5,FALSE) -> 622.60972 | AP28: =CIF!$X$8+VLOOKUP($AP$5&$E28,OCEAN!$E:$J,5,FALSE) -> 573.77273 | AQ28: =CIF!$X$9+VLOOKUP($AQ$5&$E28,OCEAN!$E:$J,5,FALSE) -> 415.22727 | AR28: =AVERAGE(IF(ISNUMBER(AM28),AM28,""),IF(ISNUMBER(AO28),AO28,""),IF(ISNUMBER(AP28),AP28,""),IF(ISNUMBER(AQ28),AQ28,"")) -> 548.01607 | AS28: =AVERAGE(IF(ISNUMBER(AP28),AP28,""),IF(ISNUMBER(AQ28),AQ28,"")) -> 494.5 | AV28: =CIF!$X$16+VLOOKUP($AV$6&$E28,OCEAN!$E:$J,5,FALSE) -> 223.35117 | AW28: =CIF!$X$17+VLOOKUP($AW$6&$E28,OCEAN!$E:$J,5,FALSE) -> #N/A | AX28: =COSTS!C11+COSTS!D11+COSTS!E11 -> 49.376721 | AY28: =COSTS!C11+COSTS!D11+COSTS!E11 -> 49.376721 | AZ28: =COSTS!C11+COSTS!D11+COSTS!E11 -> 49.376721 | BA28: =COSTS!C11+COSTS!D11+COSTS!E11 -> 49.376721 | BB28: =COSTS!C11+COSTS!D11+COSTS!E11 -> 49.376721 | BC28: =COSTS!C11+COSTS!D11+COSTS!E11 -> 49.376721 | BD28: =COSTS!C11+COSTS!D11+COSTS!E11 -> 49.376721 | BE28: =COSTS!C11+COSTS!D11+COSTS!E11 -> 49.376721 | BF28: =COSTS!C11+COSTS!D11+COSTS!E11 -> 49.376721 | BG28: =COSTS!I11+COSTS!J11+COSTS!K11 -> 76 | BH28: =COSTS!O11+COSTS!P11+COSTS!Q11 -> 44 | BI28: =COSTS!F11+COSTS!G11+COSTS!H11 -> 106.17808 | BJ28: =COSTS!F11+COSTS!G11+COSTS!H11 -> 106.17808 | BK28: =COSTS!F11+COSTS!G11+COSTS!H11 -> 106.17808 | BL28: =COSTS!F11+COSTS!G11+COSTS!H11 -> 106.17808 | BM28: =COSTS!F11+COSTS!G11+COSTS!H11 -> 106.17808 | BN28: =COSTS!F11+COSTS!G11+COSTS!H11 -> 106.17808 | BO28: =COSTS!F11+COSTS!G11+COSTS!H11 -> 106.17808 | BP28: =COSTS!F11+COSTS!G11+COSTS!H11 -> 106.17808 | BQ28: =COSTS!F11+COSTS!G11+COSTS!H11 -> 106.17808 | BR28: =COSTS!L11+COSTS!M11+COSTS!N11 -> 174.79452 | BS28: =COSTS!R11+COSTS!S11+COSTS!T11 -> 174 | BT28: =F28+Q28+AB28+AM28+AX28+BI28 -> 1366.5102 | BU28: =G28+R28+AC28+AN28+AY28+BJ28 -> 1512.1022 | BV28: =H28+S28+AD28+AO28+AZ28+BK28 -> 1567.0877 | BW28: =I28+T28+AE28+AP28+BA28+BL28 -> 1160.8923 | BX28: =J28+U28+AF28+AQ28+BB28+BM28 -> 985.13388 | BY28: =K28+V28+AG28+AR28+BC28+BN28 -> 1239.5094 | BZ28: =L28+W28+AH28+AS28+BD28+BO28 -> 1070.1442 | CA28: =M28+X28+AI28+AT28+BE28+BP28 -> 155.5548 | ... CD28: =P28+AA28+AL28+AW28+BH28+BS28 -> #N/A | CE28: =BT28-$BT$7 -> 144.03949 | CF28: =BU28-$BU$7 -> 285.96739 | CG28: =BV28-$BV$7 -> 282.52695 | CH28: =BW28-$BW$7 -> 239.28949 | CI28: =BX28-$BX$7 -> 192.22131 | CJ28: =BY28-$BY$7 -> 215.51676 | CK28: =BZ28-$BZ$7 -> 216.53949 | CN28: =CC28-$CC$7 -> 126.1457 | CO28: =CD28-$CD$7 -> #N/A
E29: Surabaya | F29: =$F$7 -> 307.52024 | G29: =$G$7 -> 308.68205 | H29: =$H$7 -> 452.33046 | I29: =$I$7 -> 106.65 | J29: =$J$7 -> 63.672813 | K29: =$K$7 -> 198.76926 | L29: =$L$7 -> 77.998542 | Q29: =$Q$7 -> 192.33066 | R29: =$R$7 -> 294.60561 | S29: =$S$7 -> 205.94276 | T29: =$T$7 -> 212.56873 | U29: =$U$7 -> 222.95739 | V29: =$V$7 -> 211.35138 | W29: =$W$7 -> 219.4945 | AB29: =$AB$7 -> 130.65 | AC29: =$AC$7 -> 130.65 | AD29: =$AD$7 -> 130.65 | AE29: =$AE$7 -> 112.346 | AF29: =$AF$7 -> 127.7216 | AG29: =$AG$7 -> 125.81784 | AH29: =$AH$7 -> 122.5964 | AI29: =$AI$7 -> 0 | AJ29: =$AJ$7 -> 0 | AM29: =CIF!$X$5+VLOOKUP($AM$5&$E29,OCEAN!$E:$J,5,FALSE) -> 535 | AN29: =CIF!$X$6+VLOOKUP($AN$5&$E29,OCEAN!$E:$J,5,FALSE) -> 402.60972 | AO29: =CIF!$X$7+VLOOKUP($AO$5&$E29,OCEAN!$E:$J,5,FALSE) -> 402.60972 | AP29: =CIF!$X$8+VLOOKUP($AP$5&$E29,OCEAN!$E:$J,5,FALSE) -> 461.5 | AQ29: =CIF!$X$9+VLOOKUP($AQ$5&$E29,OCEAN!$E:$J,5,FALSE) -> 331.81818 | AR29: =AVERAGE(IF(ISNUMBER(AM29),AM29,""),IF(ISNUMBER(AO29),AO29,""),IF(ISNUMBER(AP29),AP29,""),IF(ISNUMBER(AQ29),AQ29,"")) -> 432.73197 | AS29: =AVERAGE(IF(ISNUMBER(AP29),AP29,""),IF(ISNUMBER(AQ29),AQ29,"")) -> 396.65909 | AV29: =CIF!$X$16+VLOOKUP($AV$6&$E29,OCEAN!$E:$J,5,FALSE) -> 87.090629 | AW29: =CIF!$X$17+VLOOKUP($AW$6&$E29,OCEAN!$E:$J,5,FALSE) -> 117.75379 | AX29: =COSTS!C11+COSTS!D11+COSTS!E11 -> 49.376721 | AY29: =COSTS!C11+COSTS!D11+COSTS!E11 -> 49.376721 | AZ29: =COSTS!C11+COSTS!D11+COSTS!E11 -> 49.376721 | BA29: =COSTS!C11+COSTS!D11+COSTS!E11 -> 49.376721 | BB29: =COSTS!C11+COSTS!D11+COSTS!E11 -> 49.376721 | BC29: =COSTS!C11+COSTS!D11+COSTS!E11 -> 49.376721 | BD29: =COSTS!C11+COSTS!D11+COSTS!E11 -> 49.376721 | BE29: =COSTS!C11+COSTS!D11+COSTS!E11 -> 49.376721 | BF29: =COSTS!C11+COSTS!D11+COSTS!E11 -> 49.376721 | BG29: =COSTS!I11+COSTS!J11+COSTS!K11 -> 76 | BH29: =COSTS!O11+COSTS!P11+COSTS!Q11 -> 44 | BI29: =COSTS!F11+COSTS!G11+COSTS!H11 -> 106.17808 | BJ29: =COSTS!F11+COSTS!G11+COSTS!H11 -> 106.17808 | BK29: =COSTS!F11+COSTS!G11+COSTS!H11 -> 106.17808 | BL29: =COSTS!F11+COSTS!G11+COSTS!H11 -> 106.17808 | BM29: =COSTS!F11+COSTS!G11+COSTS!H11 -> 106.17808 | BN29: =COSTS!F11+COSTS!G11+COSTS!H11 -> 106.17808 | BO29: =COSTS!F11+COSTS!G11+COSTS!H11 -> 106.17808 | BP29: =COSTS!F11+COSTS!G11+COSTS!H11 -> 106.17808 | BQ29: =COSTS!F11+COSTS!G11+COSTS!H11 -> 106.17808 | BR29: =COSTS!L11+COSTS!M11+COSTS!N11 -> 174.79452 | BS29: =COSTS!R11+COSTS!S11+COSTS!T11 -> 174 | BT29: =F29+Q29+AB29+AM29+AX29+BI29 -> 1321.0557 | BU29: =G29+R29+AC29+AN29+AY29+BJ29 -> 1292.1022 | BV29: =H29+S29+AD29+AO29+AZ29+BK29 -> 1347.0877 | BW29: =I29+T29+AE29+AP29+BA29+BL29 -> 1048.6195 | BX29: =J29+U29+AF29+AQ29+BB29+BM29 -> 901.72479 | BY29: =K29+V29+AG29+AR29+BC29+BN29 -> 1124.2253 | BZ29: =L29+W29+AH29+AS29+BD29+BO29 -> 972.30334 | CA29: =M29+X29+AI29+AT29+BE29+BP29 -> 155.5548 | ... CD29: =P29+AA29+AL29+AW29+BH29+BS29 -> 335.75379 | CE29: =BT29-$BT$7 -> 98.584945 | CF29: =BU29-$BU$7 -> 65.96739 | CG29: =BV29-$BV$7 -> 62.526951 | CH29: =BW29-$BW$7 -> 127.01676 | CI29: =BX29-$BX$7 -> 108.81222 | CJ29: =BY29-$BY$7 -> 100.23267 | CK29: =BZ29-$BZ$7 -> 118.69858 | CN29: =CC29-$CC$7 -> -10.114851 | CO29: =CD29-$CD$7 -> 51.753788
A30: Thailand | B30: TH | C30: 45 | D30: 14 | E30: Bangkok | F30: =$F$7 -> 307.52024 | G30: =$G$7 -> 308.68205 | H30: =$H$7 -> 452.33046 | I30: =$I$7 -> 106.65 | J30: =$J$7 -> 63.672813 | K30: =$K$7 -> 198.76926 | L30: =$L$7 -> 77.998542 | Q30: =$Q$7 -> 192.33066 | R30: =$R$7 -> 294.60561 | S30: =$S$7 -> 205.94276 | T30: =$T$7 -> 212.56873 | U30: =$U$7 -> 222.95739 | V30: =$V$7 -> 211.35138 | W30: =$W$7 -> 219.4945 | AB30: =$AB$7 -> 130.65 | AC30: =$AC$7 -> 130.65 | AD30: =$AD$7 -> 130.65 | AE30: =$AE$7 -> 112.346 | AF30: =$AF$7 -> 127.7216 | AG30: =$AG$7 -> 125.81784 | AH30: =$AH$7 -> 122.5964 | AI30: =$AI$7 -> 0 | AJ30: =$AJ$7 -> 0 | AM30: =CIF!$X$5+VLOOKUP($AM$5&$E30,OCEAN!$E:$J,5,FALSE) -> 457.95455 | AN30: =CIF!$X$6+VLOOKUP($AN$5&$E30,OCEAN!$E:$J,5,FALSE) -> 386.24608 | AO30: =CIF!$X$7+VLOOKUP($AO$5&$E30,OCEAN!$E:$J,5,FALSE) -> 386.24608 | AP30: =CIF!$X$8+VLOOKUP($AP$5&$E30,OCEAN!$E:$J,5,FALSE) -> 477.63636 | AQ30: =CIF!$X$9+VLOOKUP($AQ$5&$E30,OCEAN!$E:$J,5,FALSE) -> 248.18182 | AR30: =AVERAGE(IF(ISNUMBER(AM30),AM30,""),IF(ISNUMBER(AO30),AO30,""),IF(ISNUMBER(AP30),AP30,""),IF(ISNUMBER(AQ30),AQ30,"")) -> 392.5047 | AS30: =AVERAGE(IF(ISNUMBER(AP30),AP30,""),IF(ISNUMBER(AQ30),AQ30,"")) -> 362.90909 | AV30: =CIF!$X$16+VLOOKUP($AV$6&$E30,OCEAN!$E:$J,5,FALSE) -> 99.791345 | AW30: =CIF!$X$17+VLOOKUP($AW$6&$E30,OCEAN!$E:$J,5,FALSE) -> 144.78817 | AX30: =COSTS!C12+COSTS!D12+COSTS!E12 -> 25.819862 | AY30: =COSTS!C12+COSTS!D12+COSTS!E12 -> 25.819862 | AZ30: =COSTS!C12+COSTS!D12+COSTS!E12 -> 25.819862 | BA30: =COSTS!C12+COSTS!D12+COSTS!E12 -> 25.819862 | BB30: =COSTS!C12+COSTS!D12+COSTS!E12 -> 25.819862 | BC30: =COSTS!C12+COSTS!D12+COSTS!E12 -> 25.819862 | BD30: =COSTS!C12+COSTS!D12+COSTS!E12 -> 25.819862 | BE30: =COSTS!C12+COSTS!D12+COSTS!E12 -> 25.819862 | BF30: =COSTS!C12+COSTS!D12+COSTS!E12 -> 25.819862 | BG30: =COSTS!I12+COSTS!J12+COSTS!K12 -> 78 | BH30: =COSTS!O11+COSTS!P11+COSTS!Q11 -> 44 | BI30: =COSTS!F12+COSTS!G12+COSTS!H12 -> 106.17808 | BJ30: =COSTS!F12+COSTS!G12+COSTS!H12 -> 106.17808 | BK30: =COSTS!F12+COSTS!G12+COSTS!H12 -> 106.17808 | BL30: =COSTS!F12+COSTS!G12+COSTS!H12 -> 106.17808 | BM30: =COSTS!F12+COSTS!G12+COSTS!H12 -> 106.17808 | BN30: =COSTS!F12+COSTS!G12+COSTS!H12 -> 106.17808 | BO30: =COSTS!F12+COSTS!G12+COSTS!H12 -> 106.17808 | BP30: =COSTS!F12+COSTS!G12+COSTS!H12 -> 106.17808 | BQ30: =COSTS!F12+COSTS!G12+COSTS!H12 -> 106.17808 | BR30: =COSTS!L12+COSTS!M12+COSTS!N12 -> 174.79452 | BS30: =COSTS!R12+COSTS!S12+COSTS!T12 -> 174 | BT30: =F30+Q30+AB30+AM30+AX30+BI30 -> 1220.4534 | BU30: =G30+R30+AC30+AN30+AY30+BJ30 -> 1252.1817 | BV30: =H30+S30+AD30+AO30+AZ30+BK30 -> 1307.1672 | BW30: =I30+T30+AE30+AP30+BA30+BL30 -> 1041.199 | BX30: =J30+U30+AF30+AQ30+BB30+BM30 -> 794.53157 | BY30: =K30+V30+AG30+AR30+BC30+BN30 -> 1060.4411 | BZ30: =L30+W30+AH30+AS30+BD30+BO30 -> 914.99648 | CA30: =M30+X30+AI30+AT30+BE30+BP30 -> 131.99794 | ... CD30: =P30+AA30+AL30+AW30+BH30+BS30 -> 362.78817 | CE30: =BT30-$BT$7 -> -2.0173687 | CF30: =BU30-$BU$7 -> 26.046895 | CG30: =BV30-$BV$7 -> 22.606456 | CH30: =BW30-$BW$7 -> 119.59627 | CI30: =BX30-$BX$7 -> 1.6189949 | CJ30: =BY30-$BY$7 -> 36.44854 | CK30: =BZ30-$BZ$7 -> 61.391722 | CN30: =CC30-$CC$7 -> 4.5858659 | CO30: =CD30-$CD$7 -> 78.78817
E31: Lat Krabang | F31: =$F$7 -> 307.52024 | G31: =$G$7 -> 308.68205 | H31: =$H$7 -> 452.33046 | I31: =$I$7 -> 106.65 | J31: =$J$7 -> 63.672813 | K31: =$K$7 -> 198.76926 | L31: =$L$7 -> 77.998542 | Q31: =$Q$7 -> 192.33066 | R31: =$R$7 -> 294.60561 | S31: =$S$7 -> 205.94276 | T31: =$T$7 -> 212.56873 | U31: =$U$7 -> 222.95739 | V31: =$V$7 -> 211.35138 | W31: =$W$7 -> 219.4945 | AB31: =$AB$7 -> 130.65 | AC31: =$AC$7 -> 130.65 | AD31: =$AD$7 -> 130.65 | AE31: =$AE$7 -> 112.346 | AF31: =$AF$7 -> 127.7216 | AG31: =$AG$7 -> 125.81784 | AH31: =$AH$7 -> 122.5964 | AI31: =$AI$7 -> 0 | AJ31: =$AJ$7 -> 0 | AM31: =CIF!$X$5+VLOOKUP($AM$5&$E31,OCEAN!$E:$J,5,FALSE) -> 457.95455 | AN31: =CIF!$X$6+VLOOKUP($AN$5&$E31,OCEAN!$E:$J,5,FALSE) -> 372.60972 | AO31: =CIF!$X$7+VLOOKUP($AO$5&$E31,OCEAN!$E:$J,5,FALSE) -> 372.60972 | AP31: =CIF!$X$8+VLOOKUP($AP$5&$E31,OCEAN!$E:$J,5,FALSE) -> 401.27273 | AQ31: =CIF!$X$9+VLOOKUP($AQ$5&$E31,OCEAN!$E:$J,5,FALSE) -> 261.59091 | AR31: =AVERAGE(IF(ISNUMBER(AM31),AM31,""),IF(ISNUMBER(AO31),AO31,""),IF(ISNUMBER(AP31),AP31,""),IF(ISNUMBER(AQ31),AQ31,"")) -> 373.35697 | AS31: =AVERAGE(IF(ISNUMBER(AP31),AP31,""),IF(ISNUMBER(AQ31),AQ31,"")) -> 331.43182 | AV31: =CIF!$X$16+VLOOKUP($AV$6&$E31,OCEAN!$E:$J,5,FALSE) -> 179.80586 | AW31: =CIF!$X$17+VLOOKUP($AW$6&$E31,OCEAN!$E:$J,5,FALSE) -> 90.900844 | AX31: =COSTS!C12+COSTS!D12+COSTS!E12 -> 25.819862 | AY31: =COSTS!C12+COSTS!D12+COSTS!E12 -> 25.819862 | AZ31: =COSTS!C12+COSTS!D12+COSTS!E12 -> 25.819862 | BA31: =COSTS!C12+COSTS!D12+COSTS!E12 -> 25.819862 | BB31: =COSTS!C12+COSTS!D12+COSTS!E12 -> 25.819862 | BC31: =COSTS!C12+COSTS!D12+COSTS!E12 -> 25.819862 | BD31: =COSTS!C12+COSTS!D12+COSTS!E12 -> 25.819862 | BE31: =COSTS!C12+COSTS!D12+COSTS!E12 -> 25.819862 | BF31: =COSTS!C12+COSTS!D12+COSTS!E12 -> 25.819862 | BG31: =COSTS!I12+COSTS!J12+COSTS!K12 -> 78 | BH31: =COSTS!I12+COSTS!J12+COSTS!K12 -> 78 | BI31: =COSTS!F12+COSTS!G12+COSTS!H12 -> 106.17808 | BJ31: =COSTS!F12+COSTS!G12+COSTS!H12 -> 106.17808 | BK31: =COSTS!F12+COSTS!G12+COSTS!H12 -> 106.17808 | BL31: =COSTS!F12+COSTS!G12+COSTS!H12 -> 106.17808 | BM31: =COSTS!F12+COSTS!G12+COSTS!H12 -> 106.17808 | BN31: =COSTS!F12+COSTS!G12+COSTS!H12 -> 106.17808 | BO31: =COSTS!F12+COSTS!G12+COSTS!H12 -> 106.17808 | BP31: =COSTS!F12+COSTS!G12+COSTS!H12 -> 106.17808 | BQ31: =COSTS!F12+COSTS!G12+COSTS!H12 -> 106.17808 | BR31: =COSTS!L12+COSTS!M12+COSTS!N12 -> 174.79452 | BS31: =COSTS!R12+COSTS!S12+COSTS!T12 -> 174 | BT31: =F31+Q31+AB31+AM31+AX31+BI31 -> 1220.4534 | BU31: =G31+R31+AC31+AN31+AY31+BJ31 -> 1238.5453 | BV31: =H31+S31+AD31+AO31+AZ31+BK31 -> 1293.5309 | BW31: =I31+T31+AE31+AP31+BA31+BL31 -> 964.8354 | BX31: =J31+U31+AF31+AQ31+BB31+BM31 -> 807.94066 | BY31: =K31+V31+AG31+AR31+BC31+BN31 -> 1041.2934 | BZ31: =L31+W31+AH31+AS31+BD31+BO31 -> 883.51921 | CA31: =M31+X31+AI31+AT31+BE31+BP31 -> 131.99794 | ... CD31: =P31+AA31+AL31+AW31+BH31+BS31 -> 342.90084 | CE31: =BT31-$BT$7 -> -2.0173687 | CF31: =BU31-$BU$7 -> 12.410531 | CG31: =BV31-$BV$7 -> 8.9700921 | CH31: =BW31-$BW$7 -> 43.232631 | CI31: =BX31-$BX$7 -> 15.028086 | CJ31: =BY31-$BY$7 -> 17.300813 | CK31: =BZ31-$BZ$7 -> 29.914449 | CN31: =CC31-$CC$7 -> 84.600381 | CO31: =CD31-$CD$7 -> 58.900844
E32: Laem Chabang | F32: =$F$7 -> 307.52024 | G32: =$G$7 -> 308.68205 | H32: =$H$7 -> 452.33046 | I32: =$I$7 -> 106.65 | J32: =$J$7 -> 63.672813 | K32: =$K$7 -> 198.76926 | L32: =$L$7 -> 77.998542 | Q32: =$Q$7 -> 192.33066 | R32: =$R$7 -> 294.60561 | S32: =$S$7 -> 205.94276 | T32: =$T$7 -> 212.56873 | U32: =$U$7 -> 222.95739 | V32: =$V$7 -> 211.35138 | W32: =$W$7 -> 219.4945 | AB32: =$AB$7 -> 130.65 | AC32: =$AC$7 -> 130.65 | AD32: =$AD$7 -> 130.65 | AE32: =$AE$7 -> 112.346 | AF32: =$AF$7 -> 127.7216 | AG32: =$AG$7 -> 125.81784 | AH32: =$AH$7 -> 122.5964 | AI32: =$AI$7 -> 0 | AJ32: =$AJ$7 -> 0 | AM32: =CIF!$X$5+VLOOKUP($AM$5&$E32,OCEAN!$E:$J,5,FALSE) -> 469.31818 | AN32: =CIF!$X$6+VLOOKUP($AN$5&$E32,OCEAN!$E:$J,5,FALSE) -> 409.65517 | AO32: =CIF!$X$7+VLOOKUP($AO$5&$E32,OCEAN!$E:$J,5,FALSE) -> 409.65517 | AP32: =CIF!$X$8+VLOOKUP($AP$5&$E32,OCEAN!$E:$J,5,FALSE) -> 439.90909 | AQ32: =CIF!$X$9+VLOOKUP($AQ$5&$E32,OCEAN!$E:$J,5,FALSE) -> 252.27273 | AR32: =AVERAGE(IF(ISNUMBER(AM32),AM32,""),IF(ISNUMBER(AO32),AO32,""),IF(ISNUMBER(AP32),AP32,""),IF(ISNUMBER(AQ32),AQ32,"")) -> 392.78879 | AS32: =AVERAGE(IF(ISNUMBER(AP32),AP32,""),IF(ISNUMBER(AQ32),AQ32,"")) -> 346.09091 | AV32: =CIF!$X$16+VLOOKUP($AV$6&$E32,OCEAN!$E:$J,5,FALSE) -> 90.719405 | AW32: =CIF!$X$17+VLOOKUP($AW$6&$E32,OCEAN!$E:$J,5,FALSE) -> 90.900844 | AX32: =COSTS!C12+COSTS!D12+COSTS!E12 -> 25.819862 | AY32: =COSTS!C12+COSTS!D12+COSTS!E12 -> 25.819862 | AZ32: =COSTS!C12+COSTS!D12+COSTS!E12 -> 25.819862 | BA32: =COSTS!C12+COSTS!D12+COSTS!E12 -> 25.819862 | BB32: =COSTS!C12+COSTS!D12+COSTS!E12 -> 25.819862 | BC32: =COSTS!C12+COSTS!D12+COSTS!E12 -> 25.819862 | BD32: =COSTS!C12+COSTS!D12+COSTS!E12 -> 25.819862 | BE32: =COSTS!C12+COSTS!D12+COSTS!E12 -> 25.819862 | BF32: =COSTS!C12+COSTS!D12+COSTS!E12 -> 25.819862 | BG32: =COSTS!I12+COSTS!J12+COSTS!K12 -> 78 | BH32: =COSTS!I12+COSTS!J12+COSTS!K12 -> 78 | BI32: =COSTS!F12+COSTS!G12+COSTS!H12 -> 106.17808 | BJ32: =COSTS!F12+COSTS!G12+COSTS!H12 -> 106.17808 | BK32: =COSTS!F12+COSTS!G12+COSTS!H12 -> 106.17808 | BL32: =COSTS!F12+COSTS!G12+COSTS!H12 -> 106.17808 | BM32: =COSTS!F12+COSTS!G12+COSTS!H12 -> 106.17808 | BN32: =COSTS!F12+COSTS!G12+COSTS!H12 -> 106.17808 | BO32: =COSTS!F12+COSTS!G12+COSTS!H12 -> 106.17808 | BP32: =COSTS!F12+COSTS!G12+COSTS!H12 -> 106.17808 | BQ32: =COSTS!F12+COSTS!G12+COSTS!H12 -> 106.17808 | BR32: =COSTS!L12+COSTS!M12+COSTS!N12 -> 174.79452 | BS32: =COSTS!R12+COSTS!S12+COSTS!T12 -> 174 | BT32: =F32+Q32+AB32+AM32+AX32+BI32 -> 1231.817 | BU32: =G32+R32+AC32+AN32+AY32+BJ32 -> 1275.5908 | BV32: =H32+S32+AD32+AO32+AZ32+BK32 -> 1330.5763 | BW32: =I32+T32+AE32+AP32+BA32+BL32 -> 1003.4718 | BX32: =J32+U32+AF32+AQ32+BB32+BM32 -> 798.62247 | BY32: =K32+V32+AG32+AR32+BC32+BN32 -> 1060.7252 | BZ32: =L32+W32+AH32+AS32+BD32+BO32 -> 898.1783 | CA32: =M32+X32+AI32+AT32+BE32+BP32 -> 131.99794 | ... CD32: =P32+AA32+AL32+AW32+BH32+BS32 -> 342.90084 | CE32: =BT32-$BT$7 -> 9.3462676 | CF32: =BU32-$BU$7 -> 49.455986 | CG32: =BV32-$BV$7 -> 46.015547 | CH32: =BW32-$BW$7 -> 81.868995 | CI32: =BX32-$BX$7 -> 5.709904 | CJ32: =BY32-$BY$7 -> 36.732631 | CK32: =BZ32-$BZ$7 -> 44.57354 | CN32: =CC32-$CC$7 -> -4.4860746 | CO32: =CD32-$CD$7 -> 58.900844
A33: Bangladesh | B33: BD | C33: 52 | D33: 14 | E33: Chittagong | F33: =$F$7 -> 307.52024 | G33: =$G$7 -> 308.68205 | H33: =$H$7 -> 452.33046 | I33: =$I$7 -> 106.65 | J33: =$J$7 -> 63.672813 | K33: =$K$7 -> 198.76926 | L33: =$L$7 -> 77.998542 | Q33: =$Q$7 -> 192.33066 | R33: =$R$7 -> 294.60561 | S33: =$S$7 -> 205.94276 | T33: =$T$7 -> 212.56873 | U33: =$U$7 -> 222.95739 | V33: =$V$7 -> 211.35138 | W33: =$W$7 -> 219.4945 | AB33: =$AB$7 -> 130.65 | AC33: =$AC$7 -> 130.65 | AD33: =$AD$7 -> 130.65 | AE33: =$AE$7 -> 112.346 | AF33: =$AF$7 -> 127.7216 | AG33: =$AG$7 -> 125.81784 | AH33: =$AH$7 -> 122.5964 | AI33: =$AI$7 -> 0 | AJ33: =$AJ$7 -> 0 | AM33: =CIF!$X$5+VLOOKUP($AM$5&$E33,OCEAN!$E:$J,5,FALSE) -> 787.5 | AN33: =CIF!$X$6+VLOOKUP($AN$5&$E33,OCEAN!$E:$J,5,FALSE) -> 645.33699 | AO33: =CIF!$X$7+VLOOKUP($AO$5&$E33,OCEAN!$E:$J,5,FALSE) -> 645.33699 | AP33: =CIF!$X$8+VLOOKUP($AP$5&$E33,OCEAN!$E:$J,5,FALSE) -> 667.18182 | AQ33: =CIF!$X$9+VLOOKUP($AQ$5&$E33,OCEAN!$E:$J,5,FALSE) -> 560.90909 | AR33: =AVERAGE(IF(ISNUMBER(AM33),AM33,""),IF(ISNUMBER(AO33),AO33,""),IF(ISNUMBER(AP33),AP33,""),IF(ISNUMBER(AQ33),AQ33,"")) -> 665.23197 | AS33: =AVERAGE(IF(ISNUMBER(AP33),AP33,""),IF(ISNUMBER(AQ33),AQ33,"")) -> 614.04545 | AV33: =CIF!$X$16+VLOOKUP($AV$6&$E33,OCEAN!$E:$J,5,FALSE) -> 237.68484 | AW33: =CIF!$X$17+VLOOKUP($AW$6&$E33,OCEAN!$E:$J,5,FALSE) -> 290.66497 | AX33: =COSTS!C13+COSTS!D13+COSTS!E13 -> 124.52994 | AY33: =COSTS!C13+COSTS!D13+COSTS!E13 -> 124.52994 | AZ33: =COSTS!C13+COSTS!D13+COSTS!E13 -> 124.52994 | BA33: =COSTS!C13+COSTS!D13+COSTS!E13 -> 124.52994 | BB33: =COSTS!C13+COSTS!D13+COSTS!E13 -> 124.52994 | BC33: =COSTS!C13+COSTS!D13+COSTS!E13 -> 124.52994 | BD33: =COSTS!C13+COSTS!D13+COSTS!E13 -> 124.52994 | BE33: =COSTS!C13+COSTS!D13+COSTS!E13 -> 124.52994 | BF33: =COSTS!C13+COSTS!D13+COSTS!E13 -> 124.52994 | BG33: =COSTS!I13+COSTS!J13+COSTS!K13 -> 138 | BH33: =COSTS!I12+COSTS!J12+COSTS!K12 -> 78 | BI33: =COSTS!F13+COSTS!G13+COSTS!H13 -> 117.39726 | BJ33: =COSTS!F13+COSTS!G13+COSTS!H13 -> 117.39726 | BK33: =COSTS!F13+COSTS!G13+COSTS!H13 -> 117.39726 | BL33: =COSTS!F13+COSTS!G13+COSTS!H13 -> 117.39726 | BM33: =COSTS!F13+COSTS!G13+COSTS!H13 -> 117.39726 | BN33: =COSTS!F13+COSTS!G13+COSTS!H13 -> 117.39726 | BO33: =COSTS!F13+COSTS!G13+COSTS!H13 -> 117.39726 | BP33: =COSTS!F13+COSTS!G13+COSTS!H13 -> 117.39726 | BQ33: =COSTS!F13+COSTS!G13+COSTS!H13 -> 117.39726 | BR33: =COSTS!L13+COSTS!M13+COSTS!N13 -> 174.79452 | BS33: =COSTS!R13+COSTS!S13+COSTS!T13 -> 174 | BT33: =F33+Q33+AB33+AM33+AX33+BI33 -> 1659.9281 | BU33: =G33+R33+AC33+AN33+AY33+BJ33 -> 1621.2019 | BV33: =H33+S33+AD33+AO33+AZ33+BK33 -> 1676.1874 | BW33: =I33+T33+AE33+AP33+BA33+BL33 -> 1340.6737 | BX33: =J33+U33+AF33+AQ33+BB33+BM33 -> 1217.1881 | BY33: =K33+V33+AG33+AR33+BC33+BN33 -> 1443.0977 | BZ33: =L33+W33+AH33+AS33+BD33+BO33 -> 1276.0621 | CA33: =M33+X33+AI33+AT33+BE33+BP33 -> 241.9272 | ... CD33: =P33+AA33+AL33+AW33+BH33+BS33 -> 542.66497 | CE33: =BT33-$BT$7 -> 437.45734 | CF33: =BU33-$BU$7 -> 395.06706 | CG33: =BV33-$BV$7 -> 391.62662 | CH33: =BW33-$BW$7 -> 419.07098 | CI33: =BX33-$BX$7 -> 424.27552 | CJ33: =BY33-$BY$7 -> 419.10507 | CK33: =BZ33-$BZ$7 -> 422.45734 | CN33: =CC33-$CC$7 -> 202.47936 | CO33: =CD33-$CD$7 -> 258.66497
A34: Pakistan | B34: PK | C34: 45 | D34: 14 | E34: Port Qasim/Karachi | F34: =$F$7 -> 307.52024 | G34: =$G$7 -> 308.68205 | H34: =$H$7 -> 452.33046 | I34: =$I$7 -> 106.65 | J34: =$J$7 -> 63.672813 | K34: =$K$7 -> 198.76926 | L34: =$L$7 -> 77.998542 | Q34: =$Q$7 -> 192.33066 | R34: =$R$7 -> 294.60561 | S34: =$S$7 -> 205.94276 | T34: =$T$7 -> 212.56873 | U34: =$U$7 -> 222.95739 | V34: =$V$7 -> 211.35138 | W34: =$W$7 -> 219.4945 | AB34: =$AB$7 -> 130.65 | AC34: =$AC$7 -> 130.65 | AD34: =$AD$7 -> 130.65 | AE34: =$AE$7 -> 112.346 | AF34: =$AF$7 -> 127.7216 | AG34: =$AG$7 -> 125.81784 | AH34: =$AH$7 -> 122.5964 | AI34: =$AI$7 -> 0 | AJ34: =$AJ$7 -> 0 | AM34: =CIF!$X$5+VLOOKUP($AM$5&$E34,OCEAN!$E:$J,5,FALSE) -> 889.09091 | AN34: =CIF!$X$6+VLOOKUP($AN$5&$E34,OCEAN!$E:$J,5,FALSE) -> 629.20063 | AO34: =CIF!$X$7+VLOOKUP($AO$5&$E34,OCEAN!$E:$J,5,FALSE) -> 629.20063 | AP34: =CIF!$X$8+VLOOKUP($AP$5&$E34,OCEAN!$E:$J,5,FALSE) -> 564.22727 | AQ34: =CIF!$X$9+VLOOKUP($AQ$5&$E34,OCEAN!$E:$J,5,FALSE) -> 405 | AR34: =AVERAGE(IF(ISNUMBER(AM34),AM34,""),IF(ISNUMBER(AO34),AO34,""),IF(ISNUMBER(AP34),AP34,""),IF(ISNUMBER(AQ34),AQ34,"")) -> 621.8797 | AS34: =AVERAGE(IF(ISNUMBER(AP34),AP34,""),IF(ISNUMBER(AQ34),AQ34,"")) -> 484.61364 | AV34: =CIF!$X$16+VLOOKUP($AV$6&$E34,OCEAN!$E:$J,5,FALSE) -> 72.575524 | AW34: =CIF!$X$17+VLOOKUP($AW$6&$E34,OCEAN!$E:$J,5,FALSE) -> 472.10378 | AX34: =COSTS!C14+COSTS!D14+COSTS!E14 -> 201.70382 | AY34: =COSTS!C14+COSTS!D14+COSTS!E14 -> 201.70382 | AZ34: =COSTS!C14+COSTS!D14+COSTS!E14 -> 201.70382 | BA34: =COSTS!C14+COSTS!D14+COSTS!E14 -> 201.70382 | BB34: =COSTS!C14+COSTS!D14+COSTS!E14 -> 201.70382 | BC34: =COSTS!C14+COSTS!D14+COSTS!E14 -> 201.70382 | BD34: =COSTS!C14+COSTS!D14+COSTS!E14 -> 201.70382 | BE34: =COSTS!C14+COSTS!D14+COSTS!E14 -> 201.70382 | BF34: =COSTS!C14+COSTS!D14+COSTS!E14 -> 201.70382 | BG34: =COSTS!I14+COSTS!J14+COSTS!K14 -> 104 | BH34: =COSTS!O13+COSTS!P13+COSTS!Q13 -> 106 | BI34: =COSTS!F14+COSTS!G14+COSTS!H14 -> 117.39726 | BJ34: =COSTS!F14+COSTS!G14+COSTS!H14 -> 117.39726 | BK34: =COSTS!F14+COSTS!G14+COSTS!H14 -> 117.39726 | BL34: =COSTS!F14+COSTS!G14+COSTS!H14 -> 117.39726 | BM34: =COSTS!F14+COSTS!G14+COSTS!H14 -> 117.39726 | BN34: =COSTS!F14+COSTS!G14+COSTS!H14 -> 117.39726 | BO34: =COSTS!F14+COSTS!G14+COSTS!H14 -> 117.39726 | BP34: =COSTS!F14+COSTS!G14+COSTS!H14 -> 117.39726 | BQ34: =COSTS!F14+COSTS!G14+COSTS!H14 -> 117.39726 | BR34: =COSTS!L14+COSTS!M14+COSTS!N14 -> 174.79452 | BS34: =COSTS!R14+COSTS!S14+COSTS!T14 -> 174 | BT34: =F34+Q34+AB34+AM34+AX34+BI34 -> 1838.6929 | BU34: =G34+R34+AC34+AN34+AY34+BJ34 -> 1682.2394 | BV34: =H34+S34+AD34+AO34+AZ34+BK34 -> 1737.2249 | BW34: =I34+T34+AE34+AP34+BA34+BL34 -> 1314.8931 | BX34: =J34+U34+AF34+AQ34+BB34+BM34 -> 1138.4529 | BY34: =K34+V34+AG34+AR34+BC34+BN34 -> 1476.9193 | BZ34: =L34+W34+AH34+AS34+BD34+BO34 -> 1223.8042 | CA34: =M34+X34+AI34+AT34+BE34+BP34 -> 319.10108 | ... CD34: =P34+AA34+AL34+AW34+BH34+BS34 -> 752.10378 | CE34: =BT34-$BT$7 -> 616.22213 | CF34: =BU34-$BU$7 -> 456.10457 | CG34: =BV34-$BV$7 -> 452.66413 | CH34: =BW34-$BW$7 -> 393.29031 | CI34: =BX34-$BX$7 -> 345.54031 | CJ34: =BY34-$BY$7 -> 452.92667 | CK34: =BZ34-$BZ$7 -> 370.1994 | CN34: =CC34-$CC$7 -> 3.3700445 | CO34: =CD34-$CD$7 -> 468.10378
A35: India | B35: IN | C35: 50 | D35: 14 | E35: Mundra | F35: =$F$7 -> 307.52024 | G35: =$G$7 -> 308.68205 | H35: =$H$7 -> 452.33046 | I35: =$I$7 -> 106.65 | J35: =$J$7 -> 63.672813 | K35: =$K$7 -> 198.76926 | L35: =$L$7 -> 77.998542 | Q35: =$Q$7 -> 192.33066 | R35: =$R$7 -> 294.60561 | S35: =$S$7 -> 205.94276 | T35: =$T$7 -> 212.56873 | U35: =$U$7 -> 222.95739 | V35: =$V$7 -> 211.35138 | W35: =$W$7 -> 219.4945 | AB35: =$AB$7 -> 130.65 | AC35: =$AC$7 -> 130.65 | AD35: =$AD$7 -> 130.65 | AE35: =$AE$7 -> 112.346 | AF35: =$AF$7 -> 127.7216 | AG35: =$AG$7 -> 125.81784 | AH35: =$AH$7 -> 122.5964 | AI35: =$AI$7 -> 0 | AJ35: =$AJ$7 -> 0 | AM35: =CIF!$X$5+VLOOKUP($AM$5&$E35,OCEAN!$E:$J,5,FALSE) -> 755.68182 | AN35: =CIF!$X$6+VLOOKUP($AN$5&$E35,OCEAN!$E:$J,5,FALSE) -> 593.29154 | AO35: =CIF!$X$7+VLOOKUP($AO$5&$E35,OCEAN!$E:$J,5,FALSE) -> 593.29154 | AP35: =CIF!$X$8+VLOOKUP($AP$5&$E35,OCEAN!$E:$J,5,FALSE) -> 503.31818 | AQ35: =CIF!$X$9+VLOOKUP($AQ$5&$E35,OCEAN!$E:$J,5,FALSE) -> 359.54545 | AR35: =AVERAGE(IF(ISNUMBER(AM35),AM35,""),IF(ISNUMBER(AO35),AO35,""),IF(ISNUMBER(AP35),AP35,""),IF(ISNUMBER(AQ35),AQ35,"")) -> 552.95925 | AS35: =AVERAGE(IF(ISNUMBER(AP35),AP35,""),IF(ISNUMBER(AQ35),AQ35,"")) -> 431.43182 | AV35: =CIF!$X$16+VLOOKUP($AV$6&$E35,OCEAN!$E:$J,5,FALSE) -> 219.54096 | AW35: =CIF!$X$17+VLOOKUP($AW$6&$E35,OCEAN!$E:$J,5,FALSE) -> 299.37404 | AX35: =COSTS!C15+COSTS!D15+COSTS!E15 -> 42.784802 | AY35: =COSTS!C15+COSTS!D15+COSTS!E15 -> 42.784802 | AZ35: =COSTS!C15+COSTS!D15+COSTS!E15 -> 42.784802 | BA35: =COSTS!C15+COSTS!D15+COSTS!E15 -> 42.784802 | BB35: =COSTS!C15+COSTS!D15+COSTS!E15 -> 42.784802 | BC35: =COSTS!C15+COSTS!D15+COSTS!E15 -> 42.784802 | BD35: =COSTS!C15+COSTS!D15+COSTS!E15 -> 42.784802 | BE35: =COSTS!C15+COSTS!D15+COSTS!E15 -> 42.784802 | BF35: =COSTS!C15+COSTS!D15+COSTS!E15 -> 42.784802 | BG35: =COSTS!I15+COSTS!J15+COSTS!K15 -> 105 | BH35: =COSTS!O14+COSTS!P14+COSTS!Q14 -> 64.0888 | BI35: =COSTS!F15+COSTS!G15+COSTS!H15 -> 117.39726 | BJ35: =COSTS!F15+COSTS!G15+COSTS!H15 -> 117.39726 | BK35: =COSTS!F15+COSTS!G15+COSTS!H15 -> 117.39726 | BL35: =COSTS!F15+COSTS!G15+COSTS!H15 -> 117.39726 | BM35: =COSTS!F15+COSTS!G15+COSTS!H15 -> 117.39726 | BN35: =COSTS!F15+COSTS!G15+COSTS!H15 -> 117.39726 | BO35: =COSTS!F15+COSTS!G15+COSTS!H15 -> 117.39726 | BP35: =COSTS!F15+COSTS!G15+COSTS!H15 -> 117.39726 | BQ35: =COSTS!F15+COSTS!G15+COSTS!H15 -> 117.39726 | BR35: =COSTS!L15+COSTS!M15+COSTS!N15 -> 187.26027 | BS35: =COSTS!R15+COSTS!S15+COSTS!T15 -> 234 | BT35: =F35+Q35+AB35+AM35+AX35+BI35 -> 1546.3648 | BU35: =G35+R35+AC35+AN35+AY35+BJ35 -> 1487.4113 | BV35: =H35+S35+AD35+AO35+AZ35+BK35 -> 1542.3968 | BW35: =I35+T35+AE35+AP35+BA35+BL35 -> 1095.065 | BX35: =J35+U35+AF35+AQ35+BB35+BM35 -> 934.07932 | BY35: =K35+V35+AG35+AR35+BC35+BN35 -> 1249.0798 | BZ35: =L35+W35+AH35+AS35+BD35+BO35 -> 1011.7033 | CA35: =M35+X35+AI35+AT35+BE35+BP35 -> 160.18206 | ... CD35: =P35+AA35+AL35+AW35+BH35+BS35 -> 597.46284 | CE35: =BT35-$BT$7 -> 323.89402 | CF35: =BU35-$BU$7 -> 261.27647 | CG35: =BV35-$BV$7 -> 257.83603 | CH35: =BW35-$BW$7 -> 173.4622 | CI35: =BX35-$BX$7 -> 141.16675 | CJ35: =BY35-$BY$7 -> 225.0872 | CK35: =BZ35-$BZ$7 -> 158.09857 | CN35: =CC35-$CC$7 -> 163.80123 | CO35: =CD35-$CD$7 -> 313.46284
E36: Tuticorin | F36: =$F$7 -> 307.52024 | G36: =$G$7 -> 308.68205 | H36: =$H$7 -> 452.33046 | I36: =$I$7 -> 106.65 | J36: =$J$7 -> 63.672813 | K36: =$K$7 -> 198.76926 | L36: =$L$7 -> 77.998542 | Q36: =$Q$7 -> 192.33066 | R36: =$R$7 -> 294.60561 | S36: =$S$7 -> 205.94276 | T36: =$T$7 -> 212.56873 | U36: =$U$7 -> 222.95739 | V36: =$V$7 -> 211.35138 | W36: =$W$7 -> 219.4945 | AB36: =$AB$7 -> 130.65 | AC36: =$AC$7 -> 130.65 | AD36: =$AD$7 -> 130.65 | AE36: =$AE$7 -> 112.346 | AF36: =$AF$7 -> 127.7216 | AG36: =$AG$7 -> 125.81784 | AH36: =$AH$7 -> 122.5964 | AI36: =$AI$7 -> 0 | AJ36: =$AJ$7 -> 0 | AM36: =CIF!$X$5+VLOOKUP($AM$5&$E36,OCEAN!$E:$J,5,FALSE) -> 547.5 | AN36: =CIF!$X$6+VLOOKUP($AN$5&$E36,OCEAN!$E:$J,5,FALSE) -> 592.83699 | AO36: =CIF!$X$7+VLOOKUP($AO$5&$E36,OCEAN!$E:$J,5,FALSE) -> 592.83699 | AP36: =CIF!$X$8+VLOOKUP($AP$5&$E36,OCEAN!$E:$J,5,FALSE) -> 614.68182 | AQ36: =CIF!$X$9+VLOOKUP($AQ$5&$E36,OCEAN!$E:$J,5,FALSE) -> 512.5 | AR36: =AVERAGE(IF(ISNUMBER(AM36),AM36,""),IF(ISNUMBER(AO36),AO36,""),IF(ISNUMBER(AP36),AP36,""),IF(ISNUMBER(AQ36),AQ36,"")) -> 566.8797 | AS36: =AVERAGE(IF(ISNUMBER(AP36),AP36,""),IF(ISNUMBER(AQ36),AQ36,"")) -> 563.59091 | AV36: =CIF!$X$16+VLOOKUP($AV$6&$E36,OCEAN!$E:$J,5,FALSE) -> 219.54096 | AW36: =CIF!$X$17+VLOOKUP($AW$6&$E36,OCEAN!$E:$J,5,FALSE) -> 326.40842 | AX36: =COSTS!C15+COSTS!D15+COSTS!E15 -> 42.784802 | AY36: =COSTS!C15+COSTS!D15+COSTS!E15 -> 42.784802 | AZ36: =COSTS!C15+COSTS!D15+COSTS!E15 -> 42.784802 | BA36: =COSTS!C15+COSTS!D15+COSTS!E15 -> 42.784802 | BB36: =COSTS!C15+COSTS!D15+COSTS!E15 -> 42.784802 | BC36: =COSTS!C15+COSTS!D15+COSTS!E15 -> 42.784802 | BD36: =COSTS!C15+COSTS!D15+COSTS!E15 -> 42.784802 | BE36: =COSTS!C15+COSTS!D15+COSTS!E15 -> 42.784802 | BF36: =COSTS!C15+COSTS!D15+COSTS!E15 -> 42.784802 | BG36: =COSTS!I15+COSTS!J15+COSTS!K15 -> 105 | BH36: =COSTS!O15+COSTS!P15+COSTS!Q15 -> 60.0888 | BI36: =COSTS!F15+COSTS!G15+COSTS!H15 -> 117.39726 | BJ36: =COSTS!F15+COSTS!G15+COSTS!H15 -> 117.39726 | BK36: =COSTS!F15+COSTS!G15+COSTS!H15 -> 117.39726 | BL36: =COSTS!F15+COSTS!G15+COSTS!H15 -> 117.39726 | BM36: =COSTS!F15+COSTS!G15+COSTS!H15 -> 117.39726 | BN36: =COSTS!F15+COSTS!G15+COSTS!H15 -> 117.39726 | BO36: =COSTS!F15+COSTS!G15+COSTS!H15 -> 117.39726 | BP36: =COSTS!F15+COSTS!G15+COSTS!H15 -> 117.39726 | BQ36: =COSTS!F15+COSTS!G15+COSTS!H15 -> 117.39726 | BR36: =COSTS!L15+COSTS!M15+COSTS!N15 -> 187.26027 | BS36: =COSTS!R15+COSTS!S15+COSTS!T15 -> 234 | BT36: =F36+Q36+AB36+AM36+AX36+BI36 -> 1338.183 | BU36: =G36+R36+AC36+AN36+AY36+BJ36 -> 1486.9567 | BV36: =H36+S36+AD36+AO36+AZ36+BK36 -> 1541.9423 | BW36: =I36+T36+AE36+AP36+BA36+BL36 -> 1206.4286 | BX36: =J36+U36+AF36+AQ36+BB36+BM36 -> 1087.0339 | BY36: =K36+V36+AG36+AR36+BC36+BN36 -> 1263.0003 | BZ36: =L36+W36+AH36+AS36+BD36+BO36 -> 1143.8624 | CA36: =M36+X36+AI36+AT36+BE36+BP36 -> 160.18206 | ... CD36: =P36+AA36+AL36+AW36+BH36+BS36 -> 620.49722 | CE36: =BT36-$BT$7 -> 115.7122 | CF36: =BU36-$BU$7 -> 260.82192 | CG36: =BV36-$BV$7 -> 257.38148 | CH36: =BW36-$BW$7 -> 284.82584 | CI36: =BX36-$BX$7 -> 294.1213 | CJ36: =BY36-$BY$7 -> 239.00766 | CK36: =BZ36-$BZ$7 -> 290.25766 | CN36: =CC36-$CC$7 -> 163.80123 | CO36: =CD36-$CD$7 -> 336.49722
E37: Nhava Sheva | F37: =$F$7 -> 307.52024 | G37: =$G$7 -> 308.68205 | H37: =$H$7 -> 452.33046 | I37: =$I$7 -> 106.65 | J37: =$J$7 -> 63.672813 | K37: =$K$7 -> 198.76926 | L37: =$L$7 -> 77.998542 | Q37: =$Q$7 -> 192.33066 | R37: =$R$7 -> 294.60561 | S37: =$S$7 -> 205.94276 | T37: =$T$7 -> 212.56873 | U37: =$U$7 -> 222.95739 | V37: =$V$7 -> 211.35138 | W37: =$W$7 -> 219.4945 | AB37: =$AB$7 -> 130.65 | AC37: =$AC$7 -> 130.65 | AD37: =$AD$7 -> 130.65 | AE37: =$AE$7 -> 112.346 | AF37: =$AF$7 -> 127.7216 | AG37: =$AG$7 -> 125.81784 | AH37: =$AH$7 -> 122.5964 | AI37: =$AI$7 -> 0 | AJ37: =$AJ$7 -> 0 | AM37: =CIF!$X$5+VLOOKUP($AM$5&$E37,OCEAN!$E:$J,5,FALSE) -> 520.22727 | AN37: =CIF!$X$6+VLOOKUP($AN$5&$E37,OCEAN!$E:$J,5,FALSE) -> 519.65517 | AO37: =CIF!$X$7+VLOOKUP($AO$5&$E37,OCEAN!$E:$J,5,FALSE) -> 519.65517 | AP37: =CIF!$X$8+VLOOKUP($AP$5&$E37,OCEAN!$E:$J,5,FALSE) -> 503.31818 | AQ37: =CIF!$X$9+VLOOKUP($AQ$5&$E37,OCEAN!$E:$J,5,FALSE) -> 359.54545 | AR37: =AVERAGE(IF(ISNUMBER(AM37),AM37,""),IF(ISNUMBER(AO37),AO37,""),IF(ISNUMBER(AP37),AP37,""),IF(ISNUMBER(AQ37),AQ37,"")) -> 475.68652 | AS37: =AVERAGE(IF(ISNUMBER(AP37),AP37,""),IF(ISNUMBER(AQ37),AQ37,"")) -> 431.43182 | AV37: =CIF!$X$16+VLOOKUP($AV$6&$E37,OCEAN!$E:$J,5,FALSE) -> 219.54096 | AW37: =CIF!$X$17+VLOOKUP($AW$6&$E37,OCEAN!$E:$J,5,FALSE) -> 299.37404 | AX37: =COSTS!C15+COSTS!D15+COSTS!E15 -> 42.784802 | AY37: =COSTS!C15+COSTS!D15+COSTS!E15 -> 42.784802 | AZ37: =COSTS!C15+COSTS!D15+COSTS!E15 -> 42.784802 | BA37: =COSTS!C15+COSTS!D15+COSTS!E15 -> 42.784802 | BB37: =COSTS!C15+COSTS!D15+COSTS!E15 -> 42.784802 | BC37: =COSTS!C15+COSTS!D15+COSTS!E15 -> 42.784802 | BD37: =COSTS!C15+COSTS!D15+COSTS!E15 -> 42.784802 | BE37: =COSTS!C15+COSTS!D15+COSTS!E15 -> 42.784802 | BF37: =COSTS!C15+COSTS!D15+COSTS!E15 -> 42.784802 | BG37: =COSTS!I15+COSTS!J15+COSTS!K15 -> 105 | BH37: =COSTS!O15+COSTS!P15+COSTS!Q15 -> 60.0888 | BI37: =COSTS!F15+COSTS!G15+COSTS!H15 -> 117.39726 | BJ37: =COSTS!F15+COSTS!G15+COSTS!H15 -> 117.39726 | BK37: =COSTS!F15+COSTS!G15+COSTS!H15 -> 117.39726 | BL37: =COSTS!F15+COSTS!G15+COSTS!H15 -> 117.39726 | BM37: =COSTS!F15+COSTS!G15+COSTS!H15 -> 117.39726 | BN37: =COSTS!F15+COSTS!G15+COSTS!H15 -> 117.39726 | BO37: =COSTS!F15+COSTS!G15+COSTS!H15 -> 117.39726 | BP37: =COSTS!F15+COSTS!G15+COSTS!H15 -> 117.39726 | BQ37: =COSTS!F15+COSTS!G15+COSTS!H15 -> 117.39726 | BR37: =COSTS!L15+COSTS!M15+COSTS!N15 -> 187.26027 | BS37: =COSTS!R15+COSTS!S15+COSTS!T15 -> 234 | BT37: =F37+Q37+AB37+AM37+AX37+BI37 -> 1310.9102 | BU37: =G37+R37+AC37+AN37+AY37+BJ37 -> 1413.7749 | BV37: =H37+S37+AD37+AO37+AZ37+BK37 -> 1468.7605 | BW37: =I37+T37+AE37+AP37+BA37+BL37 -> 1095.065 | BX37: =J37+U37+AF37+AQ37+BB37+BM37 -> 934.07932 | BY37: =K37+V37+AG37+AR37+BC37+BN37 -> 1171.8071 | BZ37: =L37+W37+AH37+AS37+BD37+BO37 -> 1011.7033 | CA37: =M37+X37+AI37+AT37+BE37+BP37 -> 160.18206 | ... CD37: =P37+AA37+AL37+AW37+BH37+BS37 -> 593.46284 | CE37: =BT37-$BT$7 -> 88.439477 | CF37: =BU37-$BU$7 -> 187.6401 | CG37: =BV37-$BV$7 -> 184.19967 | CH37: =BW37-$BW$7 -> 173.4622 | CI37: =BX37-$BX$7 -> 141.16675 | CJ37: =BY37-$BY$7 -> 147.81448 | CK37: =BZ37-$BZ$7 -> 158.09857 | CN37: =CC37-$CC$7 -> 163.80123 | CO37: =CD37-$CD$7 -> 309.46284
A38: Turkey | B38: TR | C38: 37 | D38: 14 | E38: Iskenderun | F38: =$F$7 -> 307.52024 | G38: =$G$7 -> 308.68205 | H38: =$H$7 -> 452.33046 | I38: =$I$7 -> 106.65 | J38: =$J$7 -> 63.672813 | K38: =$K$7 -> 198.76926 | L38: =$L$7 -> 77.998542 | Q38: =$Q$7 -> 192.33066 | R38: =$R$7 -> 294.60561 | S38: =$S$7 -> 205.94276 | T38: =$T$7 -> 212.56873 | U38: =$U$7 -> 222.95739 | V38: =$V$7 -> 211.35138 | W38: =$W$7 -> 219.4945 | AB38: =$AB$7 -> 130.65 | AC38: =$AC$7 -> 130.65 | AD38: =$AD$7 -> 130.65 | AE38: =$AE$7 -> 112.346 | AF38: =$AF$7 -> 127.7216 | AG38: =$AG$7 -> 125.81784 | AH38: =$AH$7 -> 122.5964 | AI38: =$AI$7 -> 0 | AJ38: =$AJ$7 -> 0 | AM38: =CIF!$X$5+VLOOKUP($AM$5&$E38,OCEAN!$E:$J,5,FALSE) -> 787.5 | AN38: =CIF!$X$6+VLOOKUP($AN$5&$E38,OCEAN!$E:$J,5,FALSE) -> 638.74608 | AO38: =CIF!$X$7+VLOOKUP($AO$5&$E38,OCEAN!$E:$J,5,FALSE) -> 638.74608 | AP38: =CIF!$X$8+VLOOKUP($AP$5&$E38,OCEAN!$E:$J,5,FALSE) -> 570.59091 | AQ38: =CIF!$X$9+VLOOKUP($AQ$5&$E38,OCEAN!$E:$J,5,FALSE) -> 377.04545 | AR38: =AVERAGE(IF(ISNUMBER(AM38),AM38,""),IF(ISNUMBER(AO38),AO38,""),IF(ISNUMBER(AP38),AP38,""),IF(ISNUMBER(AQ38),AQ38,"")) -> 593.47061 | AS38: =AVERAGE(IF(ISNUMBER(AP38),AP38,""),IF(ISNUMBER(AQ38),AQ38,"")) -> 473.81818 | AV38: =CIF!$X$16+VLOOKUP($AV$6&$E38,OCEAN!$E:$J,5,FALSE) -> 254.01433 | AW38: =CIF!$X$17+VLOOKUP($AW$6&$E38,OCEAN!$E:$J,5,FALSE) -> 707.61136 | AX38: =COSTS!C16+COSTS!D16+COSTS!E16 -> 87.973924 | AY38: =COSTS!C16+COSTS!D16+COSTS!E16 -> 87.973924 | AZ38: =COSTS!C16+COSTS!D16+COSTS!E16 -> 87.973924 | BA38: =COSTS!C16+COSTS!D16+COSTS!E16 -> 87.973924 | BB38: =COSTS!C16+COSTS!D16+COSTS!E16 -> 87.973924 | BC38: =COSTS!C16+COSTS!D16+COSTS!E16 -> 87.973924 | BD38: =COSTS!C16+COSTS!D16+COSTS!E16 -> 87.973924 | BE38: =COSTS!C16+COSTS!D16+COSTS!E16 -> 87.973924 | BF38: =COSTS!C16+COSTS!D16+COSTS!E16 -> 87.973924 | BG38: =COSTS!I16+COSTS!J16+COSTS!K16 -> 110 | BH38: =COSTS!O16+COSTS!P16+COSTS!Q16 -> 48.0888 | BI38: =COSTS!F16+COSTS!G16+COSTS!H16 -> 123.63014 | BJ38: =COSTS!F16+COSTS!G16+COSTS!H16 -> 123.63014 | BK38: =COSTS!F16+COSTS!G16+COSTS!H16 -> 123.63014 | BL38: =COSTS!F16+COSTS!G16+COSTS!H16 -> 123.63014 | BM38: =COSTS!F16+COSTS!G16+COSTS!H16 -> 123.63014 | BN38: =COSTS!F16+COSTS!G16+COSTS!H16 -> 123.63014 | BO38: =COSTS!F16+COSTS!G16+COSTS!H16 -> 123.63014 | BP38: =COSTS!F16+COSTS!G16+COSTS!H16 -> 123.63014 | BQ38: =COSTS!F16+COSTS!G16+COSTS!H16 -> 123.63014 | BR38: =COSTS!L16+COSTS!M16+COSTS!N16 -> 187.26027 | BS38: =COSTS!M16+COSTS!N16+COSTS!O16 -> 128.26027 | BT38: =F38+Q38+AB38+AM38+AX38+BI38 -> 1629.605 | BU38: =G38+R38+AC38+AN38+AY38+BJ38 -> 1584.2878 | BV38: =H38+S38+AD38+AO38+AZ38+BK38 -> 1639.2734 | BW38: =I38+T38+AE38+AP38+BA38+BL38 -> 1213.7597 | BX38: =J38+U38+AF38+AQ38+BB38+BM38 -> 1003.0013 | BY38: =K38+V38+AG38+AR38+BC38+BN38 -> 1341.0132 | BZ38: =L38+W38+AH38+AS38+BD38+BO38 -> 1105.5117 | CA38: =M38+X38+AI38+AT38+BE38+BP38 -> 211.60406 | ... CD38: =P38+AA38+AL38+AW38+BH38+BS38 -> 883.96043 | CE38: =BT38-$BT$7 -> 407.1342 | CF38: =BU38-$BU$7 -> 358.15301 | CG38: =BV38-$BV$7 -> 354.71257 | CH38: =BW38-$BW$7 -> 292.15693 | CI38: =BX38-$BX$7 -> 210.08875 | CJ38: =BY38-$BY$7 -> 317.02057 | CK38: =BZ38-$BZ$7 -> 251.90693 | CN38: T | CO38: =CD38-$CD$7 -> 599.96043
E39: Mersin | F39: =$F$7 -> 307.52024 | G39: =$G$7 -> 308.68205 | H39: =$H$7 -> 452.33046 | I39: =$I$7 -> 106.65 | J39: =$J$7 -> 63.672813 | K39: =$K$7 -> 198.76926 | L39: =$L$7 -> 77.998542 | Q39: =$Q$7 -> 192.33066 | R39: =$R$7 -> 294.60561 | S39: =$S$7 -> 205.94276 | T39: =$T$7 -> 212.56873 | U39: =$U$7 -> 222.95739 | V39: =$V$7 -> 211.35138 | W39: =$W$7 -> 219.4945 | AB39: =$AB$7 -> 130.65 | AC39: =$AC$7 -> 130.65 | AD39: =$AD$7 -> 130.65 | AE39: =$AE$7 -> 112.346 | AF39: =$AF$7 -> 127.7216 | AG39: =$AG$7 -> 125.81784 | AH39: =$AH$7 -> 122.5964 | AI39: =$AI$7 -> 0 | AJ39: =$AJ$7 -> 0 | AM39: =CIF!$X$5+VLOOKUP($AM$5&$E39,OCEAN!$E:$J,5,FALSE) -> 1082.7273 | AN39: =CIF!$X$6+VLOOKUP($AN$5&$E39,OCEAN!$E:$J,5,FALSE) -> 646.24608 | AO39: =CIF!$X$7+VLOOKUP($AO$5&$E39,OCEAN!$E:$J,5,FALSE) -> 646.24608 | AP39: =CIF!$X$8+VLOOKUP($AP$5&$E39,OCEAN!$E:$J,5,FALSE) -> 609 | AQ39: =CIF!$X$9+VLOOKUP($AQ$5&$E39,OCEAN!$E:$J,5,FALSE) -> 467.95455 | AR39: =AVERAGE(IF(ISNUMBER(AM39),AM39,""),IF(ISNUMBER(AO39),AO39,""),IF(ISNUMBER(AP39),AP39,""),IF(ISNUMBER(AQ39),AQ39,"")) -> 701.48197 | AS39: =AVERAGE(IF(ISNUMBER(AP39),AP39,""),IF(ISNUMBER(AQ39),AQ39,"")) -> 538.47727 | AV39: =CIF!$X$16+VLOOKUP($AV$6&$E39,OCEAN!$E:$J,5,FALSE) -> 254.01433 | AW39: =CIF!$X$17+VLOOKUP($AW$6&$E39,OCEAN!$E:$J,5,FALSE) -> 707.61136 | AX39: =COSTS!C16+COSTS!D16+COSTS!E16 -> 87.973924 | AY39: =COSTS!C16+COSTS!D16+COSTS!E16 -> 87.973924 | AZ39: =COSTS!C16+COSTS!D16+COSTS!E16 -> 87.973924 | BA39: =COSTS!C16+COSTS!D16+COSTS!E16 -> 87.973924 | BB39: =COSTS!C16+COSTS!D16+COSTS!E16 -> 87.973924 | BC39: =COSTS!C16+COSTS!D16+COSTS!E16 -> 87.973924 | BD39: =COSTS!C16+COSTS!D16+COSTS!E16 -> 87.973924 | BE39: =COSTS!C16+COSTS!D16+COSTS!E16 -> 87.973924 | BF39: =COSTS!C16+COSTS!D16+COSTS!E16 -> 87.973924 | BG39: =COSTS!I16+COSTS!J16+COSTS!K16 -> 110 | BH39: =COSTS!O16+COSTS!P16+COSTS!Q16 -> 48.0888 | BI39: =COSTS!F16+COSTS!G16+COSTS!H16 -> 123.63014 | BJ39: =COSTS!F16+COSTS!G16+COSTS!H16 -> 123.63014 | BK39: =COSTS!F16+COSTS!G16+COSTS!H16 -> 123.63014 | BL39: =COSTS!F16+COSTS!G16+COSTS!H16 -> 123.63014 | BM39: =COSTS!F16+COSTS!G16+COSTS!H16 -> 123.63014 | BN39: =COSTS!F16+COSTS!G16+COSTS!H16 -> 123.63014 | BO39: =COSTS!F16+COSTS!G16+COSTS!H16 -> 123.63014 | BP39: =COSTS!F16+COSTS!G16+COSTS!H16 -> 123.63014 | BQ39: =COSTS!F16+COSTS!G16+COSTS!H16 -> 123.63014 | BR39: =COSTS!L16+COSTS!M16+COSTS!N16 -> 187.26027 | BS39: =COSTS!M16+COSTS!N16+COSTS!O16 -> 128.26027 | BT39: =F39+Q39+AB39+AM39+AX39+BI39 -> 1924.8322 | BU39: =G39+R39+AC39+AN39+AY39+BJ39 -> 1591.7878 | BV39: =H39+S39+AD39+AO39+AZ39+BK39 -> 1646.7734 | BW39: =I39+T39+AE39+AP39+BA39+BL39 -> 1252.1688 | BX39: =J39+U39+AF39+AQ39+BB39+BM39 -> 1093.9104 | BY39: =K39+V39+AG39+AR39+BC39+BN39 -> 1449.0245 | BZ39: =L39+W39+AH39+AS39+BD39+BO39 -> 1170.1708 | CA39: =M39+X39+AI39+AT39+BE39+BP39 -> 211.60406 | ... CD39: =P39+AA39+AL39+AW39+BH39+BS39 -> 883.96043 | CE39: =BT39-$BT$7 -> 702.36148 | CF39: =BU39-$BU$7 -> 365.65301 | CG39: =BV39-$BV$7 -> 362.21257 | CH39: =BW39-$BW$7 -> 330.56602 | CI39: =BX39-$BX$7 -> 300.99784 | CJ39: =BY39-$BY$7 -> 425.03193 | CK39: =BZ39-$BZ$7 -> 316.56602 | CN39: =CC39-$CC$7 -> 203.27461 | CO39: =CD39-$CD$7 -> 599.96043
E40: Izmir | F40: =$F$7 -> 307.52024 | G40: =$G$7 -> 308.68205 | H40: =$H$7 -> 452.33046 | I40: =$I$7 -> 106.65 | J40: =$J$7 -> 63.672813 | K40: =$K$7 -> 198.76926 | L40: =$L$7 -> 77.998542 | Q40: =$Q$7 -> 192.33066 | R40: =$R$7 -> 294.60561 | S40: =$S$7 -> 205.94276 | T40: =$T$7 -> 212.56873 | U40: =$U$7 -> 222.95739 | V40: =$V$7 -> 211.35138 | W40: =$W$7 -> 219.4945 | AB40: =$AB$7 -> 130.65 | AC40: =$AC$7 -> 130.65 | AD40: =$AD$7 -> 130.65 | AE40: =$AE$7 -> 112.346 | AF40: =$AF$7 -> 127.7216 | AG40: =$AG$7 -> 125.81784 | AH40: =$AH$7 -> 122.5964 | AI40: =$AI$7 -> 0 | AJ40: =$AJ$7 -> 0 | AM40: =CIF!$X$5+VLOOKUP($AM$5&$E40,OCEAN!$E:$J,5,FALSE) -> 1083.4091 | AN40: =CIF!$X$6+VLOOKUP($AN$5&$E40,OCEAN!$E:$J,5,FALSE) -> 607.60972 | AO40: =CIF!$X$7+VLOOKUP($AO$5&$E40,OCEAN!$E:$J,5,FALSE) -> 607.60972 | AP40: =CIF!$X$8+VLOOKUP($AP$5&$E40,OCEAN!$E:$J,5,FALSE) -> 633.54545 | AQ40: =CIF!$X$9+VLOOKUP($AQ$5&$E40,OCEAN!$E:$J,5,FALSE) -> 474.31818 | AR40: =AVERAGE(IF(ISNUMBER(AM40),AM40,""),IF(ISNUMBER(AO40),AO40,""),IF(ISNUMBER(AP40),AP40,""),IF(ISNUMBER(AQ40),AQ40,"")) -> 699.72061 | AS40: =AVERAGE(IF(ISNUMBER(AP40),AP40,""),IF(ISNUMBER(AQ40),AQ40,"")) -> 553.93182 | AV40: =CIF!$X$16+VLOOKUP($AV$6&$E40,OCEAN!$E:$J,5,FALSE) -> 262.36052 | AW40: =CIF!$X$17+VLOOKUP($AW$6&$E40,OCEAN!$E:$J,5,FALSE) -> #N/A | AX40: =COSTS!C16+COSTS!D16+COSTS!E16 -> 87.973924 | AY40: =COSTS!C16+COSTS!D16+COSTS!E16 -> 87.973924 | AZ40: =COSTS!C16+COSTS!D16+COSTS!E16 -> 87.973924 | BA40: =COSTS!C16+COSTS!D16+COSTS!E16 -> 87.973924 | BB40: =COSTS!C16+COSTS!D16+COSTS!E16 -> 87.973924 | BC40: =COSTS!C16+COSTS!D16+COSTS!E16 -> 87.973924 | BD40: =COSTS!C16+COSTS!D16+COSTS!E16 -> 87.973924 | BE40: =COSTS!C16+COSTS!D16+COSTS!E16 -> 87.973924 | BF40: =COSTS!C16+COSTS!D16+COSTS!E16 -> 87.973924 | BG40: =COSTS!I16+COSTS!J16+COSTS!K16 -> 110 | BI40: =COSTS!F16+COSTS!G16+COSTS!H16 -> 123.63014 | BJ40: =COSTS!F16+COSTS!G16+COSTS!H16 -> 123.63014 | BK40: =COSTS!F16+COSTS!G16+COSTS!H16 -> 123.63014 | BL40: =COSTS!F16+COSTS!G16+COSTS!H16 -> 123.63014 | BM40: =COSTS!F16+COSTS!G16+COSTS!H16 -> 123.63014 | BN40: =COSTS!F16+COSTS!G16+COSTS!H16 -> 123.63014 | BO40: =COSTS!F16+COSTS!G16+COSTS!H16 -> 123.63014 | BP40: =COSTS!F16+COSTS!G16+COSTS!H16 -> 123.63014 | BQ40: =COSTS!F16+COSTS!G16+COSTS!H16 -> 123.63014 | BR40: =COSTS!L16+COSTS!M16+COSTS!N16 -> 187.26027 | BS40: =COSTS!M16+COSTS!N16+COSTS!O16 -> 128.26027 | BT40: =F40+Q40+AB40+AM40+AX40+BI40 -> 1925.514 | BU40: =G40+R40+AC40+AN40+AY40+BJ40 -> 1553.1514 | BV40: =H40+S40+AD40+AO40+AZ40+BK40 -> 1608.137 | BW40: =I40+T40+AE40+AP40+BA40+BL40 -> 1276.7142 | BX40: =J40+U40+AF40+AQ40+BB40+BM40 -> 1100.274 | BY40: =K40+V40+AG40+AR40+BC40+BN40 -> 1447.2632 | BZ40: =L40+W40+AH40+AS40+BD40+BO40 -> 1185.6253 | CA40: =M40+X40+AI40+AT40+BE40+BP40 -> 211.60406 | ... CD40: =P40+AA40+AL40+AW40+BH40+BS40 -> #N/A | CE40: =BT40-$BT$7 -> 703.04329 | CF40: =BU40-$BU$7 -> 327.01665 | CG40: =BV40-$BV$7 -> 323.57621 | CH40: =BW40-$BW$7 -> 355.11148 | CI40: =BX40-$BX$7 -> 307.36148 | CJ40: =BY40-$BY$7 -> 423.27057 | CK40: =BZ40-$BZ$7 -> 332.02057 | CN40: =CC40-$CC$7 -> 211.62079 | CO40: =CD40-$CD$7 -> #N/A
A41: Mexico | B41: MX | D41: N/A | E41: Yecapixtla | F41: =$F$7 -> 307.52024 | G41: =$G$7 -> 308.68205 | H41: =$H$7 -> 452.33046 | I41: =$I$7 -> 106.65 | J41: =$J$7 -> 63.672813 | K41: =$K$7 -> 198.76926 | L41: =$L$7 -> 77.998542 | Q41: {=AVERAGE(_xlfn._xlws.FILTER(PTS!AW:AW, (PTS!$E:$E="WTX") * ISNUMBER(PTS!AW:AW)))} -> 363.55063 | R41: {=AVERAGE(_xlfn._xlws.FILTER(PTS!AW:AW, (PTS!$E:$E="WTXH") * ISNUMBER(PTS!AW:AW)))} -> 364.3138 | S41: {=AVERAGE(_xlfn._xlws.FILTER(PTS!AW:AW, (PTS!$E:$E="STEX") * ISNUMBER(PTS!AW:AW)))} -> 282.4224 | T41: {=AVERAGE(_xlfn._xlws.FILTER(PTS!AW:AW, (PTS!$E:$E="Memphis Rule 5") * ISNUMBER(PTS!AW:AW)))} -> 486.39037 | U41: {=AVERAGE(_xlfn._xlws.FILTER(PTS!AW:AW, (PTS!$E:$E="GA 30 DAY") * ISNUMBER(PTS!AW:AW)))} -> 498.53169 | V41: =AVERAGE(Q41,S41,T41,U41) -> 407.72378 | W41: =AVERAGE(T41,U41) -> 492.46103 | AB41: =((COSTS!AA23+COSTS!AC23)*20)+COSTS!G17 -> 83.052055 | AC41: =((COSTS!AA23+COSTS!AC23)*20)+COSTS!G17 -> 83.052055 | AD41: =((COSTS!AA23+COSTS!AC23)*20)+COSTS!G17 -> 83.052055 | AE41: =((COSTS!AA23+COSTS!AC23)*20)+COSTS!G17 -> 83.052055 | AF41: =((COSTS!AA23+COSTS!AC23)*20)+COSTS!G17 -> 83.052055 | AG41: =((COSTS!AA23+COSTS!AC23)*20)+COSTS!G17 -> 83.052055 | AH41: =((COSTS!AA23+COSTS!AC23)*20)+COSTS!G17 -> 83.052055 | AM41: =VLOOKUP($B$41&$E$41, OCEAN!$E:$J,5,FALSE) -> 477.27273 | AN41: =AM41 -> 477.27273 | AO41: =AN41 -> 477.27273 | AP41: =AO41 -> 477.27273 | AQ41: =AP41 -> 477.27273 | AR41: =AQ41 -> 477.27273 | AS41: =AR41 -> 477.27273 | AX41: =COSTS!$X$32 -> 185.45455 | AY41: =COSTS!$X$32 -> 185.45455 | AZ41: =COSTS!$X$32 -> 185.45455 | BA41: =COSTS!$X$32 -> 185.45455 | BB41: =COSTS!$X$32 -> 185.45455 | BC41: =COSTS!$X$32 -> 185.45455 | BD41: =COSTS!$X$32 -> 185.45455 | BE41: =COSTS!$X$32 -> 185.45455 | BF41: =COSTS!$X$32 -> 185.45455 | BI41: =COSTS!F17 -> 80 | BJ41: =BI41 -> 80 | BK41: =BJ41 -> 80 | BL41: =BK41 -> 80 | BM41: =BL41 -> 80 | BN41: =BM41 -> 80 | BO41: =BN41 -> 80 | BT41: =F41+Q41+AB41+AM41+AX41+BI41 -> 1496.8502 | BU41: =G41+R41+AC41+AN41+AY41+BJ41 -> 1498.7752 | BV41: =H41+S41+AD41+AO41+AZ41+BK41 -> 1560.5322 | BW41: =I41+T41+AE41+AP41+BA41+BL41 -> 1418.8197 | BX41: =J41+U41+AF41+AQ41+BB41+BM41 -> 1387.9838 | BY41: =K41+V41+AG41+AR41+BC41+BN41 -> 1432.2724 | BZ41: =L41+W41+AH41+AS41+BD41+BO41 -> 1396.2389 | CE41: =BT41-$BT$7 -> 274.37944 | CF41: =BU41-$BU$7 -> 272.64038 | CG41: =BV41-$BV$7 -> 275.9714 | CH41: =BW41-$BW$7 -> 497.21693 | CI41: =BX41-$BX$7 -> 595.07126 | CJ41: =BY41-$BY$7 -> 408.27977 | CK41: =BZ41-$BZ$7 -> 542.63415
B42: Weslaco | E42: Parras | F42: =$F$7 -> 307.52024 | G42: =$G$7 -> 308.68205 | H42: =$H$7 -> 452.33046 | I42: =$I$7 -> 106.65 | J42: =$J$7 -> 63.672813 | K42: =$K$7 -> 198.76926 | L42: =$L$7 -> 77.998542 | Q42: =Q41 -> 363.55063 | R42: =R41 -> 364.3138 | S42: =S41 -> 282.4224 | T42: =T41 -> 486.39037 | U42: =U41 -> 498.53169 | V42: =V41 -> 407.72378 | W42: =W41 -> 492.46103 | AB42: =AB41 -> 83.052055 | AC42: =AC41 -> 83.052055 | AD42: =AD41 -> 83.052055 | AE42: =AE41 -> 83.052055 | AF42: =AF41 -> 83.052055 | AG42: =AG41 -> 83.052055 | AH42: =AH41 -> 83.052055 | AM42: =VLOOKUP($B$41&$E$42, OCEAN!$E:$J,5,FALSE) -> 289.77273 | AN42: =AM42 -> 289.77273 | AO42: =AN42 -> 289.77273 | AP42: =AO42 -> 289.77273 | AQ42: =AP42 -> 289.77273 | AR42: =AQ42 -> 289.77273 | AS42: =AR42 -> 289.77273 | AX42: =COSTS!$X$32 -> 185.45455 | AY42: =COSTS!$X$32 -> 185.45455 | AZ42: =COSTS!$X$32 -> 185.45455 | BA42: =COSTS!$X$32 -> 185.45455 | BB42: =COSTS!$X$32 -> 185.45455 | BC42: =COSTS!$X$32 -> 185.45455 | BD42: =COSTS!$X$32 -> 185.45455 | BE42: =COSTS!$X$32 -> 185.45455 | BF42: =COSTS!$X$32 -> 185.45455 | BI42: =COSTS!F17 -> 80 | BJ42: =BI42 -> 80 | BK42: =BJ42 -> 80 | BL42: =BK42 -> 80 | BM42: =BL42 -> 80 | BN42: =BM42 -> 80 | BO42: =BN42 -> 80 | BT42: =F42+Q42+AB42+AM42+AX42+BI42 -> 1309.3502 | BU42: =G42+R42+AC42+AN42+AY42+BJ42 -> 1311.2752 | BV42: =H42+S42+AD42+AO42+AZ42+BK42 -> 1373.0322 | BW42: =I42+T42+AE42+AP42+BA42+BL42 -> 1231.3197 | BX42: =J42+U42+AF42+AQ42+BB42+BM42 -> 1200.4838 | BY42: =K42+V42+AG42+AR42+BC42+BN42 -> 1244.7724 | BZ42: =L42+W42+AH42+AS42+BD42+BO42 -> 1208.7389 | CE42: =BT42-$BT$7 -> 86.879444 | CF42: =BU42-$BU$7 -> 85.14038 | CG42: =BV42-$BV$7 -> 88.471399 | CH42: =BW42-$BW$7 -> 309.71693 | CI42: =BX42-$BX$7 -> 407.57126 | CJ42: =BY42-$BY$7 -> 220.77977 | CK42: =BZ42-$BZ$7 -> 355.13415
E43: CD Victoria | F43: =$F$7 -> 307.52024 | G43: =$G$7 -> 308.68205 | H43: =$H$7 -> 452.33046 | I43: =$I$7 -> 106.65 | J43: =$J$7 -> 63.672813 | K43: =$K$7 -> 198.76926 | L43: =$L$7 -> 77.998542 | Q43: =Q41 -> 363.55063 | R43: =R41 -> 364.3138 | S43: =S41 -> 282.4224 | T43: =T41 -> 486.39037 | U43: =U41 -> 498.53169 | V43: =V41 -> 407.72378 | W43: =W41 -> 492.46103 | AB43: =AB41 -> 83.052055 | AC43: =AC41 -> 83.052055 | AD43: =AD41 -> 83.052055 | AE43: =AE41 -> 83.052055 | AF43: =AF41 -> 83.052055 | AG43: =AG41 -> 83.052055 | AH43: =AH41 -> 83.052055 | AM43: =VLOOKUP($B$41&$E$43, OCEAN!$E:$J,5,FALSE) -> 272.72727 | AN43: =AM43 -> 272.72727 | AO43: =AN43 -> 272.72727 | AP43: =AO43 -> 272.72727 | AQ43: =AP43 -> 272.72727 | AR43: =AQ43 -> 272.72727 | AS43: =AR43 -> 272.72727 | AX43: =COSTS!$X$32 -> 185.45455 | AY43: =COSTS!$X$32 -> 185.45455 | AZ43: =COSTS!$X$32 -> 185.45455 | BA43: =COSTS!$X$32 -> 185.45455 | BB43: =COSTS!$X$32 -> 185.45455 | BC43: =COSTS!$X$32 -> 185.45455 | BD43: =COSTS!$X$32 -> 185.45455 | BE43: =COSTS!$X$32 -> 185.45455 | BF43: =COSTS!$X$32 -> 185.45455 | BI43: =COSTS!F17 -> 80 | BJ43: =BI43 -> 80 | BK43: =BJ43 -> 80 | BL43: =BK43 -> 80 | BM43: =BL43 -> 80 | BN43: =BM43 -> 80 | BO43: =BN43 -> 80 | BT43: =F43+Q43+AB43+AM43+AX43+BI43 -> 1292.3047 | BU43: =G43+R43+AC43+AN43+AY43+BJ43 -> 1294.2297 | BV43: =H43+S43+AD43+AO43+AZ43+BK43 -> 1355.9867 | BW43: =I43+T43+AE43+AP43+BA43+BL43 -> 1214.2742 | BX43: =J43+U43+AF43+AQ43+BB43+BM43 -> 1183.4384 | BY43: =K43+V43+AG43+AR43+BC43+BN43 -> 1227.7269 | BZ43: =L43+W43+AH43+AS43+BD43+BO43 -> 1191.6934 | CE43: =BT43-$BT$7 -> 69.833989 | CF43: =BU43-$BU$7 -> 68.094926 | CG43: =BV43-$BV$7 -> 71.425945 | CH43: =BW43-$BW$7 -> 292.67148 | CI43: =BX43-$BX$7 -> 390.52581 | CJ43: =BY43-$BY$7 -> 203.73432 | CK43: =BZ43-$BZ$7 -> 338.08869
A44: Peru | B44: PE | C44: 11 | D44: 18 | E44: Callao | F44: =$F$7 -> 307.52024 | G44: =$G$7 -> 308.68205 | H44: =$H$7 -> 452.33046 | I44: =$I$7 -> 106.65 | J44: =$J$7 -> 63.672813 | K44: =$K$7 -> 198.76926 | L44: =$L$7 -> 77.998542 | Q44: =$Q$7 -> 192.33066 | R44: =$R$7 -> 294.60561 | S44: =$S$7 -> 205.94276 | T44: =$T$7 -> 212.56873 | U44: =$U$7 -> 222.95739 | V44: =$V$7 -> 211.35138 | W44: =$W$7 -> 219.4945 | AB44: =$AB$7 -> 130.65 | AC44: =$AC$7 -> 130.65 | AD44: =$AD$7 -> 130.65 | AE44: =$AE$7 -> 112.346 | AF44: =$AF$7 -> 127.7216 | AG44: =$AG$7 -> 125.81784 | AH44: =$AH$7 -> 122.5964 | AI44: =$AI$7 -> 0 | AJ44: =$AJ$7 -> 0 | AM44: =CIF!$X$5+VLOOKUP($AM$5&$E44,OCEAN!$E:$J,5,FALSE) -> #N/A | AN44: =CIF!$X$6+VLOOKUP($AN$5&$E44,OCEAN!$E:$J,5,FALSE) -> 464.65517 | AO44: =CIF!$X$7+VLOOKUP($AO$5&$E44,OCEAN!$E:$J,5,FALSE) -> 464.65517 | AP44: =CIF!$X$8+VLOOKUP($AP$5&$E44,OCEAN!$E:$J,5,FALSE) -> 566.04545 | AQ44: =CIF!$X$9+VLOOKUP($AQ$5&$E44,OCEAN!$E:$J,5,FALSE) -> 401.13636 | AR44: =AVERAGE(IF(ISNUMBER(AM44),AM44,""),IF(ISNUMBER(AO44),AO44,""),IF(ISNUMBER(AP44),AP44,""),IF(ISNUMBER(AQ44),AQ44,"")) -> #VALUE! | AS44: =AVERAGE(IF(ISNUMBER(AP44),AP44,""),IF(ISNUMBER(AQ44),AQ44,"")) -> 483.59091 | AX44: =COSTS!C18+COSTS!D18+COSTS!E18 -> 35.283145 | AY44: =COSTS!C18+COSTS!D18+COSTS!E18 -> 35.283145 | AZ44: =COSTS!C18+COSTS!D18+COSTS!E18 -> 35.283145 | BA44: =COSTS!C18+COSTS!D18+COSTS!E18 -> 35.283145 | BB44: =COSTS!C18+COSTS!D18+COSTS!E18 -> 35.283145 | BC44: =COSTS!C18+COSTS!D18+COSTS!E18 -> 35.283145 | BD44: =COSTS!C18+COSTS!D18+COSTS!E18 -> 35.283145 | BE44: =COSTS!C18+COSTS!D18+COSTS!E18 -> 35.283145 | BF44: =COSTS!C18+COSTS!D18+COSTS!E18 -> 35.283145 | BI44: =COSTS!F18+COSTS!G18+COSTS!H18 -> 97.452055 | BJ44: =COSTS!F18+COSTS!G18+COSTS!H18 -> 97.452055 | BK44: =COSTS!F18+COSTS!G18+COSTS!H18 -> 97.452055 | BL44: =COSTS!F18+COSTS!G18+COSTS!H18 -> 97.452055 | BM44: =COSTS!F18+COSTS!G18+COSTS!H18 -> 97.452055 | BN44: =COSTS!F18+COSTS!G18+COSTS!H18 -> 97.452055 | BO44: =COSTS!F18+COSTS!G18+COSTS!H18 -> 97.452055 | BP44: =COSTS!F18+COSTS!G18+COSTS!H18 -> 97.452055 | BQ44: =COSTS!F18+COSTS!G18+COSTS!H18 -> 97.452055 | BT44: =F44+Q44+AB44+AM44+AX44+BI44 -> #N/A | BU44: =G44+R44+AC44+AN44+AY44+BJ44 -> 1331.328 | BV44: =H44+S44+AD44+AO44+AZ44+BK44 -> 1386.3136 | BW44: =I44+T44+AE44+AP44+BA44+BL44 -> 1130.3454 | BX44: =J44+U44+AF44+AQ44+BB44+BM44 -> 948.22337 | BY44: =K44+V44+AG44+AR44+BC44+BN44 -> #VALUE! | BZ44: =L44+W44+AH44+AS44+BD44+BO44 -> 1036.4156 | CA44: =M44+X44+AI44+AT44+BE44+BP44 -> 132.7352 | CB44: =N44+Y44+AJ44+AU44+BF44+BQ44 -> 132.7352 | CE44: =BT44-$BT$7 -> #N/A | CF44: =BU44-$BU$7 -> 105.19324 | CG44: =BV44-$BV$7 -> 101.7528 | CH44: =BW44-$BW$7 -> 208.74261 | CI44: =BX44-$BX$7 -> 155.3108 | CJ44: =BY44-$BY$7 -> #VALUE! | CK44: =BZ44-$BZ$7 -> 182.8108
A45: Guatemala | B45: GU | C45: 8 | D45: 21 | E45: Amatitlan | F45: =$F$7 -> 307.52024 | G45: =$G$7 -> 308.68205 | H45: =$H$7 -> 452.33046 | I45: =$I$7 -> 106.65 | J45: =$J$7 -> 63.672813 | K45: =$K$7 -> 198.76926 | L45: =$L$7 -> 77.998542 | Q45: =$Q$7 -> 192.33066 | R45: =$R$7 -> 294.60561 | S45: =$S$7 -> 205.94276 | T45: =$T$7 -> 212.56873 | U45: =$U$7 -> 222.95739 | V45: =$V$7 -> 211.35138 | W45: =$W$7 -> 219.4945 | AB45: =$AB$7 -> 130.65 | AC45: =$AC$7 -> 130.65 | AD45: =$AD$7 -> 130.65 | AE45: =$AE$7 -> 112.346 | AF45: =$AF$7 -> 127.7216 | AG45: =$AG$7 -> 125.81784 | AH45: =$AH$7 -> 122.5964 | AI45: =$AI$7 -> 0 | AJ45: =$AJ$7 -> 0 | AM45: =CIF!$X$5+VLOOKUP($AM$5&$E45,OCEAN!$E:$J,5,FALSE) -> #N/A | AN45: =CIF!$X$6+VLOOKUP($AN$5&$E45,OCEAN!$E:$J,5,FALSE) -> 793.51881 | AO45: =CIF!$X$7+VLOOKUP($AO$5&$E45,OCEAN!$E:$J,5,FALSE) -> 793.51881 | AP45: =CIF!$X$8+VLOOKUP($AP$5&$E45,OCEAN!$E:$J,5,FALSE) -> 1138.0909 | AQ45: =CIF!$X$9+VLOOKUP($AQ$5&$E45,OCEAN!$E:$J,5,FALSE) -> 922.04545 | AR45: =AVERAGE(IF(ISNUMBER(AM45),AM45,""),IF(ISNUMBER(AO45),AO45,""),IF(ISNUMBER(AP45),AP45,""),IF(ISNUMBER(AQ45),AQ45,"")) -> #VALUE! | AS45: =AVERAGE(IF(ISNUMBER(AP45),AP45,""),IF(ISNUMBER(AQ45),AQ45,"")) -> 1030.0682 | AX45: =COSTS!C19+COSTS!D19+COSTS!E19 -> 33.582156 | AY45: =COSTS!C19+COSTS!D19+COSTS!E19 -> 33.582156 | AZ45: =COSTS!C19+COSTS!D19+COSTS!E19 -> 33.582156 | BA45: =COSTS!C19+COSTS!D19+COSTS!E19 -> 33.582156 | BB45: =COSTS!C19+COSTS!D19+COSTS!E19 -> 33.582156 | BC45: =COSTS!C19+COSTS!D19+COSTS!E19 -> 33.582156 | BD45: =COSTS!C19+COSTS!D19+COSTS!E19 -> 33.582156 | BE45: =COSTS!C19+COSTS!D19+COSTS!E19 -> 33.582156 | BF45: =COSTS!C19+COSTS!D19+COSTS!E19 -> 33.582156 | BI45: =COSTS!F19+COSTS!G19+COSTS!H19 -> 97.452055 | BJ45: =COSTS!F19+COSTS!G19+COSTS!H19 -> 97.452055 | BK45: =COSTS!F19+COSTS!G19+COSTS!H19 -> 97.452055 | BL45: =COSTS!F19+COSTS!G19+COSTS!H19 -> 97.452055 | BM45: =COSTS!F19+COSTS!G19+COSTS!H19 -> 97.452055 | BN45: =COSTS!F19+COSTS!G19+COSTS!H19 -> 97.452055 | BO45: =COSTS!F19+COSTS!G19+COSTS!H19 -> 97.452055 | BP45: =COSTS!F19+COSTS!G19+COSTS!H19 -> 97.452055 | BQ45: =COSTS!F19+COSTS!G19+COSTS!H19 -> 97.452055 | BT45: =F45+Q45+AB45+AM45+AX45+BI45 -> #N/A | BU45: =G45+R45+AC45+AN45+AY45+BJ45 -> 1658.4907 | BV45: =H45+S45+AD45+AO45+AZ45+BK45 -> 1713.4762 | BW45: =I45+T45+AE45+AP45+BA45+BL45 -> 1700.6898 | BX45: =J45+U45+AF45+AQ45+BB45+BM45 -> 1467.4315 | BY45: =K45+V45+AG45+AR45+BC45+BN45 -> #VALUE! | BZ45: =L45+W45+AH45+AS45+BD45+BO45 -> 1581.1918 | CA45: =M45+X45+AI45+AT45+BE45+BP45 -> 131.03421 | CB45: =N45+Y45+AJ45+AU45+BF45+BQ45 -> 131.03421 | CE45: =BT45-$BT$7 -> #N/A | CF45: =BU45-$BU$7 -> 432.35589 | CG45: =BV45-$BV$7 -> 428.91545 | CH45: =BW45-$BW$7 -> 779.08708 | CI45: =BX45-$BX$7 -> 674.5189 | CJ45: =BY45-$BY$7 -> #VALUE! | CK45: =BZ45-$BZ$7 -> 727.58708
E46: Palin | F46: =$F$7 -> 307.52024 | G46: =$G$7 -> 308.68205 | H46: =$H$7 -> 452.33046 | I46: =$I$7 -> 106.65 | J46: =$J$7 -> 63.672813 | K46: =$K$7 -> 198.76926 | L46: =$L$7 -> 77.998542 | Q46: =$Q$7 -> 192.33066 | R46: =$R$7 -> 294.60561 | S46: =$S$7 -> 205.94276 | T46: =$T$7 -> 212.56873 | U46: =$U$7 -> 222.95739 | V46: =$V$7 -> 211.35138 | W46: =$W$7 -> 219.4945 | AB46: =$AB$7 -> 130.65 | AC46: =$AC$7 -> 130.65 | AD46: =$AD$7 -> 130.65 | AE46: =$AE$7 -> 112.346 | AF46: =$AF$7 -> 127.7216 | AG46: =$AG$7 -> 125.81784 | AH46: =$AH$7 -> 122.5964 | AI46: =$AI$7 -> 0 | AJ46: =$AJ$7 -> 0 | AM46: =CIF!$X$5+VLOOKUP($AM$5&$E46,OCEAN!$E:$J,5,FALSE) -> #N/A | AN46: =CIF!$X$6+VLOOKUP($AN$5&$E46,OCEAN!$E:$J,5,FALSE) -> 759.20063 | AO46: =CIF!$X$7+VLOOKUP($AO$5&$E46,OCEAN!$E:$J,5,FALSE) -> 759.20063 | AP46: =CIF!$X$8+VLOOKUP($AP$5&$E46,OCEAN!$E:$J,5,FALSE) -> 1160.8182 | AQ46: =CIF!$X$9+VLOOKUP($AQ$5&$E46,OCEAN!$E:$J,5,FALSE) -> 944.77273 | AR46: =AVERAGE(IF(ISNUMBER(AM46),AM46,""),IF(ISNUMBER(AO46),AO46,""),IF(ISNUMBER(AP46),AP46,""),IF(ISNUMBER(AQ46),AQ46,"")) -> #VALUE! | AS46: =AVERAGE(IF(ISNUMBER(AP46),AP46,""),IF(ISNUMBER(AQ46),AQ46,"")) -> 1052.7955 | AX46: =COSTS!C19+COSTS!D19+COSTS!E19 -> 33.582156 | AY46: =COSTS!C19+COSTS!D19+COSTS!E19 -> 33.582156 | AZ46: =COSTS!C19+COSTS!D19+COSTS!E19 -> 33.582156 | BA46: =COSTS!C19+COSTS!D19+COSTS!E19 -> 33.582156 | BB46: =COSTS!C19+COSTS!D19+COSTS!E19 -> 33.582156 | BC46: =COSTS!C19+COSTS!D19+COSTS!E19 -> 33.582156 | BD46: =COSTS!C19+COSTS!D19+COSTS!E19 -> 33.582156 | BE46: =COSTS!C19+COSTS!D19+COSTS!E19 -> 33.582156 | BF46: =COSTS!C19+COSTS!D19+COSTS!E19 -> 33.582156 | BI46: =COSTS!F19+COSTS!G19+COSTS!H19 -> 97.452055 | BJ46: =COSTS!F19+COSTS!G19+COSTS!H19 -> 97.452055 | BK46: =COSTS!F19+COSTS!G19+COSTS!H19 -> 97.452055 | BL46: =COSTS!F19+COSTS!G19+COSTS!H19 -> 97.452055 | BM46: =COSTS!F19+COSTS!G19+COSTS!H19 -> 97.452055 | BN46: =COSTS!F19+COSTS!G19+COSTS!H19 -> 97.452055 | BO46: =COSTS!F19+COSTS!G19+COSTS!H19 -> 97.452055 | BP46: =COSTS!F19+COSTS!G19+COSTS!H19 -> 97.452055 | BQ46: =COSTS!F19+COSTS!G19+COSTS!H19 -> 97.452055 | BT46: =F46+Q46+AB46+AM46+AX46+BI46 -> #N/A | BU46: =G46+R46+AC46+AN46+AY46+BJ46 -> 1624.1725 | BV46: =H46+S46+AD46+AO46+AZ46+BK46 -> 1679.1581 | BW46: =I46+T46+AE46+AP46+BA46+BL46 -> 1723.4171 | BX46: =J46+U46+AF46+AQ46+BB46+BM46 -> 1490.1587 | BY46: =K46+V46+AG46+AR46+BC46+BN46 -> #VALUE! | BZ46: =L46+W46+AH46+AS46+BD46+BO46 -> 1603.9191 | CA46: =M46+X46+AI46+AT46+BE46+BP46 -> 131.03421 | CB46: =N46+Y46+AJ46+AU46+BF46+BQ46 -> 131.03421 | CE46: =BT46-$BT$7 -> #N/A | CF46: =BU46-$BU$7 -> 398.03771 | CG46: =BV46-$BV$7 -> 394.59727 | CH46: =BW46-$BW$7 -> 801.81435 | CI46: =BX46-$BX$7 -> 697.24617 | CJ46: =BY46-$BY$7 -> #VALUE! | CK46: =BZ46-$BZ$7 -> 750.31435
A47: Honduras | B47: HO | C47: 11 | D47: 18 | E47: Naco | F47: =$F$7 -> 307.52024 | G47: =$G$7 -> 308.68205 | H47: =$H$7 -> 452.33046 | I47: =$I$7 -> 106.65 | J47: =$J$7 -> 63.672813 | K47: =$K$7 -> 198.76926 | L47: =$L$7 -> 77.998542 | Q47: =$Q$7 -> 192.33066 | R47: =$R$7 -> 294.60561 | S47: =$S$7 -> 205.94276 | T47: =$T$7 -> 212.56873 | U47: =$U$7 -> 222.95739 | V47: =$V$7 -> 211.35138 | W47: =$W$7 -> 219.4945 | AB47: =$AB$7 -> 130.65 | AC47: =$AC$7 -> 130.65 | AD47: =$AD$7 -> 130.65 | AE47: =$AE$7 -> 112.346 | AF47: =$AF$7 -> 127.7216 | AG47: =$AG$7 -> 125.81784 | AH47: =$AH$7 -> 122.5964 | AI47: =$AI$7 -> 0 | AJ47: =$AJ$7 -> 0 | AM47: =CIF!$X$5+VLOOKUP($AM$5&$E47,OCEAN!$E:$J,5,FALSE) -> #N/A | AN47: =CIF!$X$6+VLOOKUP($AN$5&$E47,OCEAN!$E:$J,5,FALSE) -> 769.65517 | AO47: =CIF!$X$7+VLOOKUP($AO$5&$E47,OCEAN!$E:$J,5,FALSE) -> 769.65517 | AP47: =CIF!$X$8+VLOOKUP($AP$5&$E47,OCEAN!$E:$J,5,FALSE) -> #VALUE! | AQ47: =CIF!$X$9+VLOOKUP($AQ$5&$E47,OCEAN!$E:$J,5,FALSE) -> #VALUE! | AR47: =AVERAGE(IF(ISNUMBER(AM47),AM47,""),IF(ISNUMBER(AO47),AO47,""),IF(ISNUMBER(AP47),AP47,""),IF(ISNUMBER(AQ47),AQ47,"")) -> #VALUE! | AS47: =AVERAGE(IF(ISNUMBER(AP47),AP47,""),IF(ISNUMBER(AQ47),AQ47,"")) -> #VALUE! | AX47: =COSTS!C20+COSTS!D20+COSTS!E20 -> 33.582156 | AY47: =COSTS!C20+COSTS!D20+COSTS!E20 -> 33.582156 | AZ47: =COSTS!C20+COSTS!D20+COSTS!E20 -> 33.582156 | BA47: =COSTS!C20+COSTS!D20+COSTS!E20 -> 33.582156 | BB47: =COSTS!C20+COSTS!D20+COSTS!E20 -> 33.582156 | BC47: =COSTS!C20+COSTS!D20+COSTS!E20 -> 33.582156 | BD47: =COSTS!C20+COSTS!D20+COSTS!E20 -> 33.582156 | BE47: =COSTS!C20+COSTS!D20+COSTS!E20 -> 33.582156 | BF47: =COSTS!C20+COSTS!D20+COSTS!E20 -> 33.582156 | BI47: =COSTS!F20+COSTS!G20+COSTS!H20 -> 97.452055 | BJ47: =COSTS!F20+COSTS!G20+COSTS!H20 -> 97.452055 | BK47: =COSTS!F20+COSTS!G20+COSTS!H20 -> 97.452055 | BL47: =COSTS!F20+COSTS!G20+COSTS!H20 -> 97.452055 | BM47: =COSTS!F20+COSTS!G20+COSTS!H20 -> 97.452055 | BN47: =COSTS!F20+COSTS!G20+COSTS!H20 -> 97.452055 | BO47: =COSTS!F20+COSTS!G20+COSTS!H20 -> 97.452055 | BP47: =COSTS!F20+COSTS!G20+COSTS!H20 -> 97.452055 | BQ47: =COSTS!F20+COSTS!G20+COSTS!H20 -> 97.452055 | BT47: =F47+Q47+AB47+AM47+AX47+BI47 -> #N/A | BU47: =G47+R47+AC47+AN47+AY47+BJ47 -> 1634.627 | BV47: =H47+S47+AD47+AO47+AZ47+BK47 -> 1689.6126 | BW47: =I47+T47+AE47+AP47+BA47+BL47 -> #VALUE! | BX47: =J47+U47+AF47+AQ47+BB47+BM47 -> #VALUE! | BY47: =K47+V47+AG47+AR47+BC47+BN47 -> #VALUE! | BZ47: =L47+W47+AH47+AS47+BD47+BO47 -> #VALUE! | CA47: =M47+X47+AI47+AT47+BE47+BP47 -> 131.03421 | CB47: =N47+Y47+AJ47+AU47+BF47+BQ47 -> 131.03421 | CE47: =BT47-$BT$7 -> #N/A | CF47: =BU47-$BU$7 -> 408.49225 | CG47: =BV47-$BV$7 -> 405.05181 | CH47: =BW47-$BW$7 -> #VALUE! | CI47: =BX47-$BX$7 -> #VALUE! | CJ47: =BY47-$BY$7 -> #VALUE! | CK47: =BZ47-$BZ$7 -> #VALUE!
A48: Spain | B48: ES | D48: 14 | E48: Santa Barbara | F48: =$F$7 -> 307.52024 | G48: =$G$7 -> 308.68205 | H48: =$H$7 -> 452.33046 | I48: =$I$7 -> 106.65 | J48: =$J$7 -> 63.672813 | K48: =$K$7 -> 198.76926 | L48: =$L$7 -> 77.998542 | Q48: =$Q$7 -> 192.33066 | R48: =$R$7 -> 294.60561 | S48: =$S$7 -> 205.94276 | T48: =$T$7 -> 212.56873 | U48: =$U$7 -> 222.95739 | V48: =$V$7 -> 211.35138 | W48: =$W$7 -> 219.4945 | AB48: =$AB$7 -> 130.65 | AC48: =$AC$7 -> 130.65 | AD48: =$AD$7 -> 130.65 | AE48: =$AE$7 -> 112.346 | AF48: =$AF$7 -> 127.7216 | AG48: =$AG$7 -> 125.81784 | AH48: =$AH$7 -> 122.5964 | AI48: =$AI$7 -> 0 | AJ48: =$AJ$7 -> 0 | AM48: =CIF!$X$5+VLOOKUP($AM$5&$E48,OCEAN!$E:$J,5,FALSE) -> #N/A | AN48: =CIF!$X$6+VLOOKUP($AN$5&$E48,OCEAN!$E:$J,5,FALSE) -> 743.06426 | AO48: =CIF!$X$7+VLOOKUP($AO$5&$E48,OCEAN!$E:$J,5,FALSE) -> 743.06426 | AP48: =CIF!$X$8+VLOOKUP($AP$5&$E48,OCEAN!$E:$J,5,FALSE) -> 1085.8182 | AQ48: =CIF!$X$9+VLOOKUP($AQ$5&$E48,OCEAN!$E:$J,5,FALSE) -> #VALUE! | AR48: =AVERAGE(IF(ISNUMBER(AM48),AM48,""),IF(ISNUMBER(AO48),AO48,""),IF(ISNUMBER(AP48),AP48,""),IF(ISNUMBER(AQ48),AQ48,"")) -> #VALUE! | AS48: =AVERAGE(IF(ISNUMBER(AP48),AP48,""),IF(ISNUMBER(AQ48),AQ48,"")) -> #VALUE! | AX48: =COSTS!C23+COSTS!D23+COSTS!E23 -> 14.7352 | AY48: =COSTS!C23+COSTS!D23+COSTS!E23 -> 14.7352 | AZ48: =COSTS!C23+COSTS!D23+COSTS!E23 -> 14.7352 | BA48: =COSTS!C23+COSTS!D23+COSTS!E23 -> 14.7352 | BB48: =COSTS!C23+COSTS!D23+COSTS!E23 -> 14.7352 | BC48: =COSTS!C23+COSTS!D23+COSTS!E23 -> 14.7352 | BD48: =COSTS!C23+COSTS!D23+COSTS!E23 -> 14.7352 | BE48: =COSTS!C23+COSTS!D23+COSTS!E23 -> 14.7352 | BF48: =COSTS!C23+COSTS!D23+COSTS!E23 -> 14.7352 | BI48: =COSTS!F23+COSTS!G23+COSTS!H23 -> 97.452055 | BJ48: =COSTS!F23+COSTS!G23+COSTS!H23 -> 97.452055 | BK48: =COSTS!F23+COSTS!G23+COSTS!H23 -> 97.452055 | BL48: =COSTS!F23+COSTS!G23+COSTS!H23 -> 97.452055 | BM48: =COSTS!F23+COSTS!G23+COSTS!H23 -> 97.452055 | BN48: =COSTS!F23+COSTS!G23+COSTS!H23 -> 97.452055 | BO48: =COSTS!F23+COSTS!G23+COSTS!H23 -> 97.452055 | BP48: =COSTS!F23+COSTS!G23+COSTS!H23 -> 97.452055 | BQ48: =COSTS!F23+COSTS!G23+COSTS!H23 -> 97.452055 | BT48: =F48+Q48+AB48+AM48+AX48+BI48 -> #N/A | BU48: =G48+R48+AC48+AN48+AY48+BJ48 -> 1589.1892 | BV48: =H48+S48+AD48+AO48+AZ48+BK48 -> 1644.1747 | BW48: =I48+T48+AE48+AP48+BA48+BL48 -> 1629.5702 | BX48: =J48+U48+AF48+AQ48+BB48+BM48 -> #VALUE! | BY48: =K48+V48+AG48+AR48+BC48+BN48 -> #VALUE! | BZ48: =L48+W48+AH48+AS48+BD48+BO48 -> #VALUE! | CA48: =M48+X48+AI48+AT48+BE48+BP48 -> 112.18725 | CB48: =N48+Y48+AJ48+AU48+BF48+BQ48 -> 112.18725 | CE48: =BT48-$BT$7 -> #N/A | CF48: =BU48-$BU$7 -> 363.05439 | CG48: =BV48-$BV$7 -> 359.61395 | CH48: =BW48-$BW$7 -> 707.9674 | CI48: =BX48-$BX$7 -> #VALUE! | CJ48: =BY48-$BY$7 -> #VALUE! | CK48: =BZ48-$BZ$7 -> #VALUE!
A49: ITALY | B49: IT | D49: 14 | E49: Bergamo | F49: =$F$7 -> 307.52024 | G49: =$G$7 -> 308.68205 | H49: =$H$7 -> 452.33046 | I49: =$I$7 -> 106.65 | J49: =$J$7 -> 63.672813 | K49: =$K$7 -> 198.76926 | L49: =$L$7 -> 77.998542 | Q49: =$Q$7 -> 192.33066 | R49: =$R$7 -> 294.60561 | S49: =$S$7 -> 205.94276 | T49: =$T$7 -> 212.56873 | U49: =$U$7 -> 222.95739 | V49: =$V$7 -> 211.35138 | W49: =$W$7 -> 219.4945 | AB49: =$AB$7 -> 130.65 | AC49: =$AC$7 -> 130.65 | AD49: =$AD$7 -> 130.65 | AE49: =$AE$7 -> 112.346 | AF49: =$AF$7 -> 127.7216 | AG49: =$AG$7 -> 125.81784 | AH49: =$AH$7 -> 122.5964 | AI49: =$AI$7 -> 0 | AJ49: =$AJ$7 -> 0 | AM49: =CIF!$X$5+VLOOKUP($AM$5&$E49,OCEAN!$E:$J,5,FALSE) -> #N/A | AN49: =CIF!$X$6+VLOOKUP($AN$5&$E49,OCEAN!$E:$J,5,FALSE) -> 581.70063 | AO49: =CIF!$X$7+VLOOKUP($AO$5&$E49,OCEAN!$E:$J,5,FALSE) -> 581.70063 | AP49: =CIF!$X$8+VLOOKUP($AP$5&$E49,OCEAN!$E:$J,5,FALSE) -> 781.04545 | AQ49: =CIF!$X$9+VLOOKUP($AQ$5&$E49,OCEAN!$E:$J,5,FALSE) -> 540.22727 | AR49: =AVERAGE(IF(ISNUMBER(AM49),AM49,""),IF(ISNUMBER(AO49),AO49,""),IF(ISNUMBER(AP49),AP49,""),IF(ISNUMBER(AQ49),AQ49,"")) -> #VALUE! | AS49: =AVERAGE(IF(ISNUMBER(AP49),AP49,""),IF(ISNUMBER(AQ49),AQ49,"")) -> 660.63636 | AX49: =COSTS!C24+COSTS!D24+COSTS!E24 -> 14.7352 | AY49: =COSTS!C24+COSTS!D24+COSTS!E24 -> 14.7352 | AZ49: =COSTS!C24+COSTS!D24+COSTS!E24 -> 14.7352 | BA49: =COSTS!C24+COSTS!D24+COSTS!E24 -> 14.7352 | BB49: =COSTS!C24+COSTS!D24+COSTS!E24 -> 14.7352 | BC49: =COSTS!C24+COSTS!D24+COSTS!E24 -> 14.7352 | BD49: =COSTS!C24+COSTS!D24+COSTS!E24 -> 14.7352 | BE49: =COSTS!C24+COSTS!D24+COSTS!E24 -> 14.7352 | BF49: =COSTS!C24+COSTS!D24+COSTS!E24 -> 14.7352 | BI49: =COSTS!F24+COSTS!G24+COSTS!H24 -> 97.452055 | BJ49: =COSTS!F24+COSTS!G24+COSTS!H24 -> 97.452055 | BK49: =COSTS!F24+COSTS!G24+COSTS!H24 -> 97.452055 | BL49: =COSTS!F24+COSTS!G24+COSTS!H24 -> 97.452055 | BM49: =COSTS!F24+COSTS!G24+COSTS!H24 -> 97.452055 | BN49: =COSTS!F24+COSTS!G24+COSTS!H24 -> 97.452055 | BO49: =COSTS!F24+COSTS!G24+COSTS!H24 -> 97.452055 | BP49: =COSTS!F24+COSTS!G24+COSTS!H24 -> 97.452055 | BQ49: =COSTS!F24+COSTS!G24+COSTS!H24 -> 97.452055 | BT49: =F49+Q49+AB49+AM49+AX49+BI49 -> #N/A | BU49: =G49+R49+AC49+AN49+AY49+BJ49 -> 1427.8255 | BV49: =H49+S49+AD49+AO49+AZ49+BK49 -> 1482.8111 | BW49: =I49+T49+AE49+AP49+BA49+BL49 -> 1324.7974 | BX49: =J49+U49+AF49+AQ49+BB49+BM49 -> 1066.7663 | BY49: =K49+V49+AG49+AR49+BC49+BN49 -> #VALUE! | BZ49: =L49+W49+AH49+AS49+BD49+BO49 -> 1192.9131 | CA49: =M49+X49+AI49+AT49+BE49+BP49 -> 112.18725 | CB49: =N49+Y49+AJ49+AU49+BF49+BQ49 -> 112.18725 | CE49: =BT49-$BT$7 -> #N/A | CF49: =BU49-$BU$7 -> 201.69075 | CG49: =BV49-$BV$7 -> 198.25031 | CH49: =BW49-$BW$7 -> 403.19467 | CI49: =BX49-$BX$7 -> 273.85376 | CJ49: =BY49-$BY$7 -> #VALUE! | CK49: =BZ49-$BZ$7 -> 339.30831
E50: Salerno | F50: =$F$7 -> 307.52024 | G50: =$G$7 -> 308.68205 | H50: =$H$7 -> 452.33046 | I50: =$I$7 -> 106.65 | J50: =$J$7 -> 63.672813 | K50: =$K$7 -> 198.76926 | L50: =$L$7 -> 77.998542 | Q50: =$Q$7 -> 192.33066 | R50: =$R$7 -> 294.60561 | S50: =$S$7 -> 205.94276 | T50: =$T$7 -> 212.56873 | U50: =$U$7 -> 222.95739 | V50: =$V$7 -> 211.35138 | W50: =$W$7 -> 219.4945 | AB50: =$AB$7 -> 130.65 | AC50: =$AC$7 -> 130.65 | AD50: =$AD$7 -> 130.65 | AE50: =$AE$7 -> 112.346 | AF50: =$AF$7 -> 127.7216 | AG50: =$AG$7 -> 125.81784 | AH50: =$AH$7 -> 122.5964 | AI50: =$AI$7 -> 0 | AJ50: =$AJ$7 -> 0 | AM50: =CIF!$X$5+VLOOKUP($AM$5&$E50,OCEAN!$E:$J,5,FALSE) -> #N/A | AN50: =CIF!$X$6+VLOOKUP($AN$5&$E50,OCEAN!$E:$J,5,FALSE) -> 704.4279 | AO50: =CIF!$X$7+VLOOKUP($AO$5&$E50,OCEAN!$E:$J,5,FALSE) -> 704.4279 | AP50: =CIF!$X$8+VLOOKUP($AP$5&$E50,OCEAN!$E:$J,5,FALSE) -> 650.36364 | AQ50: =CIF!$X$9+VLOOKUP($AQ$5&$E50,OCEAN!$E:$J,5,FALSE) -> 468.40909 | AR50: =AVERAGE(IF(ISNUMBER(AM50),AM50,""),IF(ISNUMBER(AO50),AO50,""),IF(ISNUMBER(AP50),AP50,""),IF(ISNUMBER(AQ50),AQ50,"")) -> #VALUE! | AS50: =AVERAGE(IF(ISNUMBER(AP50),AP50,""),IF(ISNUMBER(AQ50),AQ50,"")) -> 559.38636 | AX50: =COSTS!C24+COSTS!D24+COSTS!E24 -> 14.7352 | AY50: =COSTS!C24+COSTS!D24+COSTS!E24 -> 14.7352 | AZ50: =COSTS!C24+COSTS!D24+COSTS!E24 -> 14.7352 | BA50: =COSTS!C24+COSTS!D24+COSTS!E24 -> 14.7352 | BB50: =COSTS!C24+COSTS!D24+COSTS!E24 -> 14.7352 | BC50: =COSTS!C24+COSTS!D24+COSTS!E24 -> 14.7352 | BD50: =COSTS!C24+COSTS!D24+COSTS!E24 -> 14.7352 | BE50: =COSTS!C24+COSTS!D24+COSTS!E24 -> 14.7352 | BF50: =COSTS!C24+COSTS!D24+COSTS!E24 -> 14.7352 | BI50: =COSTS!F24+COSTS!G24+COSTS!H24 -> 97.452055 | BJ50: =COSTS!F24+COSTS!G24+COSTS!H24 -> 97.452055 | BK50: =COSTS!F24+COSTS!G24+COSTS!H24 -> 97.452055 | BL50: =COSTS!F24+COSTS!G24+COSTS!H24 -> 97.452055 | BM50: =COSTS!F24+COSTS!G24+COSTS!H24 -> 97.452055 | BN50: =COSTS!F24+COSTS!G24+COSTS!H24 -> 97.452055 | BO50: =COSTS!F24+COSTS!G24+COSTS!H24 -> 97.452055 | BP50: =COSTS!F24+COSTS!G24+COSTS!H24 -> 97.452055 | BQ50: =COSTS!F24+COSTS!G24+COSTS!H24 -> 97.452055 | BT50: =F50+Q50+AB50+AM50+AX50+BI50 -> #N/A | BU50: =G50+R50+AC50+AN50+AY50+BJ50 -> 1550.5528 | BV50: =H50+S50+AD50+AO50+AZ50+BK50 -> 1605.5384 | BW50: =I50+T50+AE50+AP50+BA50+BL50 -> 1194.1156 | BX50: =J50+U50+AF50+AQ50+BB50+BM50 -> 994.94815 | BY50: =K50+V50+AG50+AR50+BC50+BN50 -> #VALUE! | BZ50: =L50+W50+AH50+AS50+BD50+BO50 -> 1091.6631 | CA50: =M50+X50+AI50+AT50+BE50+BP50 -> 112.18725 | CB50: =N50+Y50+AJ50+AU50+BF50+BQ50 -> 112.18725 | CE50: =BT50-$BT$7 -> #N/A | CF50: =BU50-$BU$7 -> 324.41802 | CG50: =BV50-$BV$7 -> 320.97758 | CH50: =BW50-$BW$7 -> 272.51285 | CI50: =BX50-$BX$7 -> 202.03558 | CJ50: =BY50-$BY$7 -> #VALUE! | CK50: =BZ50-$BZ$7 -> 238.05831
A52: Other | B52: OT | C52: - | D52: - | E52: Dalian | F52: =$F$7 -> 307.52024 | G52: =$G$7 -> 308.68205 | H52: =$H$7 -> 452.33046 | I52: =$I$7 -> 106.65 | J52: =$J$7 -> 63.672813 | K52: =$K$7 -> 198.76926 | L52: =$L$7 -> 77.998542 | Q52: =$Q$7 -> 192.33066 | R52: =$R$7 -> 294.60561 | S52: =$S$7 -> 205.94276 | T52: =$T$7 -> 212.56873 | U52: =$U$7 -> 222.95739 | V52: =$V$7 -> 211.35138 | W52: =$W$7 -> 219.4945 | AB52: =$AB$7 -> 130.65 | AC52: =$AC$7 -> 130.65 | AD52: =$AD$7 -> 130.65 | AE52: =$AE$7 -> 112.346 | AF52: =$AF$7 -> 127.7216 | AG52: =$AG$7 -> 125.81784 | AH52: =$AH$7 -> 122.5964 | AI52: =$AI$7 -> 0 | AJ52: =$AJ$7 -> 0 | AM52: =CIF!$X$5+VLOOKUP($AM$5&$E52,OCEAN!$E:$J,5,FALSE) -> 476.13636 | AN52: =CIF!$X$6+VLOOKUP($AN$5&$E52,OCEAN!$E:$J,5,FALSE) -> 392.60972 | AO52: =CIF!$X$7+VLOOKUP($AO$5&$E52,OCEAN!$E:$J,5,FALSE) -> 392.60972 | AP52: =CIF!$X$8+VLOOKUP($AP$5&$E52,OCEAN!$E:$J,5,FALSE) -> 473.31818 | AQ52: =CIF!$X$9+VLOOKUP($AQ$5&$E52,OCEAN!$E:$J,5,FALSE) -> 325.68182 | AR52: =AVERAGE(IF(ISNUMBER(AM52),AM52,""),IF(ISNUMBER(AO52),AO52,""),IF(ISNUMBER(AP52),AP52,""),IF(ISNUMBER(AQ52),AQ52,"")) -> 416.93652 | AV52: =CIF!$X$16+VLOOKUP($AV$6&$E52,OCEAN!$E:$J,5,FALSE) -> 76.2043 | AW52: =CIF!$X$17+VLOOKUP($AW$6&$E52,OCEAN!$E:$J,5,FALSE) -> #N/A | BT52: =F52+Q52+AB52+AM52+AX52+BI52 -> 1106.6373 | BU52: =G52+R52+AC52+AN52+AY52+BJ52 -> 1126.5474 | BV52: =H52+S52+AD52+AO52+AZ52+BK52 -> 1181.5329 | BW52: =I52+T52+AE52+AP52+BA52+BL52 -> 904.88291 | BX52: =J52+U52+AF52+AQ52+BB52+BM52 -> 740.03362 | BY52: =K52+V52+AG52+AR52+BC52+BN52 -> 952.87501 | BZ52: =L52+W52+AH52+AS52+BD52+BO52 -> 420.08944 | CA52: =M52+X52+AI52+AT52+BE52+BP52 -> 0 | ... CD52: =P52+AA52+AL52+AW52+BH52+BS52 -> #N/A
AT54: SLC - MR5 | AU54: SLC - ER5 | CA54: SLC - MR5 | CB54: SLC - ER5 | CL54: SLC - MR5 | CM54: SLC - ER5
A55: Domestic | B55: OE | E55: Salisbury | F55: =$F$7 -> 307.52024 | G55: =$G$7 -> 308.68205 | H55: =H7 -> 452.33046 | I55: =I7 -> 106.65 | J55: =J7 -> 63.672813 | K55: =K7 -> 198.76926 | L55: =L7 -> 77.998542 | T55: {=AVERAGE(_xlfn._xlws.FILTER(PTS!AX:AX, (PTS!$E:$E="Memphis Rule 5") * ISNUMBER(PTS!AX:AX)))} -> 466.61157 | U55: {=AVERAGE(_xlfn._xlws.FILTER(PTS!AX:AX, (PTS!$E:$E="Ga 30 Day") * ISNUMBER(PTS!AX:AX)))} -> 298.76598 | W55: =AVERAGE(T55,U55) -> 382.68878 | AE55: =((COSTS!AA22+COSTS!AC22)*20) -> 59.414 | AF55: =((COSTS!AA22+COSTS!AC22)*20) -> 59.414 | AH55: =((COSTS!AA22+COSTS!AC22)*20) -> 59.414 | BA55: 8 | BB55: 8 | BD55: 8 | BW55: =I55+T55+AE55+AP55+BA55+BL55 -> 640.67557 | BX55: =J55+U55+AF55+AQ55+BB55+BM55 -> 429.85279 | BZ55: =L55+W55+AH55+AS55+BD55+BO55 -> 528.10132 | CH55: =BW55-$BW$7 -> -280.9272 | CI55: =BX55-$BX$7 -> -363.05978
B56: RS | E56: Mocksville | F56: =$F$7 -> 307.52024 | G56: =$G$7 -> 308.68205 | H56: =H8 -> 452.33046 | I56: =I8 -> 106.65 | J56: =J8 -> 63.672813 | K56: =K8 -> 198.76926 | L56: =L8 -> 77.998542 | T56: =T55 -> 466.61157 | U56: =U55 -> 298.76598 | W56: =W55 -> 382.68878 | AE56: =AE55 -> 59.414 | AF56: =AF55 -> 59.414 | AH56: =AH55 -> 59.414 | BA56: 8 | BB56: 8 | BD56: 8 | BW56: =I56+T56+AE56+AP56+BA56+BL56 -> 640.67557 | BX56: =J56+U56+AF56+AQ56+BB56+BM56 -> 429.85279 | BZ56: =L56+W56+AH56+AS56+BD56+BO56 -> 528.10132 | CH56: =BW56-$BW$7 -> -280.9272 | CI56: =BX56-$BX$7 -> -363.05978
B57: OE | E57: Sanford | F57: =$F$7 -> 307.52024 | G57: =$G$7 -> 308.68205 | H57: =H9 -> 452.33046 | I57: =I9 -> 106.65 | J57: =J9 -> 63.672813 | K57: =K9 -> 198.76926 | L57: =L9 -> 77.998542 | T57: =T56 -> 466.61157 | U57: =U56 -> 298.76598 | W57: =W56 -> 382.68878 | AE57: =AE56 -> 59.414 | AF57: =AF56 -> 59.414 | AH57: =AH56 -> 59.414 | AT57: Price direct to Mill from Mail Region Pts | BA57: 8 | BB57: 8 | BD57: 8 | BW57: =I57+T57+AE57+AP57+BA57+BL57 -> 640.67557 | BX57: =J57+U57+AF57+AQ57+BB57+BM57 -> 429.85279 | BZ57: =L57+W57+AH57+AS57+BD57+BO57 -> 528.10132 | CH57: =BW57-$BW$7 -> -280.9272 | CI57: =BX57-$BX$7 -> -363.05978
B58: OE | E58: Mayodan | F58: =$F$7 -> 307.52024 | G58: =$G$7 -> 308.68205 | H58: =H10 -> 452.33046 | I58: =I10 -> 106.65 | J58: =J10 -> 63.672813 | K58: =K10 -> 198.76926 | L58: =L10 -> 77.998542 | T58: =T57 -> 466.61157 | U58: =U57 -> 298.76598 | W58: =W57 -> 382.68878 | AE58: =AE57 -> 59.414 | AF58: =AF57 -> 59.414 | AH58: =AH57 -> 59.414 | AN58: add mill lanes to OTR sheet | BA58: 8 | BB58: 8 | BD58: 8 | BW58: =I58+T58+AE58+AP58+BA58+BL58 -> 640.67557 | BX58: =J58+U58+AF58+AQ58+BB58+BM58 -> 429.85279 | BZ58: =L58+W58+AH58+AS58+BD58+BO58 -> 528.10132 | CH58: =BW58-$BW$7 -> -280.9272 | CI58: =BX58-$BX$7 -> -363.05978
B59: MVS | E59: Clarkton | F59: =$F$7 -> 307.52024 | G59: =$G$7 -> 308.68205 | H59: =H11 -> 452.33046 | I59: =I11 -> 106.65 | J59: =J11 -> 63.672813 | K59: =K11 -> 198.76926 | L59: =L11 -> 77.998542 | T59: =T58 -> 466.61157 | U59: =U58 -> 298.76598 | W59: =W58 -> 382.68878 | AE59: =AE58 -> 59.414 | AF59: =AF58 -> 59.414 | AH59: =AH58 -> 59.414 | BA59: 8 | BB59: 8 | BD59: 8 | BW59: =I59+T59+AE59+AP59+BA59+BL59 -> 640.67557 | BX59: =J59+U59+AF59+AQ59+BB59+BM59 -> 429.85279 | BZ59: =L59+W59+AH59+AS59+BD59+BO59 -> 528.10132 | CH59: =BW59-$BW$7 -> -280.9272 | CI59: =BX59-$BX$7 -> -363.05978
B60: RS | E60: Eden | F60: =$F$7 -> 307.52024 | G60: =$G$7 -> 308.68205 | H60: =H12 -> 452.33046 | I60: =I12 -> 106.65 | J60: =J12 -> 63.672813 | K60: =K12 -> 198.76926 | L60: =L12 -> 77.998542 | T60: =T59 -> 466.61157 | U60: =U59 -> 298.76598 | W60: =W59 -> 382.68878 | AE60: =AE59 -> 59.414 | AF60: =AF59 -> 59.414 | AH60: =AH59 -> 59.414 | BA60: 8 | BB60: 8 | BD60: 8 | BW60: =I60+T60+AE60+AP60+BA60+BL60 -> 640.67557 | BX60: =J60+U60+AF60+AQ60+BB60+BM60 -> 429.85279 | BZ60: =L60+W60+AH60+AS60+BD60+BO60 -> 528.10132 | CH60: =BW60-$BW$7 -> -280.9272 | CI60: =BX60-$BX$7 -> -363.05978
B61: PD | E61: Gaffney | F61: =$F$7 -> 307.52024 | G61: =$G$7 -> 308.68205 | H61: =H13 -> 452.33046 | I61: =I13 -> 106.65 | J61: =J13 -> 63.672813 | K61: =K13 -> 198.76926 | L61: =L13 -> 77.998542 | T61: =T60 -> 466.61157 | U61: =U60 -> 298.76598 | W61: =W60 -> 382.68878 | AE61: =AE60 -> 59.414 | AF61: =AF60 -> 59.414 | AH61: =AH60 -> 59.414 | BA61: 8 | BB61: 8 | BD61: 8 | BW61: =I61+T61+AE61+AP61+BA61+BL61 -> 640.67557 | BX61: =J61+U61+AF61+AQ61+BB61+BM61 -> 429.85279 | BZ61: =L61+W61+AH61+AS61+BD61+BO61 -> 528.10132 | CH61: =BW61-$BW$7 -> -280.9272 | CI61: =BX61-$BX$7 -> -363.05978
B62: PD | E62: Rabun Gap | F62: =$F$7 -> 307.52024 | G62: =$G$7 -> 308.68205 | H62: =H14 -> 452.33046 | I62: =I14 -> 106.65 | J62: =J14 -> 63.672813 | K62: =K14 -> 198.76926 | L62: =L14 -> 77.998542 | T62: =T61 -> 466.61157 | U62: =U61 -> 298.76598 | W62: =W61 -> 382.68878 | AE62: =AE61 -> 59.414 | AF62: =AF61 -> 59.414 | AH62: =AH61 -> 59.414 | BA62: 8 | BB62: 8 | BD62: 8 | BW62: =I62+T62+AE62+AP62+BA62+BL62 -> 640.67557 | BX62: =J62+U62+AF62+AQ62+BB62+BM62 -> 429.85279 | BZ62: =L62+W62+AH62+AS62+BD62+BO62 -> 528.10132 | CH62: =BW62-$BW$7 -> -280.9272 | CI62: =BX62-$BX$7 -> -363.05978
B63: KEER | E63: Indian Land | F63: =$F$7 -> 307.52024 | G63: =$G$7 -> 308.68205 | H63: =H15 -> 452.33046 | I63: =I15 -> 106.65 | J63: =J15 -> 63.672813 | K63: =K15 -> 198.76926 | L63: =L15 -> 77.998542 | T63: =T62 -> 466.61157 | U63: =U62 -> 298.76598 | W63: =W62 -> 382.68878 | AE63: =AE62 -> 59.414 | AF63: =AF62 -> 59.414 | AH63: =AH62 -> 59.414 | BA63: 8 | BB63: 8 | BD63: 8 | BW63: =I63+T63+AE63+AP63+BA63+BL63 -> 640.67557 | BX63: =J63+U63+AF63+AQ63+BB63+BM63 -> 429.85279 | BZ63: =L63+W63+AH63+AS63+BD63+BO63 -> 528.10132 | CH63: =BW63-$BW$7 -> -280.9272 | CI63: =BX63-$BX$7 -> -363.05978

Sheet OFFERS
B3: PND TO MAP TO OFFER SHEET
F5: PREIMIUM AND DISCOUNTS
C6: TT | D6: FT | F6: WTX | G6: WTXH | H6: STX | I6: MR5 | J6: ER5 | K6: EMOT | L6: ME | M6: HOU | N6: DAL | O6: BRZ | P6: AUS
A7: Base | E7: CIF FE | F7: =EXPORT!CE7 -> 0 | G7: =EXPORT!CF7 -> 0 | H7: =EXPORT!CG7 -> 0 | I7: =EXPORT!CH7 -> 0 | J7: =EXPORT!CI7 -> 0 | K7: =EXPORT!CJ7 -> 0 | L7: =EXPORT!CK7 -> 0 | M7: =EXPORT!CL7 -> 0 | N7: =EXPORT!CM7 -> 0
A8: China | B8: CN | C8: 38 | D8: 18 | E8: Qingdao | F8: =EXPORT!CE8 -> 0 | G8: =EXPORT!CF8 -> 1.0188088 | H8: =EXPORT!CG8 -> -2.4216301 | I8: =EXPORT!CH8 -> -1.5681818 | J8: =EXPORT!CI8 -> 0 | K8: =EXPORT!CJ8 -> 0 | L8: =EXPORT!CK8 -> 0 | M8: =EXPORT!CL8 -> 0 | N8: =EXPORT!CM8 -> 0
E9: Xiamen | F9: =EXPORT!CE9 -> -52.272727 | G9: =EXPORT!CF9 -> -26.481191 | H9: =EXPORT!CG9 -> -29.92163 | I9: =EXPORT!CH9 -> -36.568182 | J9: =EXPORT!CI9 -> 40.909091 | K9: =EXPORT!CJ9 -> -18.465909 | L9: =EXPORT!CK9 -> 2.9545455 | M9: =EXPORT!CL9 -> 0 | N9: =EXPORT!CM9 -> 0
E10: Lianyungang | F10: =EXPORT!CE10 -> 129.54545 | G10: =EXPORT!CF10 -> 7.8369906 | H10: =EXPORT!CG10 -> 4.3965517 | I10: =EXPORT!CH10 -> 72.522727 | J10: =EXPORT!CI10 -> 54.545455 | K10: =EXPORT!CJ10 -> 66.25 | L10: =EXPORT!CK10 -> 64.318182 | M10: =EXPORT!CL10 -> 0 | N10: =EXPORT!CM10 -> 0
A11: Vietnam | B11: VN | C11: 50 | D11: 14 | E11: Ho Chi Minh | F11: =EXPORT!CE11 -> 30.942997 | G11: =EXPORT!CF11 -> 40.370896 | H11: =EXPORT!CG11 -> 36.930457 | I11: =EXPORT!CH11 -> 92.102087 | J11: =EXPORT!CI11 -> 51.852087 | K11: =EXPORT!CJ11 -> 84.839693 | L11: =EXPORT!CK11 -> 123.08939 | M11: =EXPORT!CL11 -> 0 | N11: =EXPORT!CM11 -> 0
E12: DaNang | F12: =EXPORT!CE12 -> 143.67027 | G12: =EXPORT!CF12 -> 117.18908 | H12: =EXPORT!CG12 -> 113.74864 | I12: =EXPORT!CH12 -> 173.46572 | J12: =EXPORT!CI12 -> 109.80663 | K12: =EXPORT!CJ12 -> 167.0556 | L12: =EXPORT!CK12 -> 192.74848 | M12: =EXPORT!CL12 -> 0 | N12: =EXPORT!CM12 -> 0
E13: Haiphong | F13: =EXPORT!CE13 -> 25.261178 | G13: =EXPORT!CF13 -> 26.279987 | H13: =EXPORT!CG13 -> 22.839548 | I13: =EXPORT!CH13 -> 86.192997 | J13: =EXPORT!CI13 -> 49.806633 | K13: =EXPORT!CJ13 -> 77.907875 | L13: =EXPORT!CK13 -> 119.11212 | M13: =EXPORT!CL13 -> 0 | N13: =EXPORT!CM13 -> 0
A14: Korea | B14: KO | C14: 46 | D14: 18 | E14: Busan | F14: =EXPORT!CE14 -> -36.714031 | G14: =EXPORT!CF14 -> -44.331585 | H14: =EXPORT!CG14 -> -47.772024 | I14: =EXPORT!CH14 -> -6.4640306 | J14: =EXPORT!CI14 -> -28.759485 | K14: =EXPORT!CJ14 -> 32.791394 | L14: =EXPORT!CK14 -> 64.336549 | M14: =EXPORT!CL14 -> 0 | N14: =EXPORT!CM14 -> 0
E15: Kwangyang | F15: =EXPORT!CE15 -> 24.652451 | G15: =EXPORT!CF15 -> 38.168415 | H15: =EXPORT!CG15 -> 34.727976 | I15: =EXPORT!CH15 -> 56.035969 | J15: =EXPORT!CI15 -> 47.831424 | K15: =EXPORT!CJ15 -> 103.87094 | L15: =EXPORT!CK15 -> 133.882 | M15: =EXPORT!CL15 -> 0 | N15: =EXPORT!CM15 -> 0
A16: Japan | B16: JP | C16: 43 | D16: 14 | E16: Osaka | F16: =EXPORT!CE16 -> -3.1020307 | G16: =EXPORT!CF16 -> 46.780414 | H16: =EXPORT!CG16 -> 43.339976 | I16: =EXPORT!CH16 -> 59.420697 | J16: =EXPORT!CI16 -> 75.30706 | K16: =EXPORT!CJ16 -> 116.73888 | L16: =EXPORT!CK16 -> 159.59085 | M16: =EXPORT!CL16 -> 0 | N16: =EXPORT!CM16 -> 0
E17: Kobe | F17: =EXPORT!CE17 -> -47.19294 | G17: =EXPORT!CF17 -> -10.037767 | H17: =EXPORT!CG17 -> -13.478206 | I17: =EXPORT!CH17 -> 59.420697 | J17: =EXPORT!CI17 -> -9.2383943 | K17: =EXPORT!CJ17 -> 70.375242 | L17: =EXPORT!CK17 -> 117.31812 | M17: =EXPORT!CL17 -> 0 | N17: =EXPORT!CM17 -> 0
E18: Nagoya | F18: =EXPORT!CE18 -> -47.19294 | G18: =EXPORT!CF18 -> -10.037767 | H18: =EXPORT!CG18 -> -13.478206 | I18: =EXPORT!CH18 -> 59.420697 | J18: =EXPORT!CI18 -> -9.6929397 | K18: =EXPORT!CJ18 -> 70.261606 | L18: =EXPORT!CK18 -> 117.09085 | M18: =EXPORT!CL18 -> 0 | N18: =EXPORT!CM18 -> 0
A19: Malaysia | B19: MA | C19: 40 | D19: 14 | E19: Tanjung Pelepas | F19: =EXPORT!CE19 -> 189.68229 | G19: =EXPORT!CF19 -> 77.519283 | H19: =EXPORT!CG19 -> 74.078844 | I19: =EXPORT!CH19 -> 125.38684 | J19: =EXPORT!CI19 -> 83.773201 | K19: =EXPORT!CJ19 -> 119.22775 | L19: =EXPORT!CK19 -> 105.36411 | M19: =EXPORT!CL19 -> 0 | N19: =EXPORT!CM19 -> 0
E20: Penang | F20: =EXPORT!CE20 -> -20.999526 | G20: =EXPORT!CF20 -> 105.47383 | H20: =EXPORT!CG20 -> 102.03339 | I20: =EXPORT!CH20 -> 158.34138 | J20: =EXPORT!CI20 -> 41.500474 | K20: =EXPORT!CJ20 -> 71.216383 | L20: =EXPORT!CK20 -> 100.70502 | M20: =EXPORT!CL20 -> 0 | N20: =EXPORT!CM20 -> 0
E21: Port Klang | F21: =EXPORT!CE21 -> -34.63589 | G21: =EXPORT!CF21 -> -5.2079899 | H21: =EXPORT!CG21 -> -8.6484288 | I21: =EXPORT!CH21 -> 60.61411 | J21: =EXPORT!CI21 -> 19.682292 | K21: =EXPORT!CJ21 -> 10.250474 | L21: =EXPORT!CK21 -> 40.932292 | M21: =EXPORT!CL21 -> 0 | N21: =EXPORT!CM21 -> 0
A22: Taiwan | B22: TW | C22: 45 | D22: 21 | E22: Keelung | F22: =EXPORT!CE22 -> -20.812653 | G22: =EXPORT!CF22 -> -40.475663 | H22: =EXPORT!CG22 -> -43.916102 | I22: =EXPORT!CH22 -> 85.57371 | J22: =EXPORT!CI22 -> 28.505528 | K22: =EXPORT!CJ22 -> 13.335074 | L22: =EXPORT!CK22 -> 57.82371 | M22: =EXPORT!CL22 -> 0 | N22: =EXPORT!CM22 -> 0
E23: Taichung | F23: =EXPORT!CE23 -> -9.6762898 | G23: =EXPORT!CF23 -> -63.202936 | H23: =EXPORT!CG23 -> -66.643374 | I23: =EXPORT!CH23 -> 64.437347 | J23: =EXPORT!CI23 -> -5.5853807 | K23: =EXPORT!CJ23 -> -3.3694716 | L23: =EXPORT!CK23 -> 30.210074 | M23: =EXPORT!CL23 -> 0 | N23: =EXPORT!CM23 -> 0
E24: Kaohsiung | F24: =EXPORT!CE24 -> -33.539926 | G24: =EXPORT!CF24 -> -74.566572 | H24: =EXPORT!CG24 -> -78.007011 | I24: =EXPORT!CH24 -> -3.2899261 | J24: =EXPORT!CI24 -> -16.949017 | K24: =EXPORT!CJ24 -> -31.949017 | L24: =EXPORT!CK24 -> -9.3353807 | M24: =EXPORT!CL24 -> 0 | N24: =EXPORT!CM24 -> 0
E25: Tao Yuan | F25: =EXPORT!CE25 -> 1.9146193 | G25: =EXPORT!CF25 -> 27.706155 | H25: =EXPORT!CG25 -> 24.265716 | I25: =EXPORT!CH25 -> 108.52826 | J25: =EXPORT!CI25 -> 32.141892 | K25: =EXPORT!CJ25 -> 42.710074 | L25: =EXPORT!CK25 -> 71.119165 | M25: =EXPORT!CL25 -> 0 | N25: =EXPORT!CM25 -> 0
A26: Indonesia | B26: ID | C26: 38 | D26: 14 | E26: Jakarta | F26: =EXPORT!CE26 -> 32.903127 | G26: =EXPORT!CF26 -> 65.96739 | H26: =EXPORT!CG26 -> 62.526951 | I26: =EXPORT!CH26 -> 127.01676 | J26: =EXPORT!CI26 -> 104.94858 | K26: =EXPORT!CJ26 -> 82.846308 | L26: =EXPORT!CK26 -> 116.76676 | M26: =EXPORT!CL26 -> 0 | N26: =EXPORT!CM26 -> 0
E27: Semarang | F27: =EXPORT!CE27 -> 98.584945 | G27: =EXPORT!CF27 -> 65.96739 | H27: =EXPORT!CG27 -> 62.526951 | I27: =EXPORT!CH27 -> 127.01676 | J27: =EXPORT!CI27 -> 145.85767 | K27: =EXPORT!CJ27 -> 109.49404 | L27: =EXPORT!CK27 -> 137.22131 | M27: =EXPORT!CL27 -> 0 | N27: =EXPORT!CM27 -> 0
E28: Cikarang | F28: =EXPORT!CE28 -> 144.03949 | G28: =EXPORT!CF28 -> 285.96739 | H28: =EXPORT!CG28 -> 282.52695 | I28: =EXPORT!CH28 -> 239.28949 | J28: =EXPORT!CI28 -> 192.22131 | K28: =EXPORT!CJ28 -> 215.51676 | L28: =EXPORT!CK28 -> 216.53949 | M28: =EXPORT!CL28 -> 0 | N28: =EXPORT!CM28 -> 0
E29: Surabaya | F29: =EXPORT!CE29 -> 98.584945 | G29: =EXPORT!CF29 -> 65.96739 | H29: =EXPORT!CG29 -> 62.526951 | I29: =EXPORT!CH29 -> 127.01676 | J29: =EXPORT!CI29 -> 108.81222 | K29: =EXPORT!CJ29 -> 100.23267 | L29: =EXPORT!CK29 -> 118.69858 | M29: =EXPORT!CL29 -> 0 | N29: =EXPORT!CM29 -> 0
A30: Thailand | B30: TH | C30: 45 | D30: 14 | E30: Bangkok | F30: =EXPORT!CE30 -> -2.0173687 | G30: =EXPORT!CF30 -> 26.046895 | H30: =EXPORT!CG30 -> 22.606456 | I30: =EXPORT!CH30 -> 119.59627 | J30: =EXPORT!CI30 -> 1.6189949 | K30: =EXPORT!CJ30 -> 36.44854 | L30: =EXPORT!CK30 -> 61.391722 | M30: =EXPORT!CL30 -> 0 | N30: =EXPORT!CM30 -> 0
E31: Lat Krabang | F31: =EXPORT!CE31 -> -2.0173687 | G31: =EXPORT!CF31 -> 12.410531 | H31: =EXPORT!CG31 -> 8.9700921 | I31: =EXPORT!CH31 -> 43.232631 | J31: =EXPORT!CI31 -> 15.028086 | K31: =EXPORT!CJ31 -> 17.300813 | L31: =EXPORT!CK31 -> 29.914449 | M31: =EXPORT!CL31 -> 0 | N31: =EXPORT!CM31 -> 0
E32: Laem Chabang | F32: =EXPORT!CE32 -> 9.3462676 | G32: =EXPORT!CF32 -> 49.455986 | H32: =EXPORT!CG32 -> 46.015547 | I32: =EXPORT!CH32 -> 81.868995 | J32: =EXPORT!CI32 -> 5.709904 | K32: =EXPORT!CJ32 -> 36.732631 | L32: =EXPORT!CK32 -> 44.57354 | M32: =EXPORT!CL32 -> 0 | N32: =EXPORT!CM32 -> 0
A33: Bangladesh | B33: BD | C33: 52 | D33: 14 | E33: Chittagong | F33: =EXPORT!CE33 -> 437.45734 | G33: =EXPORT!CF33 -> 395.06706 | H33: =EXPORT!CG33 -> 391.62662 | I33: =EXPORT!CH33 -> 419.07098 | J33: =EXPORT!CI33 -> 424.27552 | K33: =EXPORT!CJ33 -> 419.10507 | L33: =EXPORT!CK33 -> 422.45734 | M33: =EXPORT!CL33 -> 0 | N33: =EXPORT!CM33 -> 0
A34: Pakistan | B34: PK | C34: 45 | D34: 14 | E34: Port Qasim/Karachi | F34: =EXPORT!CE34 -> 616.22213 | G34: =EXPORT!CF34 -> 456.10457 | H34: =EXPORT!CG34 -> 452.66413 | I34: =EXPORT!CH34 -> 393.29031 | J34: =EXPORT!CI34 -> 345.54031 | K34: =EXPORT!CJ34 -> 452.92667 | L34: =EXPORT!CK34 -> 370.1994 | M34: =EXPORT!CL34 -> 0 | N34: =EXPORT!CM34 -> 0
A35: India | B35: IN | C35: 50 | D35: 14 | E35: Mundra | F35: =EXPORT!CE35 -> 323.89402 | G35: =EXPORT!CF35 -> 261.27647 | H35: =EXPORT!CG35 -> 257.83603 | I35: =EXPORT!CH35 -> 173.4622 | J35: =EXPORT!CI35 -> 141.16675 | K35: =EXPORT!CJ35 -> 225.0872 | L35: =EXPORT!CK35 -> 158.09857 | M35: =EXPORT!CL35 -> 0 | N35: =EXPORT!CM35 -> 0
E36: Tuticorin | F36: =EXPORT!CE36 -> 115.7122 | G36: =EXPORT!CF36 -> 260.82192 | H36: =EXPORT!CG36 -> 257.38148 | I36: =EXPORT!CH36 -> 284.82584 | J36: =EXPORT!CI36 -> 294.1213 | K36: =EXPORT!CJ36 -> 239.00766 | L36: =EXPORT!CK36 -> 290.25766 | M36: =EXPORT!CL36 -> 0 | N36: =EXPORT!CM36 -> 0
E37: Nhava Sheva | F37: =EXPORT!CE37 -> 88.439477 | G37: =EXPORT!CF37 -> 187.6401 | H37: =EXPORT!CG37 -> 184.19967 | I37: =EXPORT!CH37 -> 173.4622 | J37: =EXPORT!CI37 -> 141.16675 | K37: =EXPORT!CJ37 -> 147.81448 | L37: =EXPORT!CK37 -> 158.09857 | M37: =EXPORT!CL37 -> 0 | N37: =EXPORT!CM37 -> 0
A38: Turkey | B38: TR | C38: 37 | D38: 14 | E38: Iskenderun | F38: =EXPORT!CE38 -> 407.1342 | G38: =EXPORT!CF38 -> 358.15301 | H38: =EXPORT!CG38 -> 354.71257 | I38: =EXPORT!CH38 -> 292.15693 | J38: =EXPORT!CI38 -> 210.08875 | K38: =EXPORT!CJ38 -> 317.02057 | L38: =EXPORT!CK38 -> 251.90693 | M38: =EXPORT!CL38 -> 0 | N38: =EXPORT!CM38 -> 0
E39: Mersin | F39: =EXPORT!CE39 -> 702.36148 | G39: =EXPORT!CF39 -> 365.65301 | H39: =EXPORT!CG39 -> 362.21257 | I39: =EXPORT!CH39 -> 330.56602 | J39: =EXPORT!CI39 -> 300.99784 | K39: =EXPORT!CJ39 -> 425.03193 | L39: =EXPORT!CK39 -> 316.56602 | M39: =EXPORT!CL39 -> 0 | N39: =EXPORT!CM39 -> 0
E40: Izmir | F40: =EXPORT!CE40 -> 703.04329 | G40: =EXPORT!CF40 -> 327.01665 | H40: =EXPORT!CG40 -> 323.57621 | I40: =EXPORT!CH40 -> 355.11148 | J40: =EXPORT!CI40 -> 307.36148 | K40: =EXPORT!CJ40 -> 423.27057 | L40: =EXPORT!CK40 -> 332.02057 | M40: =EXPORT!CL40 -> 0 | N40: =EXPORT!CM40 -> 0
A41: Mexico | B41: MX | D41: N/A | E41: Yecapixtla | F41: =EXPORT!CE41 -> 274.37944 | G41: =EXPORT!CF41 -> 272.64038 | H41: =EXPORT!CG41 -> 275.9714 | I41: =EXPORT!CH41 -> 497.21693 | J41: =EXPORT!CI41 -> 595.07126 | K41: =EXPORT!CJ41 -> 408.27977 | L41: =EXPORT!CK41 -> 542.63415 | M41: =EXPORT!CL41 -> 0 | N41: =EXPORT!CM41 -> 0
B42: Weslaco | E42: Parras | F42: =EXPORT!CE42 -> 86.879444 | G42: =EXPORT!CF42 -> 85.14038 | H42: =EXPORT!CG42 -> 88.471399 | I42: =EXPORT!CH42 -> 309.71693 | J42: =EXPORT!CI42 -> 407.57126 | K42: =EXPORT!CJ42 -> 220.77977 | L42: =EXPORT!CK42 -> 355.13415 | M42: =EXPORT!CL42 -> 0 | N42: =EXPORT!CM42 -> 0
E43: CD Victoria | F43: =EXPORT!CE43 -> 69.833989 | G43: =EXPORT!CF43 -> 68.094926 | H43: =EXPORT!CG43 -> 71.425945 | I43: =EXPORT!CH43 -> 292.67148 | J43: =EXPORT!CI43 -> 390.52581 | K43: =EXPORT!CJ43 -> 203.73432 | L43: =EXPORT!CK43 -> 338.08869 | M43: =EXPORT!CL43 -> 0 | N43: =EXPORT!CM43 -> 0
A44: Peru | B44: PE | C44: 11 | D44: 18 | E44: Callao | F44: =EXPORT!CE44 -> #N/A | G44: =EXPORT!CF44 -> 105.19324 | H44: =EXPORT!CG44 -> 101.7528 | I44: =EXPORT!CH44 -> 208.74261 | J44: =EXPORT!CI44 -> 155.3108 | K44: =EXPORT!CJ44 -> #VALUE! | L44: =EXPORT!CK44 -> 182.8108 | M44: =EXPORT!CL44 -> 0 | N44: =EXPORT!CM44 -> 0
A45: Guatemala | B45: GU | C45: 8 | D45: 21 | E45: Amatitlan | F45: =EXPORT!CE45 -> #N/A | G45: =EXPORT!CF45 -> 432.35589 | H45: =EXPORT!CG45 -> 428.91545 | I45: =EXPORT!CH45 -> 779.08708 | J45: =EXPORT!CI45 -> 674.5189 | K45: =EXPORT!CJ45 -> #VALUE! | L45: =EXPORT!CK45 -> 727.58708 | M45: =EXPORT!CL45 -> 0 | N45: =EXPORT!CM45 -> 0
E46: Palin | F46: =EXPORT!CE46 -> #N/A | G46: =EXPORT!CF46 -> 398.03771 | H46: =EXPORT!CG46 -> 394.59727 | I46: =EXPORT!CH46 -> 801.81435 | J46: =EXPORT!CI46 -> 697.24617 | K46: =EXPORT!CJ46 -> #VALUE! | L46: =EXPORT!CK46 -> 750.31435 | M46: =EXPORT!CL46 -> 0 | N46: =EXPORT!CM46 -> 0
A47: Honduras | B47: HO | C47: 11 | D47: 18 | E47: Naco | F47: =EXPORT!CE47 -> #N/A | G47: =EXPORT!CF47 -> 408.49225 | H47: =EXPORT!CG47 -> 405.05181 | I47: =EXPORT!CH47 -> #VALUE! | J47: =EXPORT!CI47 -> #VALUE! | K47: =EXPORT!CJ47 -> #VALUE! | L47: =EXPORT!CK47 -> #VALUE! | M47: =EXPORT!CL47 -> 0 | N47: =EXPORT!CM47 -> 0
A48: Spain | B48: ES | D48: 14 | E48: Santa Barbara | F48: =EXPORT!CE48 -> #N/A | G48: =EXPORT!CF48 -> 363.05439 | H48: =EXPORT!CG48 -> 359.61395 | I48: =EXPORT!CH48 -> 707.9674 | J48: =EXPORT!CI48 -> #VALUE! | K48: =EXPORT!CJ48 -> #VALUE! | L48: =EXPORT!CK48 -> #VALUE! | M48: =EXPORT!CL48 -> 0 | N48: =EXPORT!CM48 -> 0
A49: ITALY | B49: IT | D49: 14 | E49: Bergamo | F49: =EXPORT!CE49 -> #N/A | G49: =EXPORT!CF49 -> 201.69075 | H49: =EXPORT!CG49 -> 198.25031 | I49: =EXPORT!CH49 -> 403.19467 | J49: =EXPORT!CI49 -> 273.85376 | K49: =EXPORT!CJ49 -> #VALUE! | L49: =EXPORT!CK49 -> 339.30831 | M49: =EXPORT!CL49 -> 0 | N49: =EXPORT!CM49 -> 0
E50: Salerno | F50: =EXPORT!CE50 -> #N/A | G50: =EXPORT!CF50 -> 324.41802 | H50: =EXPORT!CG50 -> 320.97758 | I50: =EXPORT!CH50 -> 272.51285 | J50: =EXPORT!CI50 -> 202.03558 | K50: =EXPORT!CJ50 -> #VALUE! | L50: =EXPORT!CK50 -> 238.05831 | M50: =EXPORT!CL50 -> 0 | N50: =EXPORT!CM50 -> 0
A52: Other | B52: OT | C52: - | D52: - | E52: Dalian | F52: =EXPORT!CE52 -> 0 | G52: =EXPORT!CF52 -> 0 | H52: =EXPORT!CG52 -> 0 | I52: =EXPORT!CH52 -> 0 | J52: =EXPORT!CI52 -> 0 | K52: =EXPORT!CJ52 -> 0 | L52: =EXPORT!CK52 -> 0 | M52: =EXPORT!CL52 -> 0 | ... P52: =EXPORT!CO52 -> 0

Sheet SEAM
D1: Origin Warehouse | O1: Inland Logistics | T1: Consolidation | Y1: Outbound Logistics | AC1: Documentation | AI1: CIF | AO1: Cert Costs | AR1: Terms Total
A2: City | B2: State | C2: Combine | D2: Terms | E2: Receiving | F2: Load Out | G2: Compression | H2: Class | I2: Marking | J2: Storage | K2: Interest | L2: Origin Commission | M2: Total Equity | N2: Total Origin | O2: Flatbed | P2: Late Fee | Q2: Transit Truck | S2: Total Inland | T2: Block Handling | U2: Storage | V2: Interest | X2: Total Consol | Y2: Dray | Z2: Ocean | AB2: Total Out | AC2: Sight LC | AD2: Forwarding | AE2: Controlling | AF2: Insurance | AH2: Total Doc | AI2: Destination Comission | AJ2: High Seas | AK2: Qclaim | AL2: Interest | AN2: Total CIF | AO2: USDA | AP2: ICE | AQ2: Total CERT | AR2: Cash | AS2: Equity
A3: Jackson | B3: NC | C3: =A3&B3 -> JacksonNC | D3: =VLOOKUP(A:A,PTS!C:R,6,FALSE) -> 1 | E3: {=AVERAGE(_xlfn._xlws.FILTER(PTS!I:I, (PTS!$C:$C=A3) * ISNUMBER(PTS!I:I)))} -> 25 | F3: {=AVERAGE(_xlfn._xlws.FILTER(PTS!J:J, (PTS!$C:$C=A3) * ISNUMBER(PTS!J:J)))} -> 212.33333 | G3: {=AVERAGE(_xlfn._xlws.FILTER(PTS!K:K, (PTS!$C:$C=A3) * ISNUMBER(PTS!K:K)))} -> 0 | H3: {=AVERAGE(_xlfn._xlws.FILTER(PTS!L:L, (PTS!$C:$C=A3) * ISNUMBER(PTS!L:L)))} -> 40.333333 | I3: {=AVERAGE(_xlfn._xlws.FILTER(PTS!M:M, (PTS!$C:$C=A3) * ISNUMBER(PTS!M:M)))} -> 1.6666667 | J3: {=AVERAGE(_xlfn._xlws.FILTER(PTS!N:N, (PTS!$C:$C=A3) * ISNUMBER(PTS!N:N)))} -> 67.333333 | K3: {=AVERAGE(_xlfn._xlws.FILTER(PTS!O:O, (PTS!$C:$C=A3) * ISNUMBER(PTS!O:O)))} -> 37.916667 | L3: {=AVERAGE(_xlfn._xlws.FILTER(PTS!P:P, (PTS!$C:$C=A3) * ISNUMBER(PTS!P:P)))} -> 0 | M3: =E3+F3+G3+H3+I3+J3+K3+L3 -> 384.58333 | N3: =IF(D3=1,SUM(J3),IF(D3=2,SUM(G3,J3),IF(D3=3,SUM(F3,G3,H3,J3),IF(D3=4,SUM(H3),"ERROR"))))+K3 -> 105.25 | O3: {=AVERAGE(_xlfn._xlws.FILTER(PTS!S:S, (PTS!$C:$C=A3) * ISNUMBER(PTS!S:S)))} -> 0 | P3: {=AVERAGE(_xlfn._xlws.FILTER(PTS!T:T, (PTS!$C:$C=A3) * ISNUMBER(PTS!T:T)))} -> 0 | Q3: {=AVERAGE(_xlfn._xlws.FILTER(PTS!U:U, (PTS!$C:$C=A3) * ISNUMBER(PTS!U:U)))} -> 316.3642 | S3: =O3+P3+Q3+R3 -> 316.3642 | T3: {=AVERAGE(_xlfn._xlws.FILTER(PTS!X:X, (PTS!$C:$C=A3) * ISNUMBER(PTS!X:X)))} -> 50.666667 | U3: {=AVERAGE(_xlfn._xlws.FILTER(PTS!Y:Y, (PTS!$C:$C=A3) * ISNUMBER(PTS!Y:Y)))} -> 39.2 | V3: {=AVERAGE(_xlfn._xlws.FILTER(PTS!Z:Z, (PTS!$C:$C=A3) * ISNUMBER(PTS!Z:Z)))} -> 26.25 | X3: =T3+U3+V3+W3 -> 116.11667 | Y3: {=AVERAGE(_xlfn._xlws.FILTER(PTS!AC:AC, (PTS!$C:$C=A3) * ISNUMBER(PTS!AC:AC)))} -> 134.09091 | Z3: {=AVERAGE(_xlfn._xlws.FILTER(PTS!AD:AD, (PTS!$C:$C=A3) * ISNUMBER(PTS!AD:AD)))} -> 157.5 | AB3: =Y3+Z3+AA3 -> 291.59091 | AC3: {=AVERAGE(_xlfn._xlws.FILTER(PTS!AG:AG, (PTS!$C:$C=A3) * ISNUMBER(PTS!AG:AG)))} -> 28.8143 | AD3: {=AVERAGE(_xlfn._xlws.FILTER(PTS!AH:AH, (PTS!$C:$C=A3) * ISNUMBER(PTS!AH:AH)))} -> 6.9731405 | AE3: {=AVERAGE(_xlfn._xlws.FILTER(PTS!AI:AI, (PTS!$C:$C=A3) * ISNUMBER(PTS!AI:AI)))} -> 12.587317 | AF3: {=AVERAGE(_xlfn._xlws.FILTER(PTS!AJ:AJ, (PTS!$C:$C=A3) * ISNUMBER(PTS!AJ:AJ)))} -> 6.7352 | AH3: =AC3+AD3+AE3+AF3+AG3 -> 55.109958 | AI3: {=AVERAGE(_xlfn._xlws.FILTER(PTS!AM:AM, (PTS!$C:$C=A3) * ISNUMBER(PTS!AM:AM)))} -> 80 | AJ3: {=AVERAGE(_xlfn._xlws.FILTER(PTS!AN:AN, (PTS!$C:$C=A3) * ISNUMBER(PTS!AN:AN)))} -> 26.178082 | AK3: {=AVERAGE(_xlfn._xlws.FILTER(PTS!AO:AO, (PTS!$C:$C=A3) * ISNUMBER(PTS!AO:AO)))} -> 0 | AN3: =AI3+AJ3+AK3+AL3+AM3 -> 106.17808 | AR3: =N3+S3+X3+AB3+AH3+AN3 -> 990.60982 | AS3: =M3+S3+X3+AB3+AH3+AN3 -> 1269.9432
A4: Jackson | B4: TN | C4: =A4&B4 -> JacksonTN | D4: =VLOOKUP(A:A,PTS!C:R,6,FALSE) -> 1 | E4: {=AVERAGE(_xlfn._xlws.FILTER(PTS!I:I, (PTS!$C:$C=A4) * ISNUMBER(PTS!I:I)))} -> 25 | F4: {=AVERAGE(_xlfn._xlws.FILTER(PTS!J:J, (PTS!$C:$C=A4) * ISNUMBER(PTS!J:J)))} -> 212.33333 | G4: {=AVERAGE(_xlfn._xlws.FILTER(PTS!K:K, (PTS!$C:$C=A4) * ISNUMBER(PTS!K:K)))} -> 0 | H4: {=AVERAGE(_xlfn._xlws.FILTER(PTS!L:L, (PTS!$C:$C=A4) * ISNUMBER(PTS!L:L)))} -> 40.333333 | I4: {=AVERAGE(_xlfn._xlws.FILTER(PTS!M:M, (PTS!$C:$C=A4) * ISNUMBER(PTS!M:M)))} -> 1.6666667 | J4: {=AVERAGE(_xlfn._xlws.FILTER(PTS!N:N, (PTS!$C:$C=A4) * ISNUMBER(PTS!N:N)))} -> 67.333333 | K4: {=AVERAGE(_xlfn._xlws.FILTER(PTS!O:O, (PTS!$C:$C=A4) * ISNUMBER(PTS!O:O)))} -> 37.916667 | L4: {=AVERAGE(_xlfn._xlws.FILTER(PTS!P:P, (PTS!$C:$C=A4) * ISNUMBER(PTS!P:P)))} -> 0 | M4: =E4+F4+G4+H4+I4+J4+K4+L4 -> 384.58333 | N4: =IF(D4=1,SUM(J4),IF(D4=2,SUM(G4,J4),IF(D4=3,SUM(F4,G4,H4,J4),IF(D4=4,SUM(H4),"ERROR"))))+K4 -> 105.25 | O4: {=AVERAGE(_xlfn._xlws.FILTER(PTS!S:S, (PTS!$C:$C=A4) * ISNUMBER(PTS!S:S)))} -> 0 | P4: {=AVERAGE(_xlfn._xlws.FILTER(PTS!T:T, (PTS!$C:$C=A4) * ISNUMBER(PTS!T:T)))} -> 0 | Q4: {=AVERAGE(_xlfn._xlws.FILTER(PTS!U:U, (PTS!$C:$C=A4) * ISNUMBER(PTS!U:U)))} -> 316.3642 | S4: =O4+P4+Q4+R4 -> 316.3642 | T4: {=AVERAGE(_xlfn._xlws.FILTER(PTS!X:X, (PTS!$C:$C=A4) * ISNUMBER(PTS!X:X)))} -> 50.666667 | U4: {=AVERAGE(_xlfn._xlws.FILTER(PTS!Y:Y, (PTS!$C:$C=A4) * ISNUMBER(PTS!Y:Y)))} -> 39.2 | V4: {=AVERAGE(_xlfn._xlws.FILTER(PTS!Z:Z, (PTS!$C:$C=A4) * ISNUMBER(PTS!Z:Z)))} -> 26.25 | X4: =T4+U4+V4+W4 -> 116.11667 | Y4: {=AVERAGE(_xlfn._xlws.FILTER(PTS!AC:AC, (PTS!$C:$C=A4) * ISNUMBER(PTS!AC:AC)))} -> 134.09091 | Z4: {=AVERAGE(_xlfn._xlws.FILTER(PTS!AD:AD, (PTS!$C:$C=A4) * ISNUMBER(PTS!AD:AD)))} -> 157.5 | AB4: =Y4+Z4+AA4 -> 291.59091 | AC4: {=AVERAGE(_xlfn._xlws.FILTER(PTS!AG:AG, (PTS!$C:$C=A4) * ISNUMBER(PTS!AG:AG)))} -> 28.8143 | AD4: {=AVERAGE(_xlfn._xlws.FILTER(PTS!AH:AH, (PTS!$C:$C=A4) * ISNUMBER(PTS!AH:AH)))} -> 6.9731405 | AE4: {=AVERAGE(_xlfn._xlws.FILTER(PTS!AI:AI, (PTS!$C:$C=A4) * ISNUMBER(PTS!AI:AI)))} -> 12.587317 | AF4: {=AVERAGE(_xlfn._xlws.FILTER(PTS!AJ:AJ, (PTS!$C:$C=A4) * ISNUMBER(PTS!AJ:AJ)))} -> 6.7352 | AH4: =AC4+AD4+AE4+AF4+AG4 -> 55.109958 | AI4: {=AVERAGE(_xlfn._xlws.FILTER(PTS!AM:AM, (PTS!$C:$C=A4) * ISNUMBER(PTS!AM:AM)))} -> 80 | AJ4: {=AVERAGE(_xlfn._xlws.FILTER(PTS!AN:AN, (PTS!$C:$C=A4) * ISNUMBER(PTS!AN:AN)))} -> 26.178082 | AK4: {=AVERAGE(_xlfn._xlws.FILTER(PTS!AO:AO, (PTS!$C:$C=A4) * ISNUMBER(PTS!AO:AO)))} -> 0 | AN4: =AI4+AJ4+AK4+AL4+AM4 -> 106.17808 | AR4: =N4+S4+X4+AB4+AH4+AN4 -> 990.60982 | AS4: =M4+S4+X4+AB4+AH4+AN4 -> 1269.9432
